Workbook
Name A部门L1: [1]员工信息统计表!$I1

Sheet 汇总
A1: 创想悦动2026年7月工资汇总表
A2: 分类 | B2: 部门 | C2: 人数 | D2: 基本工资 | E2: 绩效工资 | F2: 岗位津贴 | G2: 节日福利 | H2: 通讯补贴 | I2: 考勤扣款 | J2: 其他扣款 | K2: 加班费 | L2: 绩效奖金 | M2: 其他奖金 | N2: 伙食补贴 | O2: 住房补贴 | P2: 司机补贴 | Q2: 专利奖 | R2: 其他补发 | S2: 补发合计 | T2: 应付工资 | U2: 借款逾期扣款 | V2: 房租水电 | W2: 房租水电1 | X2: 其他代扣款 | Y2: 扣款合计 | Z2: 养老保险 | AA2: 医疗保险 | AB2: 失业保险 | AC2: 住房公积金 | AD2: 所得税 | AE2: 实发工资
A3: 销售 | B3: 创想悦动-销售 | C3: =SUMIF(工资表明细!$J$2:$J$82,$B3,工资表明细!L$2:L$82) -> 14 | D3: =SUMIF(工资表明细!$J$3:$J$82,$B3,工资表明细!P$3:P$82) -> 246000 | E3: =SUMIF(工资表明细!$J$3:$J$82,$B3,工资表明细!Q$3:Q$82) -> 0 | F3: =SUMIF(工资表明细!$J$3:$J$82,$B3,工资表明细!R$3:R$82) -> 0 | G3: =SUMIF(工资表明细!$J$3:$J$82,$B3,工资表明细!S$3:S$82) -> 0 | H3: =SUMIF(工资表明细!$J$3:$J$82,$B3,工资表明细!T$3:T$82) -> 0 | I3: =SUMIF(工资表明细!$J$3:$J$82,$B3,工资表明细!U$3:U$82) -> 6206.9 | J3: =SUMIF(工资表明细!$J$3:$J$82,$B3,工资表明细!V$3:V$82) -> 0 | K3: =SUMIF(工资表明细!$J$3:$J$82,$B3,工资表明细!W$3:W$82) -> 0 | ... AC3: =SUMIF(工资表明细!$J$3:$J$82,$B3,工资表明细!AO$3:AO$82) -> 20480 | AD3: =SUMIF(工资表明细!$J$3:$J$82,$B3,工资表明细!BE$3:BE$82) -> 7179.72 | AE3: =SUMIF(工资表明细!$J$3:$J$82,$B3,工资表明细!BF$3:BF$82) -> 190569.54
B4: 小计 | C4: =SUM(C3:C3) -> 14 | D4: =SUM(D3:D3) -> 246000 | E4: =SUM(E3:E3) -> 0 | F4: =SUM(F3:F3) -> 0 | G4: =SUM(G3:G3) -> 0 | H4: =SUM(H3:H3) -> 0 | I4: =SUM(I3:I3) -> 6206.9 | J4: =SUM(J3:J3) -> 0 | ... AE4: =SUM(AE3:AE3) -> 190569.54
A5: 研发 | B5: 创想悦动-研发 | C5: =SUMIF(工资表明细!$J$2:$J$82,$B5,工资表明细!L$2:L$82) -> 55 | D5: =SUMIF(工资表明细!$J$3:$J$82,$B5,工资表明细!P$3:P$82) -> 1263300 | E5: =SUMIF(工资表明细!$J$3:$J$82,$B5,工资表明细!Q$3:Q$82) -> 0 | F5: =SUMIF(工资表明细!$J$3:$J$82,$B5,工资表明细!R$3:R$82) -> 0 | G5: =SUMIF(工资表明细!$J$3:$J$82,$B5,工资表明细!S$3:S$82) -> 0 | H5: =SUMIF(工资表明细!$J$3:$J$82,$B5,工资表明细!T$3:T$82) -> 0 | I5: =SUMIF(工资表明细!$J$3:$J$82,$B5,工资表明细!U$3:U$82) -> 43287.36 | J5: =SUMIF(工资表明细!$J$3:$J$82,$B5,工资表明细!V$3:V$82) -> 0 | K5: =SUMIF(工资表明细!$J$3:$J$82,$B5,工资表明细!W$3:W$82) -> 0 | ... AC5: =SUMIF(工资表明细!$J$3:$J$82,$B5,工资表明细!AO$3:AO$82) -> 88863.6 | AD5: =SUMIF(工资表明细!$J$3:$J$82,$B5,工资表明细!BE$3:BE$82) -> 85237.98 | AE5: =SUMIF(工资表明细!$J$3:$J$82,$B5,工资表明细!BF$3:BF$82) -> 932559.11
B6: 小计 | C6: =SUM(C5:C5) -> 55 | D6: =SUM(D5:D5) -> 1263300 | E6: =SUM(E5:E5) -> 0 | F6: =SUM(F5:F5) -> 0 | G6: =SUM(G5:G5) -> 0 | H6: =SUM(H5:H5) -> 0 | I6: =SUM(I5:I5) -> 43287.36 | J6: =SUM(J5:J5) -> 0 | ... AE6: =SUM(AE5:AE5) -> 932559.11
A7: 职能 | B7: 创想悦动-管理 | C7: =SUMIF(工资表明细!$J$2:$J$82,$B7,工资表明细!L$2:L$82) -> 9 | D7: =SUMIF(工资表明细!$J$3:$J$82,$B7,工资表明细!P$3:P$82) -> 281000 | E7: =SUMIF(工资表明细!$J$3:$J$82,$B7,工资表明细!Q$3:Q$82) -> 0 | F7: =SUMIF(工资表明细!$J$3:$J$82,$B7,工资表明细!R$3:R$82) -> 0 | G7: =SUMIF(工资表明细!$J$3:$J$82,$B7,工资表明细!S$3:S$82) -> 0 | H7: =SUMIF(工资表明细!$J$3:$J$82,$B7,工资表明细!T$3:T$82) -> 0 | I7: =SUMIF(工资表明细!$J$3:$J$82,$B7,工资表明细!U$3:U$82) -> 0 | J7: =SUMIF(工资表明细!$J$3:$J$82,$B7,工资表明细!V$3:V$82) -> 0 | K7: =SUMIF(工资表明细!$J$3:$J$82,$B7,工资表明细!W$3:W$82) -> 0 | ... AC7: =SUMIF(工资表明细!$J$3:$J$82,$B7,工资表明细!AO$3:AO$82) -> 21739.5 | AD7: =SUMIF(工资表明细!$J$3:$J$82,$B7,工资表明细!BE$3:BE$82) -> 34577.71 | AE7: =SUMIF(工资表明细!$J$3:$J$82,$B7,工资表明细!BF$3:BF$82) -> 206836.83
B8: 小计 | C8: =SUM(C7:C7) -> 9 | D8: =SUM(D7:D7) -> 281000 | E8: =SUM(E7:E7) -> 0 | F8: =SUM(F7:F7) -> 0 | G8: =SUM(G7:G7) -> 0 | H8: =SUM(H7:H7) -> 0 | I8: =SUM(I7:I7) -> 0 | J8: =SUM(J7:J7) -> 0 | ... AE8: =SUM(AE7:AE7) -> 206836.83
A9: 总计 | C9: =C4+C6+C8 -> 78 | D9: =D4+D6+D8 -> 1790300 | E9: =E4+E6+E8 -> 0 | F9: =F4+F6+F8 -> 0 | G9: =G4+G6+G8 -> 0 | H9: =H4+H6+H8 -> 0 | I9: =I4+I6+I8 -> 49494.26 | J9: =J4+J6+J8 -> 0 | ... AE9: =AE4+AE6+AE8 -> 1329965.5
C10: =C9-工资表明细!L83 -> 0 | D10: =D9-工资表明细!P83 -> 0 | E10: =E9-工资表明细!Q83 -> 0 | F10: =F9-工资表明细!R83 -> 0 | G10: =G9-工资表明细!S83 -> 0 | H10: =H9-工资表明细!T83 -> 0 | I10: =I9-工资表明细!U83 -> 0 | J10: =J9-工资表明细!V83 -> 0 | K10: =K9-工资表明细!W83 -> 0 | ... AC10: =AC9-工资表明细!AO83 -> 0 | AD10: =AD9-工资表明细!BE83 -> 0 | AE10: =AE9-工资表明细!BF83 -> 0

Sheet 环比变动
A1: 2026年7月创想悦动工资环比变动情况
A2: 年月 | B2: 项目 | C2: 人数 | D2: 基础工资 | E2: 绩效工资 | F2: 岗位津贴 | G2: 节日福利 | H2: 通讯补贴 | I2: 考勤扣款 | J2: 其他扣款 | K2: 加班费 | L2: 绩效奖金 | M2: 其他奖金 | N2: 伙食补贴 | O2: 住房补贴 | P2: 司机补贴 | Q2: 专利奖 | R2: 其他补发 | S2: 补发合计 | T2: 应付工资 | U2: 借款逾期扣款 | V2: 水电费 | W2: 房租 | X2: 其他代扣款 | Y2: 扣款合计 | Z2: 社保费 | AA2: 住房公积金 | AB2: 个人所得税 | AC2: 实发工资
A3: 46204 | B3: 职能 | C3: =汇总!C8 -> 9 | D3: =汇总!D8 -> 281000 | E3: =汇总!E8 -> 0 | F3: =汇总!F8 -> 0 | G3: =汇总!G8 -> 0 | H3: =汇总!H8 -> 0 | I3: =汇总!I8 -> 0 | J3: =汇总!J8 -> 0 | ... Y3: =汇总!Y8 -> -140.24 | Z3: =汇总!Z8+汇总!AA8+汇总!AB8 -> 17986.2 | AA3: =汇总!AC8 -> 21739.5 | AB3: =汇总!AD8 -> 34577.71 | AC3: =汇总!AE8 -> 206836.83
B4: 研发 | C4: =汇总!C6 -> 55 | D4: =汇总!D6 -> 1263300 | E4: =汇总!E6 -> 0 | F4: =汇总!F6 -> 0 | G4: =汇总!G6 -> 0 | H4: =汇总!H6 -> 0 | I4: =汇总!I6 -> 43287.36 | J4: =汇总!J6 -> 0 | ... Y4: =汇总!Y6 -> 1280.25 | Z4: =汇总!Z6+汇总!AA6+汇总!AB6 -> 112871.7 | AA4: =汇总!AC6 -> 88863.6 | AB4: =汇总!AD6 -> 85237.98 | AC4: =汇总!AE6 -> 932559.11
B5: 销售 | C5: =汇总!C4 -> 14 | D5: =汇总!D4 -> 246000 | E5: =汇总!E4 -> 0 | F5: =汇总!F4 -> 0 | G5: =汇总!G4 -> 0 | H5: =汇总!H4 -> 0 | I5: =汇总!I4 -> 6206.9 | J5: =汇总!J4 -> 0 | ... Y5: =汇总!Y4 -> -1840 | Z5: =汇总!Z4+汇总!AA4+汇总!AB4 -> 23403.84 | AA5: =汇总!AC4 -> 20480 | AB5: =汇总!AD4 -> 7179.72 | AC5: =汇总!AE4 -> 190569.54
B6: 合计 | C6: =SUM(C3:C5) -> 78 | D6: =SUM(D3:D5) -> 1790300 | E6: =SUM(E3:E5) -> 0 | F6: =SUM(F3:F5) -> 0 | G6: =SUM(G3:G5) -> 0 | H6: =SUM(H3:H5) -> 0 | I6: =SUM(I3:I5) -> 49494.26 | J6: =SUM(J3:J5) -> 0 | ... AC6: =SUM(AC3:AC5) -> 1329965.5
A7: 46174 | B7: 职能 | C7: 9 | D7: 281000 | E7: 0 | F7: 0 | G7: 0 | H7: 0 | I7: 1379.31 | J7: 0 | K7: 0 | L7: 0 | M7: 0 | N7: 0 | O7: 0 | P7: 0 | Q7: 0 | R7: 1800 | S7: 1800 | T7: 281420.69 | U7: 0 | V7: 0 | W7: 0 | X7: 1800 | Y7: 1800 | Z7: 17961.91 | AA7: 13487.7 | AB7: 34488.18 | AC7: 213682.9
B8: 研发 | C8: 55 | D8: 1244300 | E8: 0 | F8: 0 | G8: 0 | H8: 0 | I8: 145206.91 | J8: 0 | K8: 0 | L8: 0 | M8: 0 | N8: 0 | O8: 0 | P8: 0 | Q8: 0 | R8: 10800 | S8: 10800 | T8: 1109893.1 | U8: 0 | V8: 0 | W8: 0 | X8: 10800 | Y8: 10800 | Z8: 102917.69 | AA8: 66257.7 | AB8: 73910.59 | AC8: 856007.11
B9: 销售 | C9: 12 | D9: 214000 | E9: 0 | F9: 0 | G9: 0 | H9: 0 | I9: 34344.83 | J9: 0 | K9: 5655.17 | L9: 0 | M9: 0 | N9: 0 | O9: 0 | P9: 0 | Q9: 0 | R9: 2800 | S9: 8455.17 | T9: 188110.34 | U9: 0 | V9: 0 | W9: 0 | X9: 2800 | Y9: 2800 | Z9: 18119.92 | AA9: 10500 | AB9: 6181.46 | AC9: 150508.96
B10: 合计 | C10: =SUM(C7:C9) -> 76 | D10: =SUM(D7:D9) -> 1739300 | E10: =SUM(E7:E9) -> 0 | F10: =SUM(F7:F9) -> 0 | G10: =SUM(G7:G9) -> 0 | H10: =SUM(H7:H9) -> 0 | I10: =SUM(I7:I9) -> 180931.05 | J10: =SUM(J7:J9) -> 0 | ... AC10: =SUM(AC7:AC9) -> 1220199
A11: 变动 | B11: 职能 | C11: =C3-C7 -> 0 | D11: =D3-D7 -> 0 | E11: =E3-E7 -> 0 | F11: =F3-F7 -> 0 | G11: =G3-G7 -> 0 | H11: =H3-H7 -> 0 | I11: =I3-I7 -> -1379.31 | J11: =J3-J7 -> 0 | ... AC11: =AC3-AC7 -> -6846.07
B12: 研发 | C12: =C4-C8 -> 0 | D12: =D4-D8 -> 19000 | E12: =E4-E8 -> 0 | F12: =F4-F8 -> 0 | G12: =G4-G8 -> 0 | H12: =H4-H8 -> 0 | I12: =I4-I8 -> -101919.55 | J12: =J4-J8 -> 0 | ... AC12: =AC4-AC8 -> 76552
B13: 销售 | C13: =C5-C9 -> 2 | D13: =D5-D9 -> 32000 | E13: =E5-E9 -> 0 | F13: =F5-F9 -> 0 | G13: =G5-G9 -> 0 | H13: =H5-H9 -> 0 | I13: =I5-I9 -> -28137.93 | J13: =J5-J9 -> 0 | ... AC13: =AC5-AC9 -> 40060.58
B14: 合计 | C14: =SUM(C11:C13) -> 2 | D14: =SUM(D11:D13) -> 51000 | E14: =SUM(E11:E13) -> 0 | F14: =SUM(F11:F13) -> 0 | G14: =SUM(G11:G13) -> 0 | H14: =SUM(H11:H13) -> 0 | I14: =SUM(I11:I13) -> -131436.79 | J14: =SUM(J11:J13) -> 0 | ... AC14: =SUM(AC11:AC13) -> 109766.51
B17: 检查 | C17: =C6-工资表明细!L83 -> 0 | D17: =D6-工资表明细!P83 -> 0 | E17: =E6-工资表明细!Q83 -> 0 | F17: =F6-工资表明细!R83 -> 0 | G17: =G6-工资表明细!S83 -> 0 | H17: =H6-工资表明细!T83 -> 0 | I17: =I6-工资表明细!U83 -> 0 | J17: =J6-工资表明细!V83 -> 0 | K17: =K6-工资表明细!W83 -> 0 | ... Y17: =Y6-工资表明细!AK83 -> 0 | Z17: =Z6-工资表明细!AL83-工资表明细!AM83-工资表明细!AN83 -> -1.6370905e-11 | AA17: =AA6-工资表明细!AO83 -> 0 | AB17: =AB6-工资表明细!BE83 -> 0 | AC17: =AC6-工资表明细!BF83 -> 0

Sheet 同比变动
A1: 2025年8月创想悦动工资同比变动情况
A2: 年月 | B2: 项目 | C2: 人数 | D2: 基础工资 | E2: 绩效工资 | F2: 岗位津贴 | G2: 节日福利 | H2: 通讯补贴 | I2: 考勤扣款 | J2: 其他扣款 | K2: 加班费 | L2: 绩效奖金 | M2: 其他奖金 | N2: 伙食补贴 | O2: 住房补贴 | P2: 司机补贴 | Q2: 专利奖 | R2: 其他补发 | S2: 补发合计 | T2: 应付工资 | U2: 借款逾期扣款 | V2: 水电费 | W2: 房租 | X2: 其他代扣款 | Y2: 扣款合计 | Z2: 社保费 | AA2: 住房公积金 | AB2: 个人所得税 | AC2: 实发工资
A3: 46023 | B3: 职能 | C3: =环比变动!C3 -> 9 | D3: =环比变动!D3 -> 281000 | E3: =环比变动!E3 -> 0 | F3: =环比变动!F3 -> 0 | G3: =环比变动!G3 -> 0 | H3: =环比变动!H3 -> 0 | I3: =环比变动!I3 -> 0 | J3: =环比变动!J3 -> 0 | ... AC3: =环比变动!AC3 -> 206836.83
B4: 研发 | C4: =环比变动!C4 -> 55 | D4: =环比变动!D4 -> 1263300 | E4: =环比变动!E4 -> 0 | F4: =环比变动!F4 -> 0 | G4: =环比变动!G4 -> 0 | H4: =环比变动!H4 -> 0 | I4: =环比变动!I4 -> 43287.36 | J4: =环比变动!J4 -> 0 | ... AC4: =环比变动!AC4 -> 932559.11
B5: 销售 | C5: =环比变动!C5 -> 14 | D5: =环比变动!D5 -> 246000 | E5: =环比变动!E5 -> 0 | F5: =环比变动!F5 -> 0 | G5: =环比变动!G5 -> 0 | H5: =环比变动!H5 -> 0 | I5: =环比变动!I5 -> 6206.9 | J5: =环比变动!J5 -> 0 | ... AC5: =环比变动!AC5 -> 190569.54
B6: 合计 | C6: =SUM(C3:C5) -> 78 | D6: =SUM(D3:D5) -> 1790300 | E6: =SUM(E3:E5) -> 0 | F6: =SUM(F3:F5) -> 0 | G6: =SUM(G3:G5) -> 0 | H6: =SUM(H3:H5) -> 0 | I6: =SUM(I3:I5) -> 49494.26 | J6: =SUM(J3:J5) -> 0 | ... AC6: =SUM(AC3:AC5) -> 1329965.5
A7: 45658 | B7: 职能 | C7: 0 | D7: 0 | E7: 0 | F7: 0 | G7: 0 | H7: 0 | I7: 0 | J7: 0 | K7: 0 | L7: 0 | M7: 0 | N7: 0 | O7: 0 | P7: 0 | Q7: 0 | R7: 0 | S7: 0 | T7: 0
B8: 研发 | C8: 0 | D8: 0 | E8: 0 | F8: 0 | G8: 0 | H8: 0 | I8: 0 | J8: 0 | K8: 0 | L8: 0 | M8: 0 | N8: 0 | O8: 0 | P8: 0 | Q8: 0 | R8: 0 | S8: 0 | T8: 0
B9: 销售 | C9: 0 | D9: 0 | E9: 0 | F9: 0 | G9: 0 | H9: 0 | I9: 0 | J9: 0 | K9: 0 | L9: 0 | M9: 0 | N9: 0 | O9: 0 | P9: 0 | Q9: 0 | R9: 0 | S9: 0 | T9: 0
B10: 合计 | C10: =SUM(C7:C9) -> 0 | D10: =SUM(D7:D9) -> 0 | E10: =SUM(E7:E9) -> 0 | F10: =SUM(F7:F9) -> 0 | G10: =SUM(G7:G9) -> 0 | H10: =SUM(H7:H9) -> 0 | I10: =SUM(I7:I9) -> 0 | J10: =SUM(J7:J9) -> 0 | ... AC10: =SUM(AC7:AC9) -> 0
A11: 变动 | B11: 职能 | C11: =C3-C7 -> 9 | D11: =D3-D7 -> 281000 | E11: =E3-E7 -> 0 | F11: =F3-F7 -> 0 | G11: =G3-G7 -> 0 | H11: =H3-H7 -> 0 | I11: =I3-I7 -> 0 | J11: =J3-J7 -> 0 | ... AC11: =AC3-AC7 -> 206836.83
B12: 研发 | C12: =C4-C8 -> 55 | D12: =D4-D8 -> 1263300 | E12: =E4-E8 -> 0 | F12: =F4-F8 -> 0 | G12: =G4-G8 -> 0 | H12: =H4-H8 -> 0 | I12: =I4-I8 -> 43287.36 | J12: =J4-J8 -> 0 | ... AC12: =AC4-AC8 -> 932559.11
B13: 销售 | C13: =C5-C9 -> 14 | D13: =D5-D9 -> 246000 | E13: =E5-E9 -> 0 | F13: =F5-F9 -> 0 | G13: =G5-G9 -> 0 | H13: =H5-H9 -> 0 | I13: =I5-I9 -> 6206.9 | J13: =J5-J9 -> 0 | ... AC13: =AC5-AC9 -> 190569.54
B14: 合计 | C14: =SUM(C11:C13) -> 78 | D14: =SUM(D11:D13) -> 1790300 | E14: =SUM(E11:E13) -> 0 | F14: =SUM(F11:F13) -> 0 | G14: =SUM(G11:G13) -> 0 | H14: =SUM(H11:H13) -> 0 | I14: =SUM(I11:I13) -> 49494.26 | J14: =SUM(J11:J13) -> 0 | ... AC14: =SUM(AC11:AC13) -> 1329965.5

Sheet 各公司汇总
A1: 深圳创想悦动科技有限公司2026年7月工资表
A2: 一级成本中心 | B2: 成本中心编码 | C2: 人数 | D2: 基本工资 | E2: 绩效工资 | F2: 岗位津贴 | G2: 过节费 | H2: 通讯补贴 | I2: 考勤扣款 | J2: 其他扣款 | K2: 加班费 | L2: 绩效奖金 | M2: 其他奖金 | N2: 伙食补贴 | O2: 住房补贴 | P2: 司机补贴 | Q2: 专利奖 | R2: 其他补发 | S2: 补发合计 | T2: 应付工资 | U2: 借款逾期扣款 | V2: 房租水电 | W2: 房租水电1 | X2: 其他税后扣款 | Y2: 扣款合计 | Z2: 养老保险 | AA2: 医疗保险 | AB2: 失业保险 | AC2: 住房公积金 | AD2: 所得税 | AE2: 实发工资
A3: 创想悦动-管理 | B3: 创想悦动-管理 | C3: =SUMIF(工资表明细!$M$3:$M$85,$B3,工资表明细!$L$3:$L$85) -> 9 | D3: =SUMIF(工资表明细!$M$3:$M$82,$B3,工资表明细!P$3:P$82) -> 281000 | E3: =SUMIF(工资表明细!$M$3:$M$82,$B3,工资表明细!Q$3:Q$82) -> 0 | F3: =SUMIF(工资表明细!$M$3:$M$82,$B3,工资表明细!R$3:R$82) -> 0 | G3: =SUMIF(工资表明细!$M$3:$M$82,$B3,工资表明细!S$3:S$82) -> 0 | H3: =SUMIF(工资表明细!$M$3:$M$82,$B3,工资表明细!T$3:T$82) -> 0 | I3: =SUMIF(工资表明细!$M$3:$M$82,$B3,工资表明细!U$3:U$82) -> 0 | J3: =SUMIF(工资表明细!$M$3:$M$82,$B3,工资表明细!V$3:V$82) -> 0 | K3: =SUMIF(工资表明细!$M$3:$M$82,$B3,工资表明细!W$3:W$82) -> 0 | ... AC3: =SUMIF(工资表明细!$M$3:$M$82,$B3,工资表明细!AO$3:AO$82) -> 21739.5 | AD3: =SUMIF(工资表明细!$M$3:$M$82,$B3,工资表明细!BE$3:BE$82) -> 34577.71 | AE3: =SUMIF(工资表明细!$M$3:$M$82,$B3,工资表明细!BF$3:BF$82) -> 206836.83
A4: 创想悦动-研发 | B4: 创想悦动-研发 | C4: =SUMIF(工资表明细!$M$3:$M$85,$B4,工资表明细!$L$3:$L$85) -> 55 | D4: =SUMIF(工资表明细!$M$3:$M$82,$B4,工资表明细!P$3:P$82) -> 1263300 | E4: =SUMIF(工资表明细!$M$3:$M$82,$B4,工资表明细!Q$3:Q$82) -> 0 | F4: =SUMIF(工资表明细!$M$3:$M$82,$B4,工资表明细!R$3:R$82) -> 0 | G4: =SUMIF(工资表明细!$M$3:$M$82,$B4,工资表明细!S$3:S$82) -> 0 | H4: =SUMIF(工资表明细!$M$3:$M$82,$B4,工资表明细!T$3:T$82) -> 0 | I4: =SUMIF(工资表明细!$M$3:$M$82,$B4,工资表明细!U$3:U$82) -> 43287.36 | J4: =SUMIF(工资表明细!$M$3:$M$82,$B4,工资表明细!V$3:V$82) -> 0 | K4: =SUMIF(工资表明细!$M$3:$M$82,$B4,工资表明细!W$3:W$82) -> 0 | ... AC4: =SUMIF(工资表明细!$M$3:$M$82,$B4,工资表明细!AO$3:AO$82) -> 88863.6 | AD4: =SUMIF(工资表明细!$M$3:$M$82,$B4,工资表明细!BE$3:BE$82) -> 85237.98 | AE4: =SUMIF(工资表明细!$M$3:$M$82,$B4,工资表明细!BF$3:BF$82) -> 932559.11
A5: 创想悦动-销售 | B5: 创想悦动-销售 | C5: =SUMIF(工资表明细!$M$3:$M$85,$B5,工资表明细!$L$3:$L$85) -> 14 | D5: =SUMIF(工资表明细!$M$3:$M$82,$B5,工资表明细!P$3:P$82) -> 246000 | E5: =SUMIF(工资表明细!$M$3:$M$82,$B5,工资表明细!Q$3:Q$82) -> 0 | F5: =SUMIF(工资表明细!$M$3:$M$82,$B5,工资表明细!R$3:R$82) -> 0 | G5: =SUMIF(工资表明细!$M$3:$M$82,$B5,工资表明细!S$3:S$82) -> 0 | H5: =SUMIF(工资表明细!$M$3:$M$82,$B5,工资表明细!T$3:T$82) -> 0 | I5: =SUMIF(工资表明细!$M$3:$M$82,$B5,工资表明细!U$3:U$82) -> 6206.9 | J5: =SUMIF(工资表明细!$M$3:$M$82,$B5,工资表明细!V$3:V$82) -> 0 | K5: =SUMIF(工资表明细!$M$3:$M$82,$B5,工资表明细!W$3:W$82) -> 0 | ... AC5: =SUMIF(工资表明细!$M$3:$M$82,$B5,工资表明细!AO$3:AO$82) -> 20480 | AD5: =SUMIF(工资表明细!$M$3:$M$82,$B5,工资表明细!BE$3:BE$82) -> 7179.72 | AE5: =SUMIF(工资表明细!$M$3:$M$82,$B5,工资表明细!BF$3:BF$82) -> 190569.54
A6: 总计 | C6: =SUM(C3:C5) -> 78 | D6: =SUM(D3:D5) -> 1790300 | E6: =SUM(E3:E5) -> 0 | F6: =SUM(F3:F5) -> 0 | G6: =SUM(G3:G5) -> 0 | H6: =SUM(H3:H5) -> 0 | I6: =SUM(I3:I5) -> 49494.26 | J6: =SUM(J3:J5) -> 0 | ... AE6: =SUM(AE3:AE5) -> 1329965.5
A8: 制表： | E8: 财务部： | K8: 人力资源部总监审批： | T8: 财务部总监审批： | Z8: 审批： | AC8: 审批：
A18: 深圳创想悦动科技有限公司2026年7月工资表
A19: 二级部门 | B19: 二级部门 | C19: 人数 | D19: 基本工资 | E19: 绩效工资 | F19: 岗位津贴 | G19: 过节费 | H19: 通讯补贴 | I19: 考勤扣款 | J19: 其他扣款 | K19: 加班费 | L19: 绩效奖金 | M19: 其他奖金 | N19: 伙食补贴 | O19: 住房补贴 | P19: 司机补贴 | Q19: 专利奖 | R19: 其他补发 | S19: 补发合计 | T19: 应付工资 | U19: 借款逾期扣款 | V19: 房租水电 | W19: 房租水电1 | X19: 其他税后扣款 | Y19: 扣款合计 | Z19: 养老保险 | AA19: 医疗保险 | AB19: 失业保险 | AC19: 住房公积金 | AD19: 所得税 | AE19: 实发工资
A20: 公共设计组 | B20: 公共设计组 | C20: =SUMIF(工资表明细!$G$3:$G$82,$B20,工资表明细!$L$3:$L$82) -> 4 | D20: =SUMIF(工资表明细!$G$3:$G$82,$B20,工资表明细!P$3:P$82) -> 80000 | E20: =SUMIF(工资表明细!$G$3:$G$82,$B20,工资表明细!Q$3:Q$82) -> 0 | F20: =SUMIF(工资表明细!$G$3:$G$82,$B20,工资表明细!R$3:R$82) -> 0 | G20: =SUMIF(工资表明细!$G$3:$G$82,$B20,工资表明细!S$3:S$82) -> 0 | H20: =SUMIF(工资表明细!$G$3:$G$82,$B20,工资表明细!T$3:T$82) -> 0 | I20: =SUMIF(工资表明细!$G$3:$G$82,$B20,工资表明细!U$3:U$82) -> 0 | J20: =SUMIF(工资表明细!$G$3:$G$82,$B20,工资表明细!V$3:V$82) -> 0 | K20: =SUMIF(工资表明细!$G$3:$G$82,$B20,工资表明细!W$3:W$82) -> 0 | ... Z20: =SUMIF(工资表明细!$G$3:$G$82,$B20,工资表明细!AL$3:AL$82) -> 6400 | AA20: =SUMIF(工资表明细!$G$3:$G$82,$B20,工资表明细!AG$3:AG$82) -> 0 | AB20: =SUMIF(工资表明细!$G$3:$G$82,$B20,工资表明细!AN$3:AN$82) -> 160 | AC20: =SUMIF(工资表明细!$G$3:$G$82,$B20,工资表明细!AO$3:AO$82) -> 4620 | AD20: =SUMIF(工资表明细!$G$3:$G$82,$B20,工资表明细!BE$3:BE$82) -> 3072.9 | AE20: =SUMIF(工资表明细!$G$3:$G$82,$B20,工资表明细!BF$3:BF$82) -> 64547.1
A21: 品牌宣传组 | B21: 品牌宣传组 | C21: =SUMIF(工资表明细!$G$3:$G$82,$B21,工资表明细!$L$3:$L$82) -> 3 | D21: =SUMIF(工资表明细!$G$3:$G$82,$B21,工资表明细!P$3:P$82) -> 78000 | E21: =SUMIF(工资表明细!$G$3:$G$82,$B21,工资表明细!Q$3:Q$82) -> 0 | F21: =SUMIF(工资表明细!$G$3:$G$82,$B21,工资表明细!R$3:R$82) -> 0 | G21: =SUMIF(工资表明细!$G$3:$G$82,$B21,工资表明细!S$3:S$82) -> 0 | H21: =SUMIF(工资表明细!$G$3:$G$82,$B21,工资表明细!T$3:T$82) -> 0 | I21: =SUMIF(工资表明细!$G$3:$G$82,$B21,工资表明细!U$3:U$82) -> 2206.9 | J21: =SUMIF(工资表明细!$G$3:$G$82,$B21,工资表明细!V$3:V$82) -> 0 | K21: =SUMIF(工资表明细!$G$3:$G$82,$B21,工资表明细!W$3:W$82) -> 0 | ... Z21: =SUMIF(工资表明细!$G$3:$G$82,$B21,工资表明细!AL$3:AL$82) -> 5643.92 | AA21: =SUMIF(工资表明细!$G$3:$G$82,$B21,工资表明细!AG$3:AG$82) -> 0 | AB21: =SUMIF(工资表明细!$G$3:$G$82,$B21,工资表明细!AN$3:AN$82) -> 156 | AC21: =SUMIF(工资表明细!$G$3:$G$82,$B21,工资表明细!AO$3:AO$82) -> 5160 | AD21: =SUMIF(工资表明细!$G$3:$G$82,$B21,工资表明细!BE$3:BE$82) -> 3195.75 | AE21: =SUMIF(工资表明细!$G$3:$G$82,$B21,工资表明细!BF$3:BF$82) -> 60664.77
A22: 游戏研发部 | B22: 游戏研发部 | C22: =SUMIF(工资表明细!$G$3:$G$82,$B22,工资表明细!$L$3:$L$82) -> 33 | D22: =SUMIF(工资表明细!$G$3:$G$82,$B22,工资表明细!P$3:P$82) -> 770300 | E22: =SUMIF(工资表明细!$G$3:$G$82,$B22,工资表明细!Q$3:Q$82) -> 0 | F22: =SUMIF(工资表明细!$G$3:$G$82,$B22,工资表明细!R$3:R$82) -> 0 | G22: =SUMIF(工资表明细!$G$3:$G$82,$B22,工资表明细!S$3:S$82) -> 0 | H22: =SUMIF(工资表明细!$G$3:$G$82,$B22,工资表明细!T$3:T$82) -> 0 | I22: =SUMIF(工资表明细!$G$3:$G$82,$B22,工资表明细!U$3:U$82) -> 14298.85 | J22: =SUMIF(工资表明细!$G$3:$G$82,$B22,工资表明细!V$3:V$82) -> 0 | K22: =SUMIF(工资表明细!$G$3:$G$82,$B22,工资表明细!W$3:W$82) -> 0 | ... Z22: =SUMIF(工资表明细!$G$3:$G$82,$B22,工资表明细!AL$3:AL$82) -> 53951.36 | AA22: =SUMIF(工资表明细!$G$3:$G$82,$B22,工资表明细!AG$3:AG$82) -> 0 | AB22: =SUMIF(工资表明细!$G$3:$G$82,$B22,工资表明细!AN$3:AN$82) -> 1529.54 | AC22: =SUMIF(工资表明细!$G$3:$G$82,$B22,工资表明细!AO$3:AO$82) -> 56103.6 | AD22: =SUMIF(工资表明细!$G$3:$G$82,$B22,工资表明细!BE$3:BE$82) -> 54397.54 | AE22: =SUMIF(工资表明细!$G$3:$G$82,$B22,工资表明细!BF$3:BF$82) -> 573282.9
A23: 商务合作部 | B23: 商务合作部 | C23: =SUMIF(工资表明细!$G$3:$G$82,$B23,工资表明细!$L$3:$L$82) -> 6 | D23: =SUMIF(工资表明细!$G$3:$G$82,$B23,工资表明细!P$3:P$82) -> 117000 | E23: =SUMIF(工资表明细!$G$3:$G$82,$B23,工资表明细!Q$3:Q$82) -> 0 | F23: =SUMIF(工资表明细!$G$3:$G$82,$B23,工资表明细!R$3:R$82) -> 0 | G23: =SUMIF(工资表明细!$G$3:$G$82,$B23,工资表明细!S$3:S$82) -> 0 | H23: =SUMIF(工资表明细!$G$3:$G$82,$B23,工资表明细!T$3:T$82) -> 0 | I23: =SUMIF(工资表明细!$G$3:$G$82,$B23,工资表明细!U$3:U$82) -> 183.91 | J23: =SUMIF(工资表明细!$G$3:$G$82,$B23,工资表明细!V$3:V$82) -> 0 | K23: =SUMIF(工资表明细!$G$3:$G$82,$B23,工资表明细!W$3:W$82) -> 0 | ... Z23: =SUMIF(工资表明细!$G$3:$G$82,$B23,工资表明细!AL$3:AL$82) -> 5323.92 | AA23: =SUMIF(工资表明细!$G$3:$G$82,$B23,工资表明细!AG$3:AG$82) -> 0 | AB23: =SUMIF(工资表明细!$G$3:$G$82,$B23,工资表明细!AN$3:AN$82) -> 150 | AC23: =SUMIF(工资表明细!$G$3:$G$82,$B23,工资表明细!AO$3:AO$82) -> 6500 | AD23: =SUMIF(工资表明细!$G$3:$G$82,$B23,工资表明细!BE$3:BE$82) -> 9377.56 | AE23: =SUMIF(工资表明细!$G$3:$G$82,$B23,工资表明细!BF$3:BF$82) -> 94924.61
A24: 基础产品部 | B24: 基础产品部 | C24: =SUMIF(工资表明细!$G$3:$G$82,$B24,工资表明细!$L$3:$L$82) -> 17 | D24: =SUMIF(工资表明细!$G$3:$G$82,$B24,工资表明细!P$3:P$82) -> 467000 | E24: =SUMIF(工资表明细!$G$3:$G$82,$B24,工资表明细!Q$3:Q$82) -> 0 | F24: =SUMIF(工资表明细!$G$3:$G$82,$B24,工资表明细!R$3:R$82) -> 0 | G24: =SUMIF(工资表明细!$G$3:$G$82,$B24,工资表明细!S$3:S$82) -> 0 | H24: =SUMIF(工资表明细!$G$3:$G$82,$B24,工资表明细!T$3:T$82) -> 0 | I24: =SUMIF(工资表明细!$G$3:$G$82,$B24,工资表明细!U$3:U$82) -> 28988.51 | J24: =SUMIF(工资表明细!$G$3:$G$82,$B24,工资表明细!V$3:V$82) -> 0 | K24: =SUMIF(工资表明细!$G$3:$G$82,$B24,工资表明细!W$3:W$82) -> 0 | ... Z24: =SUMIF(工资表明细!$G$3:$G$82,$B24,工资表明细!AL$3:AL$82) -> 26947.44 | AA24: =SUMIF(工资表明细!$G$3:$G$82,$B24,工资表明细!AG$3:AG$82) -> 0 | AB24: =SUMIF(工资表明细!$G$3:$G$82,$B24,工资表明细!AN$3:AN$82) -> 827.88 | AC24: =SUMIF(工资表明细!$G$3:$G$82,$B24,工资表明细!AO$3:AO$82) -> 35599.5 | AD24: =SUMIF(工资表明细!$G$3:$G$82,$B24,工资表明细!BE$3:BE$82) -> 44325.1 | AE24: =SUMIF(工资表明细!$G$3:$G$82,$B24,工资表明细!BF$3:BF$82) -> 324780.93
A25: 人资行政组 | B25: 人资行政组 | C25: =SUMIF(工资表明细!$G$3:$G$82,$B25,工资表明细!$L$3:$L$82) -> 4 | D25: =SUMIF(工资表明细!$G$3:$G$82,$B25,工资表明细!P$3:P$82) -> 60000 | E25: =SUMIF(工资表明细!$G$3:$G$82,$B25,工资表明细!Q$3:Q$82) -> 0 | F25: =SUMIF(工资表明细!$G$3:$G$82,$B25,工资表明细!R$3:R$82) -> 0 | G25: =SUMIF(工资表明细!$G$3:$G$82,$B25,工资表明细!S$3:S$82) -> 0 | H25: =SUMIF(工资表明细!$G$3:$G$82,$B25,工资表明细!T$3:T$82) -> 0 | I25: =SUMIF(工资表明细!$G$3:$G$82,$B25,工资表明细!U$3:U$82) -> 0 | J25: =SUMIF(工资表明细!$G$3:$G$82,$B25,工资表明细!V$3:V$82) -> 0 | K25: =SUMIF(工资表明细!$G$3:$G$82,$B25,工资表明细!W$3:W$82) -> 0 | ... Z25: =SUMIF(工资表明细!$G$3:$G$82,$B25,工资表明细!AL$3:AL$82) -> 4800 | AA25: =SUMIF(工资表明细!$G$3:$G$82,$B25,工资表明细!AG$3:AG$82) -> 0 | AB25: =SUMIF(工资表明细!$G$3:$G$82,$B25,工资表明细!AN$3:AN$82) -> 120 | AC25: =SUMIF(工资表明细!$G$3:$G$82,$B25,工资表明细!AO$3:AO$82) -> 6360 | AD25: =SUMIF(工资表明细!$G$3:$G$82,$B25,工资表明细!BE$3:BE$82) -> 2102.96 | AE25: =SUMIF(工资表明细!$G$3:$G$82,$B25,工资表明细!BF$3:BF$82) -> 44437.28
A26: 平台运营部 | B26: 平台运营部 | C26: =SUMIF(工资表明细!$G$3:$G$82,$B26,工资表明细!$L$3:$L$82) -> 11 | D26: =SUMIF(工资表明细!$G$3:$G$82,$B26,工资表明细!P$3:P$82) -> 218000 | E26: =SUMIF(工资表明细!$G$3:$G$82,$B26,工资表明细!Q$3:Q$82) -> 0 | F26: =SUMIF(工资表明细!$G$3:$G$82,$B26,工资表明细!R$3:R$82) -> 0 | G26: =SUMIF(工资表明细!$G$3:$G$82,$B26,工资表明细!S$3:S$82) -> 0 | H26: =SUMIF(工资表明细!$G$3:$G$82,$B26,工资表明细!T$3:T$82) -> 0 | I26: =SUMIF(工资表明细!$G$3:$G$82,$B26,工资表明细!U$3:U$82) -> 3816.09 | J26: =SUMIF(工资表明细!$G$3:$G$82,$B26,工资表明细!V$3:V$82) -> 0 | K26: =SUMIF(工资表明细!$G$3:$G$82,$B26,工资表明细!W$3:W$82) -> 0 | ... Z26: =SUMIF(工资表明细!$G$3:$G$82,$B26,工资表明细!AL$3:AL$82) -> 16211.76 | AA26: =SUMIF(工资表明细!$G$3:$G$82,$B26,工资表明细!AG$3:AG$82) -> 0 | AB26: =SUMIF(工资表明细!$G$3:$G$82,$B26,工资表明细!AN$3:AN$82) -> 428 | AC26: =SUMIF(工资表明细!$G$3:$G$82,$B26,工资表明细!AO$3:AO$82) -> 16740 | AD26: =SUMIF(工资表明细!$G$3:$G$82,$B26,工资表明细!BE$3:BE$82) -> 10523.6 | AE26: =SUMIF(工资表明细!$G$3:$G$82,$B26,工资表明细!BF$3:BF$82) -> 167327.89
A27: 总计 | C27: =SUM(C20:C26) -> 78 | D27: =SUM(D20:D26) -> 1790300 | E27: =SUM(E20:E26) -> 0 | F27: =SUM(F20:F26) -> 0 | G27: =SUM(G20:G26) -> 0 | H27: =SUM(H20:H26) -> 0 | I27: =SUM(I20:I26) -> 49494.26 | J27: =SUM(J20:J26) -> 0 | ... AE27: =SUM(AE20:AE26) -> 1329965.5
A29: 制表： | E29: 财务部： | K29: 人力资源部总监审批： | T29: 财务部总监审批： | Z29: 审批： | AC29: 审批：

Sheet 工资表明细
A1: 深圳创想悦动科技有限公司2026年7月工资表
A2: 序号 | B2: 归属公司 | C2: 工号 | D2: 姓名 | E2: 用工类型 | F2: 一级部门 | G2: 二级部门 | H2: 报到本公司日期 | I2: 离职日期 | J2: 一级成本中心 | K2: 专业 | L2: 人数 | M2: 成本中心编码 | N2: 身份证号码 | O2: 卡号 | P2: 基本工资 | Q2: 绩效工资 | R2: 岗位津贴 | S2: 节日福利 | T2: 通讯补贴 | U2: 考勤扣款 | V2: 其他扣款 | W2: 加班费 | X2: 绩效奖金 | Y2: 其他奖金 | Z2: 伙食补贴 | AA2: 住房补贴 | AB2: 司机补贴 | AC2: 专利奖金 | AD2: 其他补发 | AE2: 补发合计 | AF2: 应付工资 | AG2: 借款逾期扣款 | AH2: 房租水电 | AI2: 房租水电1 | AJ2: 其他税后扣款 | AK2: 扣款合计 | AL2: 养老保险 | AM2: 医疗保险 | AN2: 失业保险 | AO2: 住房公积金 | AP2: 累计子女教育 | AQ2: 累计继续教育 | AR2: 累计住房贷款利息 | AS2: 累计住房租金 | AT2: 累计赡养老人 | AU2: 累计婴幼儿照护费用 | AV2: 累计个人养老金 | AW2: 免税额 | AX2: 本月合计扣除 | AY2: 截止上月累计收入 | AZ2: 截止本月累计收入 （实习扣减20%） | BA2: 截止上月累计扣除 | BB2: 截止当月累计扣除 | BC2: 截止本月应交个税 | BD2: 累计已扣税额 | BE2: 本月应交个税 | BF2: 实发工资 | BH2: 邮箱 | BI2: 总体逻辑检查 | BJ2: 备注
A3: =ROW()-2 -> 1 | B3: 创想悦动 | C3: SCX00001 | D3: 刘丹 | E3: 合同制人员 | F3: 创想悦动 | G3: 基础产品部 | H3: 45880 | J3: 创想悦动-管理 | K3: 计算机网络技术 | L3: 1 | M3: 创想悦动-管理 | N3: 420502197605290638 | O3: 6214855253515072 | P3: 50000 | Q3: =ROUND(SUMIF(其他补发!B:B,$C3,其他补发!D:D),2) -> 0 | R3: =ROUND(SUMIF(其他补发!B:B,$C3,其他补发!H:H),2) -> 0 | S3: =ROUND(SUMIF(其他补发!B:B,$C3,其他补发!I:I),2) -> 0 | T3: =ROUND(SUMIF(其他补发!B:B,$C3,其他补发!E:E),2) -> 0 | U3: =ROUND((VLOOKUP(C3,考勤!C:H,6,0)+VLOOKUP(C3,考勤!C:O,13,0)+VLOOKUP(C3,考勤!C:P,14,0)*0.3+VLOOKUP(C3,考勤!C:AA,25,0))*(P3+Q3+R3)/21.75,2)+ROUND((VLOOKUP(C3,考勤!C:V,19,0)+VLOOKUP(C3,考勤!C:V,20,0))*(P3+Q3+R3-2520)/21.75,2) -> 0 | V3: =ROUND(SUMIF(动态表!C:C,C3,动态表!AA:AA)+SUMIFS(其他补发!L:L,其他补发!B:B,C3),2) -> 0 | W3: =ROUND(VLOOKUP(C3,考勤!C:K,9,0)*P3/21.75/8*2+VLOOKUP(C3,考勤!C:L,10,0)*P3/21.75/8*3,2)+SUMIFS(加班费!$H:$H,加班费!$D:$D,$C3) -> 0 | X3: =SUMIF(奖金!D:D,C3,奖金!F:F) -> 0 | Y3: =SUMIF(其他补发!B:B,C3,其他补发!J:J) -> 0 | Z3: =SUMIF(其他补发!B:B,C3,其他补发!F:F) -> 0 | AA3: =SUMIF(其他补发!B:B,C3,其他补发!G:G) -> 0 | AB3: =SUMIF(其他补发!B:B,C3,其他补发!M:M) -> 0 | AC3: =SUMIF(其他补发!B:B,C3,其他补发!N:N) -> 0 | AD3: =SUMIF(其他补发!B:B,C3,其他补发!K:K) -> 0 | AE3: =AD3+AC3+AB3+AA3+Z3+Y3+X3+W3 -> 0 | AF3: =ROUND((P3+Q3+R3+S3+T3-U3-V3+AE3),2) -> 50000 | AG3: =SUMIF(税后扣款!B:B,C3,税后扣款!E:E) -> 0 | AH3: =SUMIF(房租水电!A:A,C3,房租水电!C:C) -> 0 | AI3: =SUMIF(房租水电!A:A,C3,房租水电!D:D) -> 0 | AJ3: =SUMIF(税后扣款!B:B,C3,税后扣款!D:D) -> -240 | AK3: =AJ3+AI3+AH3+AG3 -> -240 | AL3: =SUMIF(社会保险!D:D,N3,社会保险!I:I) -> 2203.92 | AM3: =SUMIF(社会保险!D:D,N3,社会保险!J:J) -> 672.66 | AN3: =SUMIF(社会保险!D:D,N3,社会保险!K:K) -> 96.94 | AO3: =SUMIF(公积金!C:C,N3,公积金!L:L) -> 5311.8 | AP3: =SUMIF(专项扣除!$B:$B,$C3,专项扣除!D:D) -> 0 | AQ3: =SUMIF(专项扣除!$B:$B,$C3,专项扣除!E:E) -> 0 | AR3: =SUMIF(专项扣除!$B:$B,$C3,专项扣除!F:F) -> 0 | AS3: =SUMIF(专项扣除!$B:$B,$C3,专项扣除!G:G) -> 0 | AT3: =SUMIF(专项扣除!$B:$B,$C3,专项扣除!H:H) -> 0 | AU3: =SUMIF(专项扣除!$B:$B,$C3,专项扣除!I:I) -> 0 | AV3: =SUMIF(专项扣除!$B:$B,$C3,专项扣除!J:J) -> 0 | AW3: 5000 | AX3: =AL3+AM3+AN3+AO3+AW3 -> 13285.32 | AY3: =SUMIF(上月累计工资累计社保和公积金!C:C,C3,上月累计工资累计社保和公积金!E:E) -> 350500 | AZ3: =IF(E3="实习人员",(AY3+AF3)*80%,AY3+AF3) -> 400500 | BA3: =SUMIF(上月累计工资累计社保和公积金!C:C,C3,上月累计工资累计社保和公积金!K:K) -> 74347.73 | BB3: =BA3+AX3 -> 87633.05 | BC3: =ROUND(MAX((AZ3-BB3-AP3-AQ3-AR3-AS3-AT3-AU3-AV3)*0.01*{3,10,20,25,30,35,45}-{0,2520,16920,31920,52920,85920,181920},0),2) -> 46296.74 | BD3: =SUMIF(上月累计工资累计社保和公积金!C:C,C3,上月累计工资累计社保和公积金!L:L) -> 38310.45 | BE3: =IF((BC3-BD3)<0,0,((BC3-BD3))) -> 7986.29 | BF3: =ROUND((AF3-AK3-BE3-AL3-AM3-AN3-AO3),2) -> 33968.39 | BH3: =VLOOKUP(C3,考勤!C:AL,36,0) -> liudan@youdoogo.com | BI3: =P3+Q3+R3+S3+T3-U3-V3+W3+X3+Y3+Z3+AA3+AB3+AC3+AD3-AG3-AH3-AI3-AJ3-AL3-AM3-AN3-AO3-BE3-BF3 -> 0
A4: =ROW()-2 -> 2 | B4: 创想悦动 | C4: SCX00002 | D4: 李奕佳 | E4: 合同制人员 | F4: 创想悦动 | G4: 人资行政组 | H4: 45880 | J4: 创想悦动-管理 | K4: 生物化学与分子生物学 | L4: 1 | M4: 创想悦动-管理 | N4: 330302200101050448 | O4: 6214834366472596 | P4: 16000 | Q4: =ROUND(SUMIF(其他补发!B:B,$C4,其他补发!D:D),2) -> 0 | R4: =ROUND(SUMIF(其他补发!B:B,$C4,其他补发!H:H),2) -> 0 | S4: =ROUND(SUMIF(其他补发!B:B,$C4,其他补发!I:I),2) -> 0 | T4: =ROUND(SUMIF(其他补发!B:B,$C4,其他补发!E:E),2) -> 0 | U4: =ROUND((VLOOKUP(C4,考勤!C:H,6,0)+VLOOKUP(C4,考勤!C:O,13,0)+VLOOKUP(C4,考勤!C:P,14,0)*0.3+VLOOKUP(C4,考勤!C:AA,25,0))*(P4+Q4+R4)/21.75,2)+ROUND((VLOOKUP(C4,考勤!C:V,19,0)+VLOOKUP(C4,考勤!C:V,20,0))*(P4+Q4+R4-2520)/21.75,2) -> 0 | V4: =ROUND(SUMIF(动态表!C:C,C4,动态表!AA:AA)+SUMIFS(其他补发!L:L,其他补发!B:B,C4),2) -> 0 | W4: =ROUND(VLOOKUP(C4,考勤!C:K,9,0)*P4/21.75/8*2+VLOOKUP(C4,考勤!C:L,10,0)*P4/21.75/8*3,2)+SUMIFS(加班费!$H:$H,加班费!$D:$D,$C4) -> 0 | X4: =SUMIF(奖金!D:D,C4,奖金!F:F) -> 0 | Y4: =SUMIF(其他补发!B:B,C4,其他补发!J:J) -> 0 | Z4: =SUMIF(其他补发!B:B,C4,其他补发!F:F) -> 0 | AA4: =SUMIF(其他补发!B:B,C4,其他补发!G:G) -> 0 | AB4: =SUMIF(其他补发!B:B,C4,其他补发!M:M) -> 0 | AC4: =SUMIF(其他补发!B:B,C4,其他补发!N:N) -> 0 | AD4: =SUMIF(其他补发!B:B,C4,其他补发!K:K) -> 0 | AE4: =AD4+AC4+AB4+AA4+Z4+Y4+X4+W4 -> 0 | AF4: =ROUND((P4+Q4+R4+S4+T4-U4-V4+AE4),2) -> 16000 | AG4: =SUMIF(税后扣款!B:B,C4,税后扣款!E:E) -> 0 | AH4: =SUMIF(房租水电!A:A,C4,房租水电!C:C) -> 0 | AI4: =SUMIF(房租水电!A:A,C4,房租水电!D:D) -> 0 | AJ4: =SUMIF(税后扣款!B:B,C4,税后扣款!D:D) -> -240 | AK4: =AJ4+AI4+AH4+AG4 -> -240 | AL4: =SUMIF(社会保险!D:D,N4,社会保险!I:I) -> 1280 | AM4: =SUMIF(社会保险!D:D,N4,社会保险!J:J) -> 320 | AN4: =SUMIF(社会保险!D:D,N4,社会保险!K:K) -> 32 | AO4: =SUMIF(公积金!C:C,N4,公积金!L:L) -> 1680 | AP4: =SUMIF(专项扣除!$B:$B,$C4,专项扣除!D:D) -> 0 | AQ4: =SUMIF(专项扣除!$B:$B,$C4,专项扣除!E:E) -> 0 | AR4: =SUMIF(专项扣除!$B:$B,$C4,专项扣除!F:F) -> 0 | AS4: =SUMIF(专项扣除!$B:$B,$C4,专项扣除!G:G) -> 10500 | AT4: =SUMIF(专项扣除!$B:$B,$C4,专项扣除!H:H) -> 0 | AU4: =SUMIF(专项扣除!$B:$B,$C4,专项扣除!I:I) -> 0 | AV4: =SUMIF(专项扣除!$B:$B,$C4,专项扣除!J:J) -> 0 | AW4: 5000 | AX4: =AL4+AM4+AN4+AO4+AW4 -> 8312 | AY4: =SUMIF(上月累计工资累计社保和公积金!C:C,C4,上月累计工资累计社保和公积金!E:E) -> 104300 | AZ4: =IF(E4="实习人员",(AY4+AF4)*80%,AY4+AF4) -> 120300 | BA4: =SUMIF(上月累计工资累计社保和公积金!C:C,C4,上月累计工资累计社保和公积金!K:K) -> 51488 | BB4: =BA4+AX4 -> 59800 | BC4: =ROUND(MAX((AZ4-BB4-AP4-AQ4-AR4-AS4-AT4-AU4-AV4)*0.01*{3,10,20,25,30,35,45}-{0,2520,16920,31920,52920,85920,181920},0),2) -> 2480 | BD4: =SUMIF(上月累计工资累计社保和公积金!C:C,C4,上月累计工资累计社保和公积金!L:L) -> 1711.2 | BE4: =IF((BC4-BD4)<0,0,((BC4-BD4))) -> 768.8 | BF4: =ROUND((AF4-AK4-BE4-AL4-AM4-AN4-AO4),2) -> 12159.2 | BH4: =VLOOKUP(C4,考勤!C:AL,36,0) -> liyijia@youdoogo.com | BI4: =P4+Q4+R4+S4+T4-U4-V4+W4+X4+Y4+Z4+AA4+AB4+AC4+AD4-AG4-AH4-AI4-AJ4-AL4-AM4-AN4-AO4-BE4-BF4 -> 0
A5: =ROW()-2 -> 3 | B5: 创想悦动 | C5: SCX00003 | D5: 申华 | E5: 合同制人员 | F5: 创想悦动 | G5: 基础产品部 | H5: 45880 | J5: 创想悦动-管理 | K5: 计算机科学与技术 | L5: 1 | M5: 创想悦动-管理 | N5: 610121198412260077 | O5: 6226096554090061 | P5: 50000 | Q5: =ROUND(SUMIF(其他补发!B:B,$C5,其他补发!D:D),2) -> 0 | R5: =ROUND(SUMIF(其他补发!B:B,$C5,其他补发!H:H),2) -> 0 | S5: =ROUND(SUMIF(其他补发!B:B,$C5,其他补发!I:I),2) -> 0 | T5: =ROUND(SUMIF(其他补发!B:B,$C5,其他补发!E:E),2) -> 0 | U5: =ROUND((VLOOKUP(C5,考勤!C:H,6,0)+VLOOKUP(C5,考勤!C:O,13,0)+VLOOKUP(C5,考勤!C:P,14,0)*0.3+VLOOKUP(C5,考勤!C:AA,25,0))*(P5+Q5+R5)/21.75,2)+ROUND((VLOOKUP(C5,考勤!C:V,19,0)+VLOOKUP(C5,考勤!C:V,20,0))*(P5+Q5+R5-2520)/21.75,2) -> 0 | V5: =ROUND(SUMIF(动态表!C:C,C5,动态表!AA:AA)+SUMIFS(其他补发!L:L,其他补发!B:B,C5),2) -> 0 | W5: =ROUND(VLOOKUP(C5,考勤!C:K,9,0)*P5/21.75/8*2+VLOOKUP(C5,考勤!C:L,10,0)*P5/21.75/8*3,2)+SUMIFS(加班费!$H:$H,加班费!$D:$D,$C5) -> 0 | X5: =SUMIF(奖金!D:D,C5,奖金!F:F) -> 0 | Y5: =SUMIF(其他补发!B:B,C5,其他补发!J:J) -> 0 | Z5: =SUMIF(其他补发!B:B,C5,其他补发!F:F) -> 0 | AA5: =SUMIF(其他补发!B:B,C5,其他补发!G:G) -> 0 | AB5: =SUMIF(其他补发!B:B,C5,其他补发!M:M) -> 0 | AC5: =SUMIF(其他补发!B:B,C5,其他补发!N:N) -> 0 | AD5: =SUMIF(其他补发!B:B,C5,其他补发!K:K) -> 0 | AE5: =AD5+AC5+AB5+AA5+Z5+Y5+X5+W5 -> 0 | AF5: =ROUND((P5+Q5+R5+S5+T5-U5-V5+AE5),2) -> 50000 | AG5: =SUMIF(税后扣款!B:B,C5,税后扣款!E:E) -> 0 | AH5: =SUMIF(房租水电!A:A,C5,房租水电!C:C) -> 0 | AI5: =SUMIF(房租水电!A:A,C5,房租水电!D:D) -> 0 | AJ5: =SUMIF(税后扣款!B:B,C5,税后扣款!D:D) -> -240 | AK5: =AJ5+AI5+AH5+AG5 -> -240 | AL5: =SUMIF(社会保险!D:D,N5,社会保险!I:I) -> 2203.92 | AM5: =SUMIF(社会保险!D:D,N5,社会保险!J:J) -> 672.66 | AN5: =SUMIF(社会保险!D:D,N5,社会保险!K:K) -> 96.94 | AO5: =SUMIF(公积金!C:C,N5,公积金!L:L) -> 5311.8 | AP5: =SUMIF(专项扣除!$B:$B,$C5,专项扣除!D:D) -> 0 | AQ5: =SUMIF(专项扣除!$B:$B,$C5,专项扣除!E:E) -> 0 | AR5: =SUMIF(专项扣除!$B:$B,$C5,专项扣除!F:F) -> 0 | AS5: =SUMIF(专项扣除!$B:$B,$C5,专项扣除!G:G) -> 0 | AT5: =SUMIF(专项扣除!$B:$B,$C5,专项扣除!H:H) -> 0 | AU5: =SUMIF(专项扣除!$B:$B,$C5,专项扣除!I:I) -> 0 | AV5: =SUMIF(专项扣除!$B:$B,$C5,专项扣除!J:J) -> 0 | AW5: 5000 | AX5: =AL5+AM5+AN5+AO5+AW5 -> 13285.32 | AY5: =SUMIF(上月累计工资累计社保和公积金!C:C,C5,上月累计工资累计社保和公积金!E:E) -> 349150.57 | AZ5: =IF(E5="实习人员",(AY5+AF5)*80%,AY5+AF5) -> 399150.57 | BA5: =SUMIF(上月累计工资累计社保和公积金!C:C,C5,上月累计工资累计社保和公积金!K:K) -> 74347.73 | BB5: =BA5+AX5 -> 87633.05 | BC5: =ROUND(MAX((AZ5-BB5-AP5-AQ5-AR5-AS5-AT5-AU5-AV5)*0.01*{3,10,20,25,30,35,45}-{0,2520,16920,31920,52920,85920,181920},0),2) -> 45959.38 | BD5: =SUMIF(上月累计工资累计社保和公积金!C:C,C5,上月累计工资累计社保和公积金!L:L) -> 38040.57 | BE5: =IF((BC5-BD5)<0,0,((BC5-BD5))) -> 7918.81 | BF5: =ROUND((AF5-AK5-BE5-AL5-AM5-AN5-AO5),2) -> 34035.87 | BH5: =VLOOKUP(C5,考勤!C:AL,36,0) -> ~@.com | BI5: =P5+Q5+R5+S5+T5-U5-V5+W5+X5+Y5+Z5+AA5+AB5+AC5+AD5-AG5-AH5-AI5-AJ5-AL5-AM5-AN5-AO5-BE5-BF5 -> 0
A6: =ROW()-2 -> 4 | B6: 创想悦动 | C6: SCX00004 | D6: 杨晓波 | E6: 合同制人员 | F6: 创想悦动 | G6: 基础产品部 | H6: 45880 | J6: 创想悦动-管理 | K6: 卡通动画 | L6: 1 | M6: 创想悦动-管理 | N6: 440881198504087112 | O6: 6225887813978158 | P6: 48000 | Q6: =ROUND(SUMIF(其他补发!B:B,$C6,其他补发!D:D),2) -> 0 | R6: =ROUND(SUMIF(其他补发!B:B,$C6,其他补发!H:H),2) -> 0 | S6: =ROUND(SUMIF(其他补发!B:B,$C6,其他补发!I:I),2) -> 0 | T6: =ROUND(SUMIF(其他补发!B:B,$C6,其他补发!E:E),2) -> 0 | U6: =ROUND((VLOOKUP(C6,考勤!C:H,6,0)+VLOOKUP(C6,考勤!C:O,13,0)+VLOOKUP(C6,考勤!C:P,14,0)*0.3+VLOOKUP(C6,考勤!C:AA,25,0))*(P6+Q6+R6)/21.75,2)+ROUND((VLOOKUP(C6,考勤!C:V,19,0)+VLOOKUP(C6,考勤!C:V,20,0))*(P6+Q6+R6-2520)/21.75,2) -> 0 | V6: =ROUND(SUMIF(动态表!C:C,C6,动态表!AA:AA)+SUMIFS(其他补发!L:L,其他补发!B:B,C6),2) -> 0 | W6: =ROUND(VLOOKUP(C6,考勤!C:K,9,0)*P6/21.75/8*2+VLOOKUP(C6,考勤!C:L,10,0)*P6/21.75/8*3,2)+SUMIFS(加班费!$H:$H,加班费!$D:$D,$C6) -> 0 | X6: =SUMIF(奖金!D:D,C6,奖金!F:F) -> 0 | Y6: =SUMIF(其他补发!B:B,C6,其他补发!J:J) -> 0 | Z6: =SUMIF(其他补发!B:B,C6,其他补发!F:F) -> 0 | AA6: =SUMIF(其他补发!B:B,C6,其他补发!G:G) -> 0 | AB6: =SUMIF(其他补发!B:B,C6,其他补发!M:M) -> 0 | AC6: =SUMIF(其他补发!B:B,C6,其他补发!N:N) -> 0 | AD6: =SUMIF(其他补发!B:B,C6,其他补发!K:K) -> 0 | AE6: =AD6+AC6+AB6+AA6+Z6+Y6+X6+W6 -> 0 | AF6: =ROUND((P6+Q6+R6+S6+T6-U6-V6+AE6),2) -> 48000 | AG6: =SUMIF(税后扣款!B:B,C6,税后扣款!E:E) -> 0 | AH6: =SUMIF(房租水电!A:A,C6,房租水电!C:C) -> 0 | AI6: =SUMIF(房租水电!A:A,C6,房租水电!D:D) -> 0 | AJ6: =SUMIF(税后扣款!B:B,C6,税后扣款!D:D) -> -240 | AK6: =AJ6+AI6+AH6+AG6 -> -240 | AL6: =SUMIF(社会保险!D:D,N6,社会保险!I:I) -> 2203.92 | AM6: =SUMIF(社会保险!D:D,N6,社会保险!J:J) -> 672.66 | AN6: =SUMIF(社会保险!D:D,N6,社会保险!K:K) -> 96 | AO6: =SUMIF(公积金!C:C,N6,公积金!L:L) -> 2655.9 | AP6: =SUMIF(专项扣除!$B:$B,$C6,专项扣除!D:D) -> 0 | AQ6: =SUMIF(专项扣除!$B:$B,$C6,专项扣除!E:E) -> 0 | AR6: =SUMIF(专项扣除!$B:$B,$C6,专项扣除!F:F) -> 0 | AS6: =SUMIF(专项扣除!$B:$B,$C6,专项扣除!G:G) -> 0 | AT6: =SUMIF(专项扣除!$B:$B,$C6,专项扣除!H:H) -> 0 | AU6: =SUMIF(专项扣除!$B:$B,$C6,专项扣除!I:I) -> 0 | AV6: =SUMIF(专项扣除!$B:$B,$C6,专项扣除!J:J) -> 0 | AW6: 5000 | AX6: =AL6+AM6+AN6+AO6+AW6 -> 10628.48 | AY6: =SUMIF(上月累计工资累计社保和公积金!C:C,C6,上月累计工资累计社保和公积金!E:E) -> 336500 | AZ6: =IF(E6="实习人员",(AY6+AF6)*80%,AY6+AF6) -> 384500 | BA6: =SUMIF(上月累计工资累计社保和公积金!C:C,C6,上月累计工资累计社保和公积金!K:K) -> 74347.73 | BB6: =BA6+AX6 -> 84976.21 | BC6: =ROUND(MAX((AZ6-BB6-AP6-AQ6-AR6-AS6-AT6-AU6-AV6)*0.01*{3,10,20,25,30,35,45}-{0,2520,16920,31920,52920,85920,181920},0),2) -> 42984.76 | BD6: =SUMIF(上月累计工资累计社保和公积金!C:C,C6,上月累计工资累计社保和公积金!L:L) -> 35510.45 | BE6: =IF((BC6-BD6)<0,0,((BC6-BD6))) -> 7474.31 | BF6: =ROUND((AF6-AK6-BE6-AL6-AM6-AN6-AO6),2) -> 35137.21 | BH6: =VLOOKUP(C6,考勤!C:AL,36,0) -> yangxiaobo@youdoogo.com | BI6: =P6+Q6+R6+S6+T6-U6-V6+W6+X6+Y6+Z6+AA6+AB6+AC6+AD6-AG6-AH6-AI6-AJ6-AL6-AM6-AN6-AO6-BE6-BF6 -> 0
A7: =ROW()-2 -> 5 | B7: 创想悦动 | C7: SCX00005 | D7: 杨振 | E7: 合同制人员 | F7: 创想悦动 | G7: 游戏研发部 | H7: 45880 | J7: 创想悦动-研发 | K7: 汉语言文学 | L7: 1 | M7: 创想悦动-研发 | N7: 110105197902051515 | O7: 6225886552211318 | P7: 45000 | Q7: =ROUND(SUMIF(其他补发!B:B,$C7,其他补发!D:D),2) -> 0 | R7: =ROUND(SUMIF(其他补发!B:B,$C7,其他补发!H:H),2) -> 0 | S7: =ROUND(SUMIF(其他补发!B:B,$C7,其他补发!I:I),2) -> 0 | T7: =ROUND(SUMIF(其他补发!B:B,$C7,其他补发!E:E),2) -> 0 | U7: =ROUND((VLOOKUP(C7,考勤!C:H,6,0)+VLOOKUP(C7,考勤!C:O,13,0)+VLOOKUP(C7,考勤!C:P,14,0)*0.3+VLOOKUP(C7,考勤!C:AA,25,0))*(P7+Q7+R7)/21.75,2)+ROUND((VLOOKUP(C7,考勤!C:V,19,0)+VLOOKUP(C7,考勤!C:V,20,0))*(P7+Q7+R7-2520)/21.75,2) -> 0 | V7: =ROUND(SUMIF(动态表!C:C,C7,动态表!AA:AA)+SUMIFS(其他补发!L:L,其他补发!B:B,C7),2) -> 0 | W7: =ROUND(VLOOKUP(C7,考勤!C:K,9,0)*P7/21.75/8*2+VLOOKUP(C7,考勤!C:L,10,0)*P7/21.75/8*3,2)+SUMIFS(加班费!$H:$H,加班费!$D:$D,$C7) -> 0 | X7: =SUMIF(奖金!D:D,C7,奖金!F:F) -> 0 | Y7: =SUMIF(其他补发!B:B,C7,其他补发!J:J) -> 0 | Z7: =SUMIF(其他补发!B:B,C7,其他补发!F:F) -> 0 | AA7: =SUMIF(其他补发!B:B,C7,其他补发!G:G) -> 0 | AB7: =SUMIF(其他补发!B:B,C7,其他补发!M:M) -> 0 | AC7: =SUMIF(其他补发!B:B,C7,其他补发!N:N) -> 0 | AD7: =SUMIF(其他补发!B:B,C7,其他补发!K:K) -> 0 | AE7: =AD7+AC7+AB7+AA7+Z7+Y7+X7+W7 -> 0 | AF7: =ROUND((P7+Q7+R7+S7+T7-U7-V7+AE7),2) -> 45000 | AG7: =SUMIF(税后扣款!B:B,C7,税后扣款!E:E) -> 0 | AH7: =SUMIF(房租水电!A:A,C7,房租水电!C:C) -> 0 | AI7: =SUMIF(房租水电!A:A,C7,房租水电!D:D) -> 0 | AJ7: =SUMIF(税后扣款!B:B,C7,税后扣款!D:D) -> -160 | AK7: =AJ7+AI7+AH7+AG7 -> -160 | AL7: =SUMIF(社会保险!D:D,N7,社会保险!I:I) -> 2203.92 | AM7: =SUMIF(社会保险!D:D,N7,社会保险!J:J) -> 672.66 | AN7: =SUMIF(社会保险!D:D,N7,社会保险!K:K) -> 90 | AO7: =SUMIF(公积金!C:C,N7,公积金!L:L) -> 2655.9 | AP7: =SUMIF(专项扣除!$B:$B,$C7,专项扣除!D:D) -> 0 | AQ7: =SUMIF(专项扣除!$B:$B,$C7,专项扣除!E:E) -> 0 | AR7: =SUMIF(专项扣除!$B:$B,$C7,专项扣除!F:F) -> 0 | AS7: =SUMIF(专项扣除!$B:$B,$C7,专项扣除!G:G) -> 0 | AT7: =SUMIF(专项扣除!$B:$B,$C7,专项扣除!H:H) -> 0 | AU7: =SUMIF(专项扣除!$B:$B,$C7,专项扣除!I:I) -> 0 | AV7: =SUMIF(专项扣除!$B:$B,$C7,专项扣除!J:J) -> 0 | AW7: 5000 | AX7: =AL7+AM7+AN7+AO7+AW7 -> 10622.48 | AY7: =SUMIF(上月累计工资累计社保和公积金!C:C,C7,上月累计工资累计社保和公积金!E:E) -> 315300 | AZ7: =IF(E7="实习人员",(AY7+AF7)*80%,AY7+AF7) -> 360300 | BA7: =SUMIF(上月累计工资累计社保和公积金!C:C,C7,上月累计工资累计社保和公积金!K:K) -> 74347.73 | BB7: =BA7+AX7 -> 84970.21 | BC7: =ROUND(MAX((AZ7-BB7-AP7-AQ7-AR7-AS7-AT7-AU7-AV7)*0.01*{3,10,20,25,30,35,45}-{0,2520,16920,31920,52920,85920,181920},0),2) -> 38145.96 | BD7: =SUMIF(上月累计工资累计社保和公积金!C:C,C7,上月累计工资累计社保和公积金!L:L) -> 31270.45 | BE7: =IF((BC7-BD7)<0,0,((BC7-BD7))) -> 6875.51 | BF7: =ROUND((AF7-AK7-BE7-AL7-AM7-AN7-AO7),2) -> 32662.01 | BH7: =VLOOKUP(C7,考勤!C:AL,36,0) -> ~@.com | BI7: =P7+Q7+R7+S7+T7-U7-V7+W7+X7+Y7+Z7+AA7+AB7+AC7+AD7-AG7-AH7-AI7-AJ7-AL7-AM7-AN7-AO7-BE7-BF7 -> 0
A8: =ROW()-2 -> 6 | B8: 创想悦动 | C8: SCX00006 | D8: 蔡昕宇 | E8: 合同制人员 | F8: 创想悦动 | G8: 商务合作部 | H8: 45880 | J8: 创想悦动-管理 | K8: 网络工程 | L8: 1 | M8: 创想悦动-管理 | N8: 210102198602153412 | O8: 6214867829480822 | P8: 38000 | Q8: =ROUND(SUMIF(其他补发!B:B,$C8,其他补发!D:D),2) -> 0 | R8: =ROUND(SUMIF(其他补发!B:B,$C8,其他补发!H:H),2) -> 0 | S8: =ROUND(SUMIF(其他补发!B:B,$C8,其他补发!I:I),2) -> 0 | T8: =ROUND(SUMIF(其他补发!B:B,$C8,其他补发!E:E),2) -> 0 | U8: =ROUND((VLOOKUP(C8,考勤!C:H,6,0)+VLOOKUP(C8,考勤!C:O,13,0)+VLOOKUP(C8,考勤!C:P,14,0)*0.3+VLOOKUP(C8,考勤!C:AA,25,0))*(P8+Q8+R8)/21.75,2)+ROUND((VLOOKUP(C8,考勤!C:V,19,0)+VLOOKUP(C8,考勤!C:V,20,0))*(P8+Q8+R8-2520)/21.75,2) -> 0 | V8: =ROUND(SUMIF(动态表!C:C,C8,动态表!AA:AA)+SUMIFS(其他补发!L:L,其他补发!B:B,C8),2) -> 0 | W8: =ROUND(VLOOKUP(C8,考勤!C:K,9,0)*P8/21.75/8*2+VLOOKUP(C8,考勤!C:L,10,0)*P8/21.75/8*3,2)+SUMIFS(加班费!$H:$H,加班费!$D:$D,$C8) -> 0 | X8: =SUMIF(奖金!D:D,C8,奖金!F:F) -> 0 | Y8: =SUMIF(其他补发!B:B,C8,其他补发!J:J) -> 0 | Z8: =SUMIF(其他补发!B:B,C8,其他补发!F:F) -> 0 | AA8: =SUMIF(其他补发!B:B,C8,其他补发!G:G) -> 0 | AB8: =SUMIF(其他补发!B:B,C8,其他补发!M:M) -> 0 | AC8: =SUMIF(其他补发!B:B,C8,其他补发!N:N) -> 0 | AD8: =SUMIF(其他补发!B:B,C8,其他补发!K:K) -> 0 | AE8: =AD8+AC8+AB8+AA8+Z8+Y8+X8+W8 -> 0 | AF8: =ROUND((P8+Q8+R8+S8+T8-U8-V8+AE8),2) -> 38000 | AG8: =SUMIF(税后扣款!B:B,C8,税后扣款!E:E) -> 0 | AH8: =SUMIF(房租水电!A:A,C8,房租水电!C:C) -> 0 | AI8: =SUMIF(房租水电!A:A,C8,房租水电!D:D) -> 0 | AJ8: =SUMIF(税后扣款!B:B,C8,税后扣款!D:D) -> -160 | AK8: =AJ8+AI8+AH8+AG8 -> -160 | AL8: =SUMIF(社会保险!D:D,N8,社会保险!I:I) -> 0 | AM8: =SUMIF(社会保险!D:D,N8,社会保险!J:J) -> 0 | AN8: =SUMIF(社会保险!D:D,N8,社会保险!K:K) -> 0 | AO8: =SUMIF(公积金!C:C,N8,公积金!L:L) -> 0 | AP8: =SUMIF(专项扣除!$B:$B,$C8,专项扣除!D:D) -> 0 | AQ8: =SUMIF(专项扣除!$B:$B,$C8,专项扣除!E:E) -> 0 | AR8: =SUMIF(专项扣除!$B:$B,$C8,专项扣除!F:F) -> 0 | AS8: =SUMIF(专项扣除!$B:$B,$C8,专项扣除!G:G) -> 0 | AT8: =SUMIF(专项扣除!$B:$B,$C8,专项扣除!H:H) -> 0 | AU8: =SUMIF(专项扣除!$B:$B,$C8,专项扣除!I:I) -> 0 | AV8: =SUMIF(专项扣除!$B:$B,$C8,专项扣除!J:J) -> 0 | AW8: 5000 | AX8: =AL8+AM8+AN8+AO8+AW8 -> 5000 | AY8: =SUMIF(上月累计工资累计社保和公积金!C:C,C8,上月累计工资累计社保和公积金!E:E) -> 254300 | AZ8: =IF(E8="实习人员",(AY8+AF8)*80%,AY8+AF8) -> 292300 | BA8: =SUMIF(上月累计工资累计社保和公积金!C:C,C8,上月累计工资累计社保和公积金!K:K) -> 35000 | BB8: =BA8+AX8 -> 40000 | BC8: =ROUND(MAX((AZ8-BB8-AP8-AQ8-AR8-AS8-AT8-AU8-AV8)*0.01*{3,10,20,25,30,35,45}-{0,2520,16920,31920,52920,85920,181920},0),2) -> 33540 | BD8: =SUMIF(上月累计工资累计社保和公积金!C:C,C8,上月累计工资累计社保和公积金!L:L) -> 26940 | BE8: =IF((BC8-BD8)<0,0,((BC8-BD8))) -> 6600 | BF8: =ROUND((AF8-AK8-BE8-AL8-AM8-AN8-AO8),2) -> 31560 | BH8: =VLOOKUP(C8,考勤!C:AL,36,0) -> Simon@youdoogo.com | BI8: =P8+Q8+R8+S8+T8-U8-V8+W8+X8+Y8+Z8+AA8+AB8+AC8+AD8-AG8-AH8-AI8-AJ8-AL8-AM8-AN8-AO8-BE8-BF8 -> 0
A9: =ROW()-2 -> 7 | B9: 创想悦动 | C9: SCX00007 | D9: 廖斌 | E9: 合同制人员 | F9: 创想悦动 | G9: 游戏研发部 | H9: 45880 | J9: 创想悦动-研发 | K9: 经济管理学 | L9: 1 | M9: 创想悦动-研发 | N9: 350824199212280012 | O9: 6214851800394657 | P9: 18000 | Q9: =ROUND(SUMIF(其他补发!B:B,$C9,其他补发!D:D),2) -> 0 | R9: =ROUND(SUMIF(其他补发!B:B,$C9,其他补发!H:H),2) -> 0 | S9: =ROUND(SUMIF(其他补发!B:B,$C9,其他补发!I:I),2) -> 0 | T9: =ROUND(SUMIF(其他补发!B:B,$C9,其他补发!E:E),2) -> 0 | U9: =ROUND((VLOOKUP(C9,考勤!C:H,6,0)+VLOOKUP(C9,考勤!C:O,13,0)+VLOOKUP(C9,考勤!C:P,14,0)*0.3+VLOOKUP(C9,考勤!C:AA,25,0))*(P9+Q9+R9)/21.75,2)+ROUND((VLOOKUP(C9,考勤!C:V,19,0)+VLOOKUP(C9,考勤!C:V,20,0))*(P9+Q9+R9-2520)/21.75,2) -> 0 | V9: =ROUND(SUMIF(动态表!C:C,C9,动态表!AA:AA)+SUMIFS(其他补发!L:L,其他补发!B:B,C9),2) -> 0 | W9: =ROUND(VLOOKUP(C9,考勤!C:K,9,0)*P9/21.75/8*2+VLOOKUP(C9,考勤!C:L,10,0)*P9/21.75/8*3,2)+SUMIFS(加班费!$H:$H,加班费!$D:$D,$C9) -> 0 | X9: =SUMIF(奖金!D:D,C9,奖金!F:F) -> 0 | Y9: =SUMIF(其他补发!B:B,C9,其他补发!J:J) -> 0 | Z9: =SUMIF(其他补发!B:B,C9,其他补发!F:F) -> 0 | AA9: =SUMIF(其他补发!B:B,C9,其他补发!G:G) -> 0 | AB9: =SUMIF(其他补发!B:B,C9,其他补发!M:M) -> 0 | AC9: =SUMIF(其他补发!B:B,C9,其他补发!N:N) -> 0 | AD9: =SUMIF(其他补发!B:B,C9,其他补发!K:K) -> 0 | AE9: =AD9+AC9+AB9+AA9+Z9+Y9+X9+W9 -> 0 | AF9: =ROUND((P9+Q9+R9+S9+T9-U9-V9+AE9),2) -> 18000 | AG9: =SUMIF(税后扣款!B:B,C9,税后扣款!E:E) -> 0 | AH9: =SUMIF(房租水电!A:A,C9,房租水电!C:C) -> 0 | AI9: =SUMIF(房租水电!A:A,C9,房租水电!D:D) -> 0 | AJ9: =SUMIF(税后扣款!B:B,C9,税后扣款!D:D) -> 0 | AK9: =AJ9+AI9+AH9+AG9 -> 0 | AL9: =SUMIF(社会保险!D:D,N9,社会保险!I:I) -> 1440 | AM9: =SUMIF(社会保险!D:D,N9,社会保险!J:J) -> 360 | AN9: =SUMIF(社会保险!D:D,N9,社会保险!K:K) -> 36 | AO9: =SUMIF(公积金!C:C,N9,公积金!L:L) -> 2160 | AP9: =SUMIF(专项扣除!$B:$B,$C9,专项扣除!D:D) -> 0 | AQ9: =SUMIF(专项扣除!$B:$B,$C9,专项扣除!E:E) -> 0 | AR9: =SUMIF(专项扣除!$B:$B,$C9,专项扣除!F:F) -> 0 | AS9: =SUMIF(专项扣除!$B:$B,$C9,专项扣除!G:G) -> 0 | AT9: =SUMIF(专项扣除!$B:$B,$C9,专项扣除!H:H) -> 0 | AU9: =SUMIF(专项扣除!$B:$B,$C9,专项扣除!I:I) -> 0 | AV9: =SUMIF(专项扣除!$B:$B,$C9,专项扣除!J:J) -> 0 | AW9: 5000 | AX9: =AL9+AM9+AN9+AO9+AW9 -> 8996 | AY9: =SUMIF(上月累计工资累计社保和公积金!C:C,C9,上月累计工资累计社保和公积金!E:E) -> 126300 | AZ9: =IF(E9="实习人员",(AY9+AF9)*80%,AY9+AF9) -> 144300 | BA9: =SUMIF(上月累计工资累计社保和公积金!C:C,C9,上月累计工资累计社保和公积金!K:K) -> 55412 | BB9: =BA9+AX9 -> 64408 | BC9: =ROUND(MAX((AZ9-BB9-AP9-AQ9-AR9-AS9-AT9-AU9-AV9)*0.01*{3,10,20,25,30,35,45}-{0,2520,16920,31920,52920,85920,181920},0),2) -> 5469.2 | BD9: =SUMIF(上月累计工资累计社保和公积金!C:C,C9,上月累计工资累计社保和公积金!L:L) -> 4568.8 | BE9: =IF((BC9-BD9)<0,0,((BC9-BD9))) -> 900.4 | BF9: =ROUND((AF9-AK9-BE9-AL9-AM9-AN9-AO9),2) -> 13103.6 | BH9: =VLOOKUP(C9,考勤!C:AL,36,0) -> ~@.com | BI9: =P9+Q9+R9+S9+T9-U9-V9+W9+X9+Y9+Z9+AA9+AB9+AC9+AD9-AG9-AH9-AI9-AJ9-AL9-AM9-AN9-AO9-BE9-BF9 -> 0
A10: =ROW()-2 -> 8 | B10: 创想悦动 | C10: SCX00008 | D10: 刘奎廷 | E10: 合同制人员 | F10: 创想悦动 | G10: 基础产品部 | H10: 45880 | J10: 创想悦动-研发 | K10: 计算机科学与技术 | L10: 1 | M10: 创想悦动-研发 | N10: 440921198308169216 | O10: 6214867555311811 | P10: 30000 | Q10: =ROUND(SUMIF(其他补发!B:B,$C10,其他补发!D:D),2) -> 0 | R10: =ROUND(SUMIF(其他补发!B:B,$C10,其他补发!H:H),2) -> 0 | S10: =ROUND(SUMIF(其他补发!B:B,$C10,其他补发!I:I),2) -> 0 | T10: =ROUND(SUMIF(其他补发!B:B,$C10,其他补发!E:E),2) -> 0 | U10: =ROUND((VLOOKUP(C10,考勤!C:H,6,0)+VLOOKUP(C10,考勤!C:O,13,0)+VLOOKUP(C10,考勤!C:P,14,0)*0.3+VLOOKUP(C10,考勤!C:AA,25,0))*(P10+Q10+R10)/21.75,2)+ROUND((VLOOKUP(C10,考勤!C:V,19,0)+VLOOKUP(C10,考勤!C:V,20,0))*(P10+Q10+R10-2520)/21.75,2) -> 0 | V10: =ROUND(SUMIF(动态表!C:C,C10,动态表!AA:AA)+SUMIFS(其他补发!L:L,其他补发!B:B,C10),2) -> 0 | W10: =ROUND(VLOOKUP(C10,考勤!C:K,9,0)*P10/21.75/8*2+VLOOKUP(C10,考勤!C:L,10,0)*P10/21.75/8*3,2)+SUMIFS(加班费!$H:$H,加班费!$D:$D,$C10) -> 0 | X10: =SUMIF(奖金!D:D,C10,奖金!F:F) -> 0 | Y10: =SUMIF(其他补发!B:B,C10,其他补发!J:J) -> 0 | Z10: =SUMIF(其他补发!B:B,C10,其他补发!F:F) -> 0 | AA10: =SUMIF(其他补发!B:B,C10,其他补发!G:G) -> 0 | AB10: =SUMIF(其他补发!B:B,C10,其他补发!M:M) -> 0 | AC10: =SUMIF(其他补发!B:B,C10,其他补发!N:N) -> 0 | AD10: =SUMIF(其他补发!B:B,C10,其他补发!K:K) -> 0 | AE10: =AD10+AC10+AB10+AA10+Z10+Y10+X10+W10 -> 0 | AF10: =ROUND((P10+Q10+R10+S10+T10-U10-V10+AE10),2) -> 30000 | AG10: =SUMIF(税后扣款!B:B,C10,税后扣款!E:E) -> 0 | AH10: =SUMIF(房租水电!A:A,C10,房租水电!C:C) -> 0 | AI10: =SUMIF(房租水电!A:A,C10,房租水电!D:D) -> 0 | AJ10: =SUMIF(税后扣款!B:B,C10,税后扣款!D:D) -> 0 | AK10: =AJ10+AI10+AH10+AG10 -> 0 | AL10: =SUMIF(社会保险!D:D,N10,社会保险!I:I) -> 2203.92 | AM10: =SUMIF(社会保险!D:D,N10,社会保险!J:J) -> 600 | AN10: =SUMIF(社会保险!D:D,N10,社会保险!K:K) -> 60 | AO10: =SUMIF(公积金!C:C,N10,公积金!L:L) -> 3600 | AP10: =SUMIF(专项扣除!$B:$B,$C10,专项扣除!D:D) -> 0 | AQ10: =SUMIF(专项扣除!$B:$B,$C10,专项扣除!E:E) -> 0 | AR10: =SUMIF(专项扣除!$B:$B,$C10,专项扣除!F:F) -> 0 | AS10: =SUMIF(专项扣除!$B:$B,$C10,专项扣除!G:G) -> 0 | AT10: =SUMIF(专项扣除!$B:$B,$C10,专项扣除!H:H) -> 0 | AU10: =SUMIF(专项扣除!$B:$B,$C10,专项扣除!I:I) -> 0 | AV10: =SUMIF(专项扣除!$B:$B,$C10,专项扣除!J:J) -> 0 | AW10: 5000 | AX10: =AL10+AM10+AN10+AO10+AW10 -> 11463.92 | AY10: =SUMIF(上月累计工资累计社保和公积金!C:C,C10,上月累计工资累计社保和公积金!E:E) -> 210300 | AZ10: =IF(E10="实习人员",(AY10+AF10)*80%,AY10+AF10) -> 240300 | BA10: =SUMIF(上月累计工资累计社保和公积金!C:C,C10,上月累计工资累计社保和公积金!K:K) -> 67647.44 | BB10: =BA10+AX10 -> 79111.36 | BC10: =ROUND(MAX((AZ10-BB10-AP10-AQ10-AR10-AS10-AT10-AU10-AV10)*0.01*{3,10,20,25,30,35,45}-{0,2520,16920,31920,52920,85920,181920},0),2) -> 15317.73 | BD10: =SUMIF(上月累计工资累计社保和公积金!C:C,C10,上月累计工资累计社保和公积金!L:L) -> 11745.26 | BE10: =IF((BC10-BD10)<0,0,((BC10-BD10))) -> 3572.47 | BF10: =ROUND((AF10-AK10-BE10-AL10-AM10-AN10-AO10),2) -> 19963.61 | BH10: =VLOOKUP(C10,考勤!C:AL,36,0) -> LiuKuiTing@.com | BI10: =P10+Q10+R10+S10+T10-U10-V10+W10+X10+Y10+Z10+AA10+AB10+AC10+AD10-AG10-AH10-AI10-AJ10-AL10-AM10-AN10-AO10-BE10-BF10 -> 0
A11: =ROW()-2 -> 9 | B11: 创想悦动 | C11: SCX00012 | D11: 张磊 | E11: 合同制人员 | F11: 创想悦动 | G11: 基础产品部 | H11: 45880 | J11: 创想悦动-研发 | K11: 计算机科学与技术 | L11: 1 | M11: 创想悦动-研发 | N11: 610422198511200056 | O11: 6225887837426135 | P11: 30000 | Q11: =ROUND(SUMIF(其他补发!B:B,$C11,其他补发!D:D),2) -> 0 | R11: =ROUND(SUMIF(其他补发!B:B,$C11,其他补发!H:H),2) -> 0 | S11: =ROUND(SUMIF(其他补发!B:B,$C11,其他补发!I:I),2) -> 0 | T11: =ROUND(SUMIF(其他补发!B:B,$C11,其他补发!E:E),2) -> 0 | U11: =ROUND((VLOOKUP(C11,考勤!C:H,6,0)+VLOOKUP(C11,考勤!C:O,13,0)+VLOOKUP(C11,考勤!C:P,14,0)*0.3+VLOOKUP(C11,考勤!C:AA,25,0))*(P11+Q11+R11)/21.75,2)+ROUND((VLOOKUP(C11,考勤!C:V,19,0)+VLOOKUP(C11,考勤!C:V,20,0))*(P11+Q11+R11-2520)/21.75,2) -> 0 | V11: =ROUND(SUMIF(动态表!C:C,C11,动态表!AA:AA)+SUMIFS(其他补发!L:L,其他补发!B:B,C11),2) -> 0 | W11: =ROUND(VLOOKUP(C11,考勤!C:K,9,0)*P11/21.75/8*2+VLOOKUP(C11,考勤!C:L,10,0)*P11/21.75/8*3,2)+SUMIFS(加班费!$H:$H,加班费!$D:$D,$C11) -> 0 | X11: =SUMIF(奖金!D:D,C11,奖金!F:F) -> 0 | Y11: =SUMIF(其他补发!B:B,C11,其他补发!J:J) -> 0 | Z11: =SUMIF(其他补发!B:B,C11,其他补发!F:F) -> 0 | AA11: =SUMIF(其他补发!B:B,C11,其他补发!G:G) -> 0 | AB11: =SUMIF(其他补发!B:B,C11,其他补发!M:M) -> 0 | AC11: =SUMIF(其他补发!B:B,C11,其他补发!N:N) -> 0 | AD11: =SUMIF(其他补发!B:B,C11,其他补发!K:K) -> 0 | AE11: =AD11+AC11+AB11+AA11+Z11+Y11+X11+W11 -> 0 | AF11: =ROUND((P11+Q11+R11+S11+T11-U11-V11+AE11),2) -> 30000 | AG11: =SUMIF(税后扣款!B:B,C11,税后扣款!E:E) -> 0 | AH11: =SUMIF(房租水电!A:A,C11,房租水电!C:C) -> 0 | AI11: =SUMIF(房租水电!A:A,C11,房租水电!D:D) -> 0 | AJ11: =SUMIF(税后扣款!B:B,C11,税后扣款!D:D) -> 0 | AK11: =AJ11+AI11+AH11+AG11 -> 0 | AL11: =SUMIF(社会保险!D:D,N11,社会保险!I:I) -> 2203.92 | AM11: =SUMIF(社会保险!D:D,N11,社会保险!J:J) -> 600 | AN11: =SUMIF(社会保险!D:D,N11,社会保险!K:K) -> 60 | AO11: =SUMIF(公积金!C:C,N11,公积金!L:L) -> 3600 | AP11: =SUMIF(专项扣除!$B:$B,$C11,专项扣除!D:D) -> 0 | AQ11: =SUMIF(专项扣除!$B:$B,$C11,专项扣除!E:E) -> 0 | AR11: =SUMIF(专项扣除!$B:$B,$C11,专项扣除!F:F) -> 0 | AS11: =SUMIF(专项扣除!$B:$B,$C11,专项扣除!G:G) -> 0 | AT11: =SUMIF(专项扣除!$B:$B,$C11,专项扣除!H:H) -> 0 | AU11: =SUMIF(专项扣除!$B:$B,$C11,专项扣除!I:I) -> 0 | AV11: =SUMIF(专项扣除!$B:$B,$C11,专项扣除!J:J) -> 0 | AW11: 5000 | AX11: =AL11+AM11+AN11+AO11+AW11 -> 11463.92 | AY11: =SUMIF(上月累计工资累计社保和公积金!C:C,C11,上月累计工资累计社保和公积金!E:E) -> 210300 | AZ11: =IF(E11="实习人员",(AY11+AF11)*80%,AY11+AF11) -> 240300 | BA11: =SUMIF(上月累计工资累计社保和公积金!C:C,C11,上月累计工资累计社保和公积金!K:K) -> 67647.44 | BB11: =BA11+AX11 -> 79111.36 | BC11: =ROUND(MAX((AZ11-BB11-AP11-AQ11-AR11-AS11-AT11-AU11-AV11)*0.01*{3,10,20,25,30,35,45}-{0,2520,16920,31920,52920,85920,181920},0),2) -> 15317.73 | BD11: =SUMIF(上月累计工资累计社保和公积金!C:C,C11,上月累计工资累计社保和公积金!L:L) -> 11745.26 | BE11: =IF((BC11-BD11)<0,0,((BC11-BD11))) -> 3572.47 | BF11: =ROUND((AF11-AK11-BE11-AL11-AM11-AN11-AO11),2) -> 19963.61 | BH11: =VLOOKUP(C11,考勤!C:AL,36,0) -> Red@youdoogo.com | BI11: =P11+Q11+R11+S11+T11-U11-V11+W11+X11+Y11+Z11+AA11+AB11+AC11+AD11-AG11-AH11-AI11-AJ11-AL11-AM11-AN11-AO11-BE11-BF11 -> 0
A12: =ROW()-2 -> 10 | B12: 创想悦动 | C12: SCX00014 | D12: 杨东升 | E12: 合同制人员 | F12: 创想悦动 | G12: 游戏研发部 | H12: 45880 | J12: 创想悦动-研发 | K12: 电子信息工程 | L12: 1 | M12: 创想悦动-研发 | N12: 610124199909050917 | O12: 6214830506177103 | P12: 20000 | Q12: =ROUND(SUMIF(其他补发!B:B,$C12,其他补发!D:D),2) -> 0 | R12: =ROUND(SUMIF(其他补发!B:B,$C12,其他补发!H:H),2) -> 0 | S12: =ROUND(SUMIF(其他补发!B:B,$C12,其他补发!I:I),2) -> 0 | T12: =ROUND(SUMIF(其他补发!B:B,$C12,其他补发!E:E),2) -> 0 | U12: =ROUND((VLOOKUP(C12,考勤!C:H,6,0)+VLOOKUP(C12,考勤!C:O,13,0)+VLOOKUP(C12,考勤!C:P,14,0)*0.3+VLOOKUP(C12,考勤!C:AA,25,0))*(P12+Q12+R12)/21.75,2)+ROUND((VLOOKUP(C12,考勤!C:V,19,0)+VLOOKUP(C12,考勤!C:V,20,0))*(P12+Q12+R12-2520)/21.75,2) -> 0 | V12: =ROUND(SUMIF(动态表!C:C,C12,动态表!AA:AA)+SUMIFS(其他补发!L:L,其他补发!B:B,C12),2) -> 0 | W12: =ROUND(VLOOKUP(C12,考勤!C:K,9,0)*P12/21.75/8*2+VLOOKUP(C12,考勤!C:L,10,0)*P12/21.75/8*3,2)+SUMIFS(加班费!$H:$H,加班费!$D:$D,$C12) -> 0 | X12: =SUMIF(奖金!D:D,C12,奖金!F:F) -> 0 | Y12: =SUMIF(其他补发!B:B,C12,其他补发!J:J) -> 0 | Z12: =SUMIF(其他补发!B:B,C12,其他补发!F:F) -> 0 | AA12: =SUMIF(其他补发!B:B,C12,其他补发!G:G) -> 0 | AB12: =SUMIF(其他补发!B:B,C12,其他补发!M:M) -> 0 | AC12: =SUMIF(其他补发!B:B,C12,其他补发!N:N) -> 0 | AD12: =SUMIF(其他补发!B:B,C12,其他补发!K:K) -> 0 | AE12: =AD12+AC12+AB12+AA12+Z12+Y12+X12+W12 -> 0 | AF12: =ROUND((P12+Q12+R12+S12+T12-U12-V12+AE12),2) -> 20000 | AG12: =SUMIF(税后扣款!B:B,C12,税后扣款!E:E) -> 0 | AH12: =SUMIF(房租水电!A:A,C12,房租水电!C:C) -> 0 | AI12: =SUMIF(房租水电!A:A,C12,房租水电!D:D) -> 0 | AJ12: =SUMIF(税后扣款!B:B,C12,税后扣款!D:D) -> 0 | AK12: =AJ12+AI12+AH12+AG12 -> 0 | AL12: =SUMIF(社会保险!D:D,N12,社会保险!I:I) -> 1600 | AM12: =SUMIF(社会保险!D:D,N12,社会保险!J:J) -> 400 | AN12: =SUMIF(社会保险!D:D,N12,社会保险!K:K) -> 40 | AO12: =SUMIF(公积金!C:C,N12,公积金!L:L) -> 1200 | AP12: =SUMIF(专项扣除!$B:$B,$C12,专项扣除!D:D) -> 0 | AQ12: =SUMIF(专项扣除!$B:$B,$C12,专项扣除!E:E) -> 0 | AR12: =SUMIF(专项扣除!$B:$B,$C12,专项扣除!F:F) -> 0 | AS12: =SUMIF(专项扣除!$B:$B,$C12,专项扣除!G:G) -> 0 | AT12: =SUMIF(专项扣除!$B:$B,$C12,专项扣除!H:H) -> 0 | AU12: =SUMIF(专项扣除!$B:$B,$C12,专项扣除!I:I) -> 0 | AV12: =SUMIF(专项扣除!$B:$B,$C12,专项扣除!J:J) -> 0 | AW12: 5000 | AX12: =AL12+AM12+AN12+AO12+AW12 -> 8240 | AY12: =SUMIF(上月累计工资累计社保和公积金!C:C,C12,上月累计工资累计社保和公积金!E:E) -> 140300 | AZ12: =IF(E12="实习人员",(AY12+AF12)*80%,AY12+AF12) -> 160300 | BA12: =SUMIF(上月累计工资累计社保和公积金!C:C,C12,上月累计工资累计社保和公积金!K:K) -> 57680 | BB12: =BA12+AX12 -> 65920 | BC12: =ROUND(MAX((AZ12-BB12-AP12-AQ12-AR12-AS12-AT12-AU12-AV12)*0.01*{3,10,20,25,30,35,45}-{0,2520,16920,31920,52920,85920,181920},0),2) -> 6918 | BD12: =SUMIF(上月累计工资累计社保和公积金!C:C,C12,上月累计工资累计社保和公积金!L:L) -> 5742 | BE12: =IF((BC12-BD12)<0,0,((BC12-BD12))) -> 1176 | BF12: =ROUND((AF12-AK12-BE12-AL12-AM12-AN12-AO12),2) -> 15584 | BH12: =VLOOKUP(C12,考勤!C:AL,36,0) -> ~@.com | BI12: =P12+Q12+R12+S12+T12-U12-V12+W12+X12+Y12+Z12+AA12+AB12+AC12+AD12-AG12-AH12-AI12-AJ12-AL12-AM12-AN12-AO12-BE12-BF12 -> 0
A13: =ROW()-2 -> 11 | B13: 创想悦动 | C13: SCX00015 | D13: 陈曦 | E13: 合同制人员 | F13: 创想悦动 | G13: 商务合作部 | H13: 45880 | J13: 创想悦动-销售 | K13: 计算机科学与技术 | L13: 1 | M13: 创想悦动-销售 | N13: 120106198508234519 | O13: 6226096550170206 | P13: 25000 | Q13: =ROUND(SUMIF(其他补发!B:B,$C13,其他补发!D:D),2) -> 0 | R13: =ROUND(SUMIF(其他补发!B:B,$C13,其他补发!H:H),2) -> 0 | S13: =ROUND(SUMIF(其他补发!B:B,$C13,其他补发!I:I),2) -> 0 | T13: =ROUND(SUMIF(其他补发!B:B,$C13,其他补发!E:E),2) -> 0 | U13: =ROUND((VLOOKUP(C13,考勤!C:H,6,0)+VLOOKUP(C13,考勤!C:O,13,0)+VLOOKUP(C13,考勤!C:P,14,0)*0.3+VLOOKUP(C13,考勤!C:AA,25,0))*(P13+Q13+R13)/21.75,2)+ROUND((VLOOKUP(C13,考勤!C:V,19,0)+VLOOKUP(C13,考勤!C:V,20,0))*(P13+Q13+R13-2520)/21.75,2) -> 0 | V13: =ROUND(SUMIF(动态表!C:C,C13,动态表!AA:AA)+SUMIFS(其他补发!L:L,其他补发!B:B,C13),2) -> 0 | W13: =ROUND(VLOOKUP(C13,考勤!C:K,9,0)*P13/21.75/8*2+VLOOKUP(C13,考勤!C:L,10,0)*P13/21.75/8*3,2)+SUMIFS(加班费!$H:$H,加班费!$D:$D,$C13) -> 0 | X13: =SUMIF(奖金!D:D,C13,奖金!F:F) -> 0 | Y13: =SUMIF(其他补发!B:B,C13,其他补发!J:J) -> 0 | Z13: =SUMIF(其他补发!B:B,C13,其他补发!F:F) -> 0 | AA13: =SUMIF(其他补发!B:B,C13,其他补发!G:G) -> 0 | AB13: =SUMIF(其他补发!B:B,C13,其他补发!M:M) -> 0 | AC13: =SUMIF(其他补发!B:B,C13,其他补发!N:N) -> 0 | AD13: =SUMIF(其他补发!B:B,C13,其他补发!K:K) -> 0 | AE13: =AD13+AC13+AB13+AA13+Z13+Y13+X13+W13 -> 0 | AF13: =ROUND((P13+Q13+R13+S13+T13-U13-V13+AE13),2) -> 25000 | AG13: =SUMIF(税后扣款!B:B,C13,税后扣款!E:E) -> 0 | AH13: =SUMIF(房租水电!A:A,C13,房租水电!C:C) -> 0 | AI13: =SUMIF(房租水电!A:A,C13,房租水电!D:D) -> 0 | AJ13: =SUMIF(税后扣款!B:B,C13,税后扣款!D:D) -> 0 | AK13: =AJ13+AI13+AH13+AG13 -> 0 | AL13: =SUMIF(社会保险!D:D,N13,社会保险!I:I) -> 2000 | AM13: =SUMIF(社会保险!D:D,N13,社会保险!J:J) -> 500 | AN13: =SUMIF(社会保险!D:D,N13,社会保险!K:K) -> 50 | AO13: =SUMIF(公积金!C:C,N13,公积金!L:L) -> 1500 | AP13: =SUMIF(专项扣除!$B:$B,$C13,专项扣除!D:D) -> 0 | AQ13: =SUMIF(专项扣除!$B:$B,$C13,专项扣除!E:E) -> 0 | AR13: =SUMIF(专项扣除!$B:$B,$C13,专项扣除!F:F) -> 0 | AS13: =SUMIF(专项扣除!$B:$B,$C13,专项扣除!G:G) -> 0 | AT13: =SUMIF(专项扣除!$B:$B,$C13,专项扣除!H:H) -> 0 | AU13: =SUMIF(专项扣除!$B:$B,$C13,专项扣除!I:I) -> 0 | AV13: =SUMIF(专项扣除!$B:$B,$C13,专项扣除!J:J) -> 0 | AW13: 5000 | AX13: =AL13+AM13+AN13+AO13+AW13 -> 9050 | AY13: =SUMIF(上月累计工资累计社保和公积金!C:C,C13,上月累计工资累计社保和公积金!E:E) -> 176050 | AZ13: =IF(E13="实习人员",(AY13+AF13)*80%,AY13+AF13) -> 201050 | BA13: =SUMIF(上月累计工资累计社保和公积金!C:C,C13,上月累计工资累计社保和公积金!K:K) -> 63350 | BB13: =BA13+AX13 -> 72400 | BC13: =ROUND(MAX((AZ13-BB13-AP13-AQ13-AR13-AS13-AT13-AU13-AV13)*0.01*{3,10,20,25,30,35,45}-{0,2520,16920,31920,52920,85920,181920},0),2) -> 10345 | BD13: =SUMIF(上月累计工资累计社保和公积金!C:C,C13,上月累计工资累计社保和公积金!L:L) -> 8750 | BE13: =IF((BC13-BD13)<0,0,((BC13-BD13))) -> 1595 | BF13: =ROUND((AF13-AK13-BE13-AL13-AM13-AN13-AO13),2) -> 19355 | BH13: =VLOOKUP(C13,考勤!C:AL,36,0) -> ～@.com | BI13: =P13+Q13+R13+S13+T13-U13-V13+W13+X13+Y13+Z13+AA13+AB13+AC13+AD13-AG13-AH13-AI13-AJ13-AL13-AM13-AN13-AO13-BE13-BF13 -> 0
A14: =ROW()-2 -> 12 | B14: 创想悦动 | C14: SCX00016 | D14: 胡豪 | E14: 合同制人员 | F14: 创想悦动 | G14: 游戏研发部 | H14: 45880 | J14: 创想悦动-研发 | K14: 生物技术 | L14: 1 | M14: 创想悦动-研发 | N14: 362401199603151514 | O14: 6214838652728835 | P14: 23000 | Q14: =ROUND(SUMIF(其他补发!B:B,$C14,其他补发!D:D),2) -> 0 | R14: =ROUND(SUMIF(其他补发!B:B,$C14,其他补发!H:H),2) -> 0 | S14: =ROUND(SUMIF(其他补发!B:B,$C14,其他补发!I:I),2) -> 0 | T14: =ROUND(SUMIF(其他补发!B:B,$C14,其他补发!E:E),2) -> 0 | U14: =ROUND((VLOOKUP(C14,考勤!C:H,6,0)+VLOOKUP(C14,考勤!C:O,13,0)+VLOOKUP(C14,考勤!C:P,14,0)*0.3+VLOOKUP(C14,考勤!C:AA,25,0))*(P14+Q14+R14)/21.75,2)+ROUND((VLOOKUP(C14,考勤!C:V,19,0)+VLOOKUP(C14,考勤!C:V,20,0))*(P14+Q14+R14-2520)/21.75,2) -> 0 | V14: =ROUND(SUMIF(动态表!C:C,C14,动态表!AA:AA)+SUMIFS(其他补发!L:L,其他补发!B:B,C14),2) -> 0 | W14: =ROUND(VLOOKUP(C14,考勤!C:K,9,0)*P14/21.75/8*2+VLOOKUP(C14,考勤!C:L,10,0)*P14/21.75/8*3,2)+SUMIFS(加班费!$H:$H,加班费!$D:$D,$C14) -> 0 | X14: =SUMIF(奖金!D:D,C14,奖金!F:F) -> 0 | Y14: =SUMIF(其他补发!B:B,C14,其他补发!J:J) -> 0 | Z14: =SUMIF(其他补发!B:B,C14,其他补发!F:F) -> 0 | AA14: =SUMIF(其他补发!B:B,C14,其他补发!G:G) -> 0 | AB14: =SUMIF(其他补发!B:B,C14,其他补发!M:M) -> 0 | AC14: =SUMIF(其他补发!B:B,C14,其他补发!N:N) -> 0 | AD14: =SUMIF(其他补发!B:B,C14,其他补发!K:K) -> 0 | AE14: =AD14+AC14+AB14+AA14+Z14+Y14+X14+W14 -> 0 | AF14: =ROUND((P14+Q14+R14+S14+T14-U14-V14+AE14),2) -> 23000 | AG14: =SUMIF(税后扣款!B:B,C14,税后扣款!E:E) -> 0 | AH14: =SUMIF(房租水电!A:A,C14,房租水电!C:C) -> 0 | AI14: =SUMIF(房租水电!A:A,C14,房租水电!D:D) -> 0 | AJ14: =SUMIF(税后扣款!B:B,C14,税后扣款!D:D) -> -160 | AK14: =AJ14+AI14+AH14+AG14 -> -160 | AL14: =SUMIF(社会保险!D:D,N14,社会保险!I:I) -> 1840 | AM14: =SUMIF(社会保险!D:D,N14,社会保险!J:J) -> 460 | AN14: =SUMIF(社会保险!D:D,N14,社会保险!K:K) -> 46 | AO14: =SUMIF(公积金!C:C,N14,公积金!L:L) -> 1380 | AP14: =SUMIF(专项扣除!$B:$B,$C14,专项扣除!D:D) -> 0 | AQ14: =SUMIF(专项扣除!$B:$B,$C14,专项扣除!E:E) -> 0 | AR14: =SUMIF(专项扣除!$B:$B,$C14,专项扣除!F:F) -> 0 | AS14: =SUMIF(专项扣除!$B:$B,$C14,专项扣除!G:G) -> 0 | AT14: =SUMIF(专项扣除!$B:$B,$C14,专项扣除!H:H) -> 0 | AU14: =SUMIF(专项扣除!$B:$B,$C14,专项扣除!I:I) -> 0 | AV14: =SUMIF(专项扣除!$B:$B,$C14,专项扣除!J:J) -> 0 | AW14: 5000 | AX14: =AL14+AM14+AN14+AO14+AW14 -> 8726 | AY14: =SUMIF(上月累计工资累计社保和公积金!C:C,C14,上月累计工资累计社保和公积金!E:E) -> 161182.76 | AZ14: =IF(E14="实习人员",(AY14+AF14)*80%,AY14+AF14) -> 184182.76 | BA14: =SUMIF(上月累计工资累计社保和公积金!C:C,C14,上月累计工资累计社保和公积金!K:K) -> 61082 | BB14: =BA14+AX14 -> 69808 | BC14: =ROUND(MAX((AZ14-BB14-AP14-AQ14-AR14-AS14-AT14-AU14-AV14)*0.01*{3,10,20,25,30,35,45}-{0,2520,16920,31920,52920,85920,181920},0),2) -> 8917.48 | BD14: =SUMIF(上月累计工资累计社保和公积金!C:C,C14,上月累计工资累计社保和公积金!L:L) -> 7490.08 | BE14: =IF((BC14-BD14)<0,0,((BC14-BD14))) -> 1427.4 | BF14: =ROUND((AF14-AK14-BE14-AL14-AM14-AN14-AO14),2) -> 18006.6 | BH14: =VLOOKUP(C14,考勤!C:AL,36,0) -> ~@.com | BI14: =P14+Q14+R14+S14+T14-U14-V14+W14+X14+Y14+Z14+AA14+AB14+AC14+AD14-AG14-AH14-AI14-AJ14-AL14-AM14-AN14-AO14-BE14-BF14 -> 0
... A80: =ROW()-2 -> 78 | B80: 创想悦动 | C80: SCX00096 | D80: 谢琰 | E80: 实习人员 | F80: 创想悦动 | G80: 平台运营部 | H80: 46234 | J80: 创想悦动-销售 | K80: 材料科学与工程 | L80: 1 | M80: 创想悦动-销售 | N80: 441827200202063628 | O80: 6214833691023108 | P80: 4000 | Q80: =ROUND(SUMIF(其他补发!B:B,$C80,其他补发!D:D),2) -> 0 | R80: =ROUND(SUMIF(其他补发!B:B,$C80,其他补发!H:H),2) -> 0 | S80: =ROUND(SUMIF(其他补发!B:B,$C80,其他补发!I:I),2) -> 0 | T80: =ROUND(SUMIF(其他补发!B:B,$C80,其他补发!E:E),2) -> 0 | U80: =ROUND((VLOOKUP(C80,考勤!C:H,6,0)+VLOOKUP(C80,考勤!C:O,13,0)+VLOOKUP(C80,考勤!C:P,14,0)*0.3+VLOOKUP(C80,考勤!C:AA,25,0))*(P80+Q80+R80)/21.75,2)+ROUND((VLOOKUP(C80,考勤!C:V,19,0)+VLOOKUP(C80,考勤!C:V,20,0))*(P80+Q80+R80-2520)/21.75,2) -> 3816.09 | V80: =ROUND(SUMIF(动态表!C:C,C80,动态表!AA:AA)+SUMIFS(其他补发!L:L,其他补发!B:B,C80),2) -> 0 | W80: =ROUND(VLOOKUP(C80,考勤!C:K,9,0)*P80/21.75/8*2+VLOOKUP(C80,考勤!C:L,10,0)*P80/21.75/8*3,2)+SUMIFS(加班费!$H:$H,加班费!$D:$D,$C80) -> 0 | X80: =SUMIF(奖金!D:D,C80,奖金!F:F) -> 0 | Y80: =SUMIF(其他补发!B:B,C80,其他补发!J:J) -> 0 | Z80: =SUMIF(其他补发!B:B,C80,其他补发!F:F) -> 0 | AA80: =SUMIF(其他补发!B:B,C80,其他补发!G:G) -> 0 | AB80: =SUMIF(其他补发!B:B,C80,其他补发!M:M) -> 0 | AC80: =SUMIF(其他补发!B:B,C80,其他补发!N:N) -> 0 | AD80: =SUMIF(其他补发!B:B,C80,其他补发!K:K) -> 0 | AE80: =AD80+AC80+AB80+AA80+Z80+Y80+X80+W80 -> 0 | AF80: =ROUND((P80+Q80+R80+S80+T80-U80-V80+AE80),2) -> 183.91 | AG80: =SUMIF(税后扣款!B:B,C80,税后扣款!E:E) -> 0 | AH80: =SUMIF(房租水电!A:A,C80,房租水电!C:C) -> 0 | AI80: =SUMIF(房租水电!A:A,C80,房租水电!D:D) -> 0 | AJ80: =SUMIF(税后扣款!B:B,C80,税后扣款!D:D) -> 0 | AK80: =AJ80+AI80+AH80+AG80 -> 0 | AL80: =SUMIF(社会保险!D:D,N80,社会保险!I:I) -> 0 | AM80: =SUMIF(社会保险!D:D,N80,社会保险!J:J) -> 0 | AN80: =SUMIF(社会保险!D:D,N80,社会保险!K:K) -> 0 | AO80: =SUMIF(公积金!C:C,N80,公积金!L:L) -> 0 | AP80: =SUMIF(专项扣除!$B:$B,$C80,专项扣除!D:D) -> 0 | AQ80: =SUMIF(专项扣除!$B:$B,$C80,专项扣除!E:E) -> 0 | AR80: =SUMIF(专项扣除!$B:$B,$C80,专项扣除!F:F) -> 0 | AS80: =SUMIF(专项扣除!$B:$B,$C80,专项扣除!G:G) -> 0 | AT80: =SUMIF(专项扣除!$B:$B,$C80,专项扣除!H:H) -> 0 | AU80: =SUMIF(专项扣除!$B:$B,$C80,专项扣除!I:I) -> 0 | AV80: =SUMIF(专项扣除!$B:$B,$C80,专项扣除!J:J) -> 0 | AW80: 5000 | AX80: =AL80+AM80+AN80+AO80+AW80 -> 5000 | AY80: =SUMIF(上月累计工资累计社保和公积金!C:C,C80,上月累计工资累计社保和公积金!E:E) -> 0 | AZ80: =IF(E80="实习人员",(AY80+AF80)*80%,AY80+AF80) -> 147.128 | BA80: =SUMIF(上月累计工资累计社保和公积金!C:C,C80,上月累计工资累计社保和公积金!K:K) -> 0 | BB80: =BA80+AX80 -> 5000 | BC80: =ROUND(MAX((AZ80-BB80-AP80-AQ80-AR80-AS80-AT80-AU80-AV80)*0.01*{3,10,20,25,30,35,45}-{0,2520,16920,31920,52920,85920,181920},0),2) -> 0 | BD80: =SUMIF(上月累计工资累计社保和公积金!C:C,C80,上月累计工资累计社保和公积金!L:L) -> 0 | BE80: =IF((BC80-BD80)<0,0,((BC80-BD80))) -> 0 | BF80: =ROUND((AF80-AK80-BE80-AL80-AM80-AN80-AO80),2) -> 183.91 | BH80: =VLOOKUP(C80,考勤!C:AL,36,0) -> Wind@youdoogo.com | BI80: =P80+Q80+R80+S80+T80-U80-V80+W80+X80+Y80+Z80+AA80+AB80+AC80+AD80-AG80-AH80-AI80-AJ80-AL80-AM80-AN80-AO80-BE80-BF80 -> 0
A83: 总计 | L83: =SUM(L3:L82) -> 78 | P83: =SUM(SUM(P3:P82)) -> 1790300 | Q83: =SUM(SUM(Q3:Q82)) -> 0 | R83: =SUM(SUM(R3:R82)) -> 0 | S83: =SUM(SUM(S3:S82)) -> 0 | T83: =SUM(SUM(T3:T82)) -> 0 | U83: =SUM(SUM(U3:U82)) -> 49494.26 | V83: =SUM(SUM(V3:V82)) -> 0 | W83: =SUM(SUM(W3:W82)) -> 0 | ... BF83: =SUM(SUM(BF3:BF82)) -> 1329965.5 | BI83: =P83+Q83+R83+S83+T83-U83-V83+W83+X83+Y83+Z83+AA83+AB83+AC83+AD83-AG83-AH83-AI83-AJ83-AL83-AM83-AN83-AO83-BE83-BF83 -> 0
B87: 制表： | H87: 财务部： | R87: 人力资源部总监审批： | Y87: 财务部总监审批： | AG87: 审批： | AO87: 审批：
F92: 总体检查 | P92: =P83-汇总!D9 -> 0 | Q92: =Q83-汇总!E9 -> 0 | R92: =R83-汇总!F9 -> 0 | S92: =S83-汇总!G9 -> 0 | T92: =T83-汇总!H9 -> 0 | U92: =U83-汇总!I9 -> 0 | V92: =V83-汇总!J9 -> 0 | W92: =W83-汇总!K9 -> 0 | ... AO92: =AO83-汇总!AC9 -> 0 | BE92: =BE83-汇总!AD9 -> 0 | BF92: =BF83-汇总!AE9 -> 0
B98: 原人数 | C98: 76
B99: 6月表往月离职需要发放 | C99: 0
B100: 6月离职 | C100: 4
B101: 7月入职 | C101: 6
B102: 往月离职需发薪 | C102: 0
B103: 校招生月中换合同 | C103: 0
B105: 当月人数合计 | C105: =C98-C99-C100+C101+C102-C103 -> 78
C107: =C98+C101-C100-C105 -> 0

Sheet 离职补偿-创想悦动
A1: 深圳创想悦动科技有限公司2026年7月离职补偿表
A2: 序号 | B2: 工号 | C2: 姓名 | D2: 组队 | E2: 成本中心 | F2: 卡号 | G2: 离职补偿金 | H2: 所得税 | I2: 其他扣款 | J2: 实发补偿金 | K2: 备注 | L2: 免税额 | M2: 应纳税额度
A3: 1 | D3: =VLOOKUP($B3,工资表明细!$C$2:$O$146,4,0) -> 0 | E3: =VLOOKUP($B3,工资表明细!$C$2:$O$146,11,0) -> 0 | F3: =VLOOKUP($B3,工资表明细!$C$2:$O$146,13,0) -> 0 | H3: =ROUND(MAX((M3)*0.01*{3,10,20,25,30,35,45}-{0,2520,16920,31920,52920,85920,181920},0),2) -> 0 | I3: 0 | J3: =G3-H3-I3 -> 0 | L3: 494262 | M3: =IF(G3-L3>0,G3-L3,0) -> 0
A4: 合计 | G4: =SUM(G3:G3) -> 0 | H4: =SUM(H3:H3) -> 0 | I4: =SUM(I3:I3) -> 0 | J4: =SUM(J3:J3) -> 0
A10: 制表：黄晓彤 | C10: 财务部：俞光武 | E10: 审批：金美娜 | G10: 审批：王茵 | I10: 审批：刘丹 | K10: 审批：赫旋

Sheet 动态表
T1: 1 | U1: 1 | Y1: 公式有调整，含绩效部分 | Z1: 1 | AA1: 基本工资+绩效工资扣款
A2: 序号 | B2: 公司 | C2: 工号 | D2: 姓名 | E2: 一级部门 | F2: 二级部门 | G2: 职位 | H2: 动态类型 | L2: 薪酬执行标准 | T2: 缺勤天数 | U2: 剩余结算年假天数 | V2: 剩余结算加班小时数 | W2: 变动日期 | X2: 备注 | Y2: 工资涨幅 | Z2: 变更前天数 | AA2: 扣款金额 | AB2: 身份证号码 | AC2: 工资卡号 | AD2: 手机号码 | AF2: 姓名检查1 | AG2: 检查
H3: 入职 | I3: 转正 | J3: 离职 | K3: 异动 | L3: 原薪资 | M3: 原岗位津贴 | N3: 现薪资 | O3: 现岗位津贴 | P3: 转正后薪资 | Q3: 转正后岗位津贴 | R3: 补发/扣发金额 | S3: 离职补偿 | AI3: 工资检查1 | AJ3: 校验 | AK3: 岗位津贴检查1 | AL3: 校验 | AM3: 入离职缺勤天数 | AN3: 校验 | AO3: 出现次数
A4: 1 | B4: 创想悦动 | C4: SCX00089 | D4: 麦汝琪 | E4: 创想悦动 | F4: 营销合作部 | G4: 商务经理 | H4: √ | N4: 8000 | P4: 8000 | T4: 0 | W4: 46204 | Y4: =IF(L4>0,(N4+O4)-(L4+M4),0) -> 0 | Z4: 0 | AA4: =ROUND(Y4/21.75*Z4,2) -> 0 | AB4: =VLOOKUP(C4,考勤!C:AH,32,0) -> 440306200211143224 | AC4: =VLOOKUP(C4,考勤!C:AI,33,0) -> 6214837889289025 | AD4: =VLOOKUP(C4,考勤!C:AK,35,0) -> 18123802382 | AF4: =VLOOKUP(C4,考勤!C:F,2,0) -> 麦汝琪 | AG4: =IF(D4=AF4,1) -> 1 | AI4: =VLOOKUP(C4,工资表明细!$C$2:$P$322,14,0) -> 8000 | AJ4: =AI4-N4 -> 0 | AK4: =VLOOKUP($C4,工资表明细!$C$2:$BF$322,16,0) -> 0 | AL4: =AK4-Q4 -> 0 | AM4: =VLOOKUP(C4,考勤!$C$2:$H$100,6,0) -> 0 | AN4: =AM4-T4 -> 0 | AO4: =COUNTIF(C:C,C4) -> 1
A5: 2 | B5: 创想悦动 | C5: SCX00088 | D5: 郑立文 | E5: 创想悦动 | F5: 品牌宣传组 | G5: 品牌经理 | H5: √ | N5: 24000 | P5: 24000 | T5: 2 | W5: 46206 | Y5: =IF(L5>0,(N5+O5)-(L5+M5),0) -> 0 | Z5: 0 | AA5: =ROUND(Y5/21.75*Z5,2) -> 0 | AB5: =VLOOKUP(C5,考勤!C:AH,32,0) -> 440103198110182443 | AC5: =VLOOKUP(C5,考勤!C:AI,33,0) -> 6214850206505908 | AD5: =VLOOKUP(C5,考勤!C:AK,35,0) -> 13824413431 | AF5: =VLOOKUP(C5,考勤!C:F,2,0) -> 郑立文 | AG5: =IF(D5=AF5,1) -> 1 | AI5: =VLOOKUP(C5,工资表明细!$C$2:$P$322,14,0) -> 24000 | AJ5: =AI5-N5 -> 0 | AK5: =VLOOKUP($C5,工资表明细!$C$2:$BF$322,16,0) -> 0 | AL5: =AK5-Q5 -> 0 | AM5: =VLOOKUP(C5,考勤!$C$2:$H$100,6,0) -> 2 | AN5: =AM5-T5 -> 0 | AO5: =COUNTIF(C:C,C5) -> 1
A6: 3 | B6: 创想悦动 | C6: SCX00090 | D6: 杨植清 | E6: 创想悦动 | F6: 游戏研发部 | G6: UI设计师 | H6: √ | N6: 22000 | P6: 22000 | T6: 10 | W6: 46218 | Y6: =IF(L6>0,(N6+O6)-(L6+M6),0) -> 0 | Z6: 0 | AA6: =ROUND(Y6/21.75*Z6,2) -> 0 | AB6: =VLOOKUP(C6,考勤!C:AH,32,0) -> 34118119951106182X | AC6: =VLOOKUP(C6,考勤!C:AI,33,0) -> 6214856552716569 | AD6: =VLOOKUP(C6,考勤!C:AK,35,0) -> 13713799617 | AF6: =VLOOKUP(C6,考勤!C:F,2,0) -> 杨植清 | AG6: =IF(D6=AF6,1) -> 1 | AI6: =VLOOKUP(C6,工资表明细!$C$2:$P$322,14,0) -> 22000 | AJ6: =AI6-N6 -> 0 | AK6: =VLOOKUP($C6,工资表明细!$C$2:$BF$322,16,0) -> 0 | AL6: =AK6-Q6 -> 0 | AM6: =VLOOKUP(C6,考勤!$C$2:$H$100,6,0) -> 10 | AN6: =AM6-T6 -> 0 | AO6: =COUNTIF(C:C,C6) -> 1
A7: 4 | B7: 创想悦动 | C7: SCX00092 | D7: 罗凯成 | E7: 创想悦动 | F7: 基础产品部 | G7: AI研发效能工程师 | H7: √ | N7: 20000 | P7: 20000 | T7: =21.75-12 -> 9.75 | W7: 46219 | Y7: =IF(L7>0,(N7+O7)-(L7+M7),0) -> 0 | Z7: 0 | AA7: =ROUND(Y7/21.75*Z7,2) -> 0 | AB7: =VLOOKUP(C7,考勤!C:AH,32,0) -> 440305200007093032 | AC7: =VLOOKUP(C7,考勤!C:AI,33,0) -> 6214851805509192 | AD7: =VLOOKUP(C7,考勤!C:AK,35,0) -> 18926598212 | AF7: =VLOOKUP(C7,考勤!C:F,2,0) -> 罗凯成 | AG7: =IF(D7=AF7,1) -> 1 | AI7: =VLOOKUP(C7,工资表明细!$C$2:$P$322,14,0) -> 20000 | AJ7: =AI7-N7 -> 0 | AK7: =VLOOKUP($C7,工资表明细!$C$2:$BF$322,16,0) -> 0 | AL7: =AK7-Q7 -> 0 | AM7: =VLOOKUP(C7,考勤!$C$2:$H$100,6,0) -> 9.75 | AN7: =AM7-T7 -> 0 | AO7: =COUNTIF(C:C,C7) -> 1
A8: 5 | B8: 创想悦动 | C8: SCX00094 | D8: 余宏伟 | E8: 创想悦动 | F8: 基础产品部 | G8: 产品策划 | H8: √ | N8: 26000 | P8: 26000 | T8: =21.75-5 -> 16.75 | W8: 46230 | Y8: =IF(L8>0,(N8+O8)-(L8+M8),0) -> 0 | Z8: 0 | AA8: =ROUND(Y8/21.75*Z8,2) -> 0 | AB8: =VLOOKUP(C8,考勤!C:AH,32,0) -> 441802199009226912 | AC8: =VLOOKUP(C8,考勤!C:AI,33,0) -> 6214830700285595 | AD8: =VLOOKUP(C8,考勤!C:AK,35,0) -> 18823858181 | AF8: =VLOOKUP(C8,考勤!C:F,2,0) -> 余宏伟 | AG8: =IF(D8=AF8,1) -> 1 | AI8: =VLOOKUP(C8,工资表明细!$C$2:$P$322,14,0) -> 26000 | AJ8: =AI8-N8 -> 0 | AK8: =VLOOKUP($C8,工资表明细!$C$2:$BF$322,16,0) -> 0 | AL8: =AK8-Q8 -> 0 | AM8: =VLOOKUP(C8,考勤!$C$2:$H$100,6,0) -> 16.75 | AN8: =AM8-T8 -> 0 | AO8: =COUNTIF(C:C,C8) -> 1
A9: 6 | B9: 创想悦动 | C9: SCX00096 | D9: 谢琰 | E9: 创想悦动 | F9: 平台运营部 | G9: 平台运营实习生 | H9: √ | N9: 4000 | P9: 4000 | T9: =21.75-1 -> 20.75 | W9: 46234 | Y9: =IF(L9>0,(N9+O9)-(L9+M9),0) -> 0 | Z9: 0 | AA9: =ROUND(Y9/21.75*Z9,2) -> 0 | AB9: =VLOOKUP(C9,考勤!C:AH,32,0) -> 441827200202063628 | AC9: =VLOOKUP(C9,考勤!C:AI,33,0) -> 6214833691023108 | AD9: =VLOOKUP(C9,考勤!C:AK,35,0) -> 13028890431 | AF9: =VLOOKUP(C9,考勤!C:F,2,0) -> 谢琰 | AG9: =IF(D9=AF9,1) -> 1 | AI9: =VLOOKUP(C9,工资表明细!$C$2:$P$322,14,0) -> 4000 | AJ9: =AI9-N9 -> 0 | AK9: =VLOOKUP($C9,工资表明细!$C$2:$BF$322,16,0) -> 0 | AL9: =AK9-Q9 -> 0 | AM9: =VLOOKUP(C9,考勤!$C$2:$H$100,6,0) -> 20.75 | AN9: =AM9-T9 -> 0 | AO9: =COUNTIF(C:C,C9) -> 1
N12: =SUM(N4:N11) -> 104000 | O12: =SUM(O4:O11) -> 0 | P12: =SUM(P4:P11) -> 104000 | Q12: =SUM(Q4:Q11) -> 0 | R12: =SUM(R4:R11) -> 0 | T12: =SUM(T4:T11) -> 59.25 | Y12: =SUM(Y4:Y11) -> 0 | Z12: =SUM(Z4:Z11) -> 0 | AA12: =SUM(AA4:AA11) -> 0
T13: =T12-考勤!H87 -> 0
Z14: 检查 | AA14: =AA12+其他补发!L14-工资表明细!V83 -> 0
B16: 待处理：
B17: 剩余调休小时结算 | C17: 无
B18: 剩余年假已结算 | C18: 无
B19: 工资表更新了 | C19: 1
B20: 入离职缺勤天数差异 | C20: 1
B21: 补偿金 | C21: 无

Sheet 考勤
A2: 序号 | B2: 日期 | C2: 工号 | D2: 姓名 | E2: 所属公司 | F2: 一级部门 | G2: 二级部门 | H2: 入离职缺勤天数 | I2: 剩余年假天数 | J2: 剩余调休(小时) | K2: 周末加班 | L2: 节假日加班 | M2: 平时额外加班 | N2: 年假 | O2: 事假 | P2: 病假 | Q2: 婚假 | R2: 产假 | S2: 陪产假 | T2: 丧假 | U2: 育儿假 | V2: 护理假 | W2: 调休 | X2: 公干 | Y2: 出差 | Z2: 旷工次数 | AA2: 全天未打卡(天) | AB2: 未打卡 | AC2: 10分钟(次) | AD2: 10-20分钟(次) | AE2: 20-30分钟(次) | AF2: 30-60分钟(次) | AG2: 累计时间(分钟) | AH2: 身份证号码 | AI2: 工资卡号 | AJ2: 成本中心 | 产品线 | AK2: 手机号码 | AL2: 邮箱 | AM2: 专业 | AN2: 员工子组 | AO2: 入职本公司时间 | AP2: 离职时间 | AR2: 基本工资 | AS2: 绩效工资 | AT2: 岗位津贴 | AU2: 检查-考勤扣款 | AV2: 检查-加班 | AW2: 加班费 | AX2: 缺勤天数 | AY2: 出勤系数 | AZ2: 次数 | BC2: 法定节假日加班费
A3: =ROW()-2 -> 1 | B3: 2026-07-01至2026-07-31 | C3: SCX00001 | D3: 刘丹 | E3: 创想悦动 | F3: 创想悦动 | K3: 0 | L3: 0 | N3: 0 | O3: 0 | P3: 0 | Q3: 0 | R3: 0 | S3: 0 | T3: 0 | U3: 0 | V3: 0 | W3: 0 | X3: 0 | Y3: 0 | AA3: 0 | AB3: 0 | AC3: 0 | AD3: 0 | AE3: 0 | AF3: 0 | AG3: 0 | AH3: 420502197605290638 | AI3: 6214855253515072 | AJ3: 创想悦动-管理 | AK3: 13699861466 | AL3: liudan@youdoogo.com | AM3: 计算机网络技术 | AN3: 合同制人员 | AO3: 2025-08-11 | AR3: =VLOOKUP($C3,工资表明细!$C$2:$Q$190,14,0) -> 50000 | AS3: =VLOOKUP($C3,工资表明细!$C$2:$Q$190,15,0) -> 0 | AT3: =SUMIFS(其他补发!H:H,其他补发!B:B,C3) -> 0 | AU3: =ROUND((AR3+AS3+AT3)/21.75*(H3+O3+P3*0.3+AA3),2)-VLOOKUP(C3,工资表明细!$C$2:$U$190,19,0) -> 0 | AV3: =ROUND(AR3/21.75/8*2*(K3+L3*3/2),2)+SUMIFS(加班费!H:H,加班费!D:D,C3)-VLOOKUP(C3,工资表明细!$C$2:$W$190,21,0) -> 0 | AW3: =ROUND(AR3/21.75/8*2*(K3+L3*3/2),2) -> 0 | AX3: =ROUND(SUM(H3,O3,P3*0.3,AA3),2) -> 0 | AY3: =ROUND(1-AX3/21.75,2) -> 1 | AZ3: =COUNTIF(C:C,C3) -> 1 | BA3: =VLOOKUP(C3,工资表明细!$C$2:$P$223,13,0) -> 6214855253515072 | BB3: =BA3=AI3 -> TRUE | BC3: =ROUND(AR3/21.75/8*3*L3,2) -> 0
A4: =ROW()-2 -> 2 | B4: 2026-07-01至2026-07-31 | C4: SCX00002 | D4: 李奕佳 | E4: 创想悦动 | F4: 创想悦动 | K4: 0 | L4: 0 | N4: 0 | O4: 0 | P4: 0 | Q4: 0 | R4: 0 | S4: 0 | T4: 0 | U4: 0 | V4: 0 | W4: 0 | X4: 0 | Y4: 0 | AA4: 0 | AB4: 0 | AC4: 0 | AD4: 0 | AE4: 0 | AF4: 0 | AG4: 0 | AH4: 330302200101050448 | AI4: 6214834366472596 | AJ4: 创想悦动-管理 | AK4: 18958823282 | AL4: liyijia@youdoogo.com | AM4: 生物化学与分子生物学 | AN4: 合同制人员 | AO4: 2025-08-11 | AR4: =VLOOKUP($C4,工资表明细!$C$2:$Q$190,14,0) -> 16000 | AS4: =VLOOKUP($C4,工资表明细!$C$2:$Q$190,15,0) -> 0 | AT4: =SUMIFS(其他补发!H:H,其他补发!B:B,C4) -> 0 | AU4: =ROUND((AR4+AS4+AT4)/21.75*(H4+O4+P4*0.3+AA4),2)-VLOOKUP(C4,工资表明细!$C$2:$U$190,19,0) -> 0 | AV4: =ROUND(AR4/21.75/8*2*(K4+L4*3/2),2)+SUMIFS(加班费!H:H,加班费!D:D,C4)-VLOOKUP(C4,工资表明细!$C$2:$W$190,21,0) -> 0 | AW4: =ROUND(AR4/21.75/8*2*(K4+L4*3/2),2) -> 0 | AX4: =ROUND(SUM(H4,O4,P4*0.3,AA4),2) -> 0 | AY4: =ROUND(1-AX4/21.75,2) -> 1 | AZ4: =COUNTIF(C:C,C4) -> 1 | BA4: =VLOOKUP(C4,工资表明细!$C$2:$P$223,13,0) -> 6214834366472596 | BB4: =BA4=AI4 -> TRUE | BC4: =ROUND(AR4/21.75/8*3*L4,2) -> 0
A5: =ROW()-2 -> 3 | B5: 2026-07-01至2026-07-31 | C5: SCX00003 | D5: 申华 | E5: 创想悦动 | F5: 创想悦动 | K5: 0 | L5: 0 | N5: 0 | O5: 0 | P5: 0 | Q5: 0 | R5: 0 | S5: 0 | T5: 0 | U5: 0 | V5: 0 | W5: 0 | X5: 0 | Y5: 0 | AA5: 0 | AB5: 0 | AC5: 0 | AD5: 0 | AE5: 0 | AF5: 0 | AG5: 0 | AH5: 610121198412260077 | AI5: 6226096554090061 | AJ5: 创想悦动-管理 | AK5: 13510424369 | AL5: ~@.com | AM5: 计算机科学与技术 | AN5: 合同制人员 | AO5: 2025-08-11 | AR5: =VLOOKUP($C5,工资表明细!$C$2:$Q$190,14,0) -> 50000 | AS5: =VLOOKUP($C5,工资表明细!$C$2:$Q$190,15,0) -> 0 | AT5: =SUMIFS(其他补发!H:H,其他补发!B:B,C5) -> 0 | AU5: =ROUND((AR5+AS5+AT5)/21.75*(H5+O5+P5*0.3+AA5),2)-VLOOKUP(C5,工资表明细!$C$2:$U$190,19,0) -> 0 | AV5: =ROUND(AR5/21.75/8*2*(K5+L5*3/2),2)+SUMIFS(加班费!H:H,加班费!D:D,C5)-VLOOKUP(C5,工资表明细!$C$2:$W$190,21,0) -> 0 | AW5: =ROUND(AR5/21.75/8*2*(K5+L5*3/2),2) -> 0 | AX5: =ROUND(SUM(H5,O5,P5*0.3,AA5),2) -> 0 | AY5: =ROUND(1-AX5/21.75,2) -> 1 | AZ5: =COUNTIF(C:C,C5) -> 1 | BA5: =VLOOKUP(C5,工资表明细!$C$2:$P$223,13,0) -> 6226096554090061 | BB5: =BA5=AI5 -> TRUE | BC5: =ROUND(AR5/21.75/8*3*L5,2) -> 0
A6: =ROW()-2 -> 4 | B6: 2026-07-01至2026-07-31 | C6: SCX00004 | D6: 杨晓波 | E6: 创想悦动 | F6: 创想悦动 | K6: 0 | L6: 0 | N6: 0 | O6: 0 | P6: 0 | Q6: 0 | R6: 0 | S6: 0 | T6: 0 | U6: 0 | V6: 0 | W6: 0 | X6: 0 | Y6: 0 | AA6: 0 | AB6: 0 | AC6: 0 | AD6: 0 | AE6: 0 | AF6: 0 | AG6: 0 | AH6: 440881198504087112 | AI6: 6225887813978158 | AJ6: 创想悦动-管理 | AK6: 13510601107 | AL6: yangxiaobo@youdoogo.com | AM6: 卡通动画 | AN6: 合同制人员 | AO6: 2025-08-11 | AR6: =VLOOKUP($C6,工资表明细!$C$2:$Q$190,14,0) -> 48000 | AS6: =VLOOKUP($C6,工资表明细!$C$2:$Q$190,15,0) -> 0 | AT6: =SUMIFS(其他补发!H:H,其他补发!B:B,C6) -> 0 | AU6: =ROUND((AR6+AS6+AT6)/21.75*(H6+O6+P6*0.3+AA6),2)-VLOOKUP(C6,工资表明细!$C$2:$U$190,19,0) -> 0 | AV6: =ROUND(AR6/21.75/8*2*(K6+L6*3/2),2)+SUMIFS(加班费!H:H,加班费!D:D,C6)-VLOOKUP(C6,工资表明细!$C$2:$W$190,21,0) -> 0 | AW6: =ROUND(AR6/21.75/8*2*(K6+L6*3/2),2) -> 0 | AX6: =ROUND(SUM(H6,O6,P6*0.3,AA6),2) -> 0 | AY6: =ROUND(1-AX6/21.75,2) -> 1 | AZ6: =COUNTIF(C:C,C6) -> 1 | BA6: =VLOOKUP(C6,工资表明细!$C$2:$P$223,13,0) -> 6225887813978158 | BB6: =BA6=AI6 -> TRUE | BC6: =ROUND(AR6/21.75/8*3*L6,2) -> 0
A7: =ROW()-2 -> 5 | B7: 2026-07-01至2026-07-31 | C7: SCX00005 | D7: 杨振 | E7: 创想悦动 | F7: 创想悦动 | K7: 0 | L7: 0 | N7: 0 | O7: 0 | P7: 0 | Q7: 0 | R7: 0 | S7: 0 | T7: 0 | U7: 0 | V7: 0 | W7: 0 | X7: 0 | Y7: 0 | AA7: 0 | AB7: 0 | AC7: 0 | AD7: 0 | AE7: 0 | AF7: 0 | AG7: 0 | AH7: 110105197902051515 | AI7: 6225886552211318 | AJ7: 创想悦动-研发 | AK7: 18665841772 | AL7: ~@.com | AM7: 汉语言文学 | AN7: 合同制人员 | AO7: 2025-08-11 | AR7: =VLOOKUP($C7,工资表明细!$C$2:$Q$190,14,0) -> 45000 | AS7: =VLOOKUP($C7,工资表明细!$C$2:$Q$190,15,0) -> 0 | AT7: =SUMIFS(其他补发!H:H,其他补发!B:B,C7) -> 0 | AU7: =ROUND((AR7+AS7+AT7)/21.75*(H7+O7+P7*0.3+AA7),2)-VLOOKUP(C7,工资表明细!$C$2:$U$190,19,0) -> 0 | AV7: =ROUND(AR7/21.75/8*2*(K7+L7*3/2),2)+SUMIFS(加班费!H:H,加班费!D:D,C7)-VLOOKUP(C7,工资表明细!$C$2:$W$190,21,0) -> 0 | AW7: =ROUND(AR7/21.75/8*2*(K7+L7*3/2),2) -> 0 | AX7: =ROUND(SUM(H7,O7,P7*0.3,AA7),2) -> 0 | AY7: =ROUND(1-AX7/21.75,2) -> 1 | AZ7: =COUNTIF(C:C,C7) -> 1 | BA7: =VLOOKUP(C7,工资表明细!$C$2:$P$223,13,0) -> 6225886552211318 | BB7: =BA7=AI7 -> TRUE | BC7: =ROUND(AR7/21.75/8*3*L7,2) -> 0
A8: =ROW()-2 -> 6 | B8: 2026-07-01至2026-07-31 | C8: SCX00006 | D8: 蔡昕宇 | E8: 创想悦动 | F8: 创想悦动 | K8: 0 | L8: 0 | N8: 0 | O8: 0 | P8: 0 | Q8: 0 | R8: 0 | S8: 0 | T8: 0 | U8: 0 | V8: 0 | W8: 0 | X8: 0 | Y8: 0 | AA8: 0 | AB8: 0 | AC8: 0 | AD8: 0 | AE8: 0 | AF8: 0 | AG8: 0 | AH8: 210102198602153412 | AI8: 6214867829480822 | AJ8: 创想悦动-管理 | AK8: 13714948663 | AL8: Simon@youdoogo.com | AM8: 网络工程 | AN8: 合同制人员 | AO8: 2025-08-11 | AR8: =VLOOKUP($C8,工资表明细!$C$2:$Q$190,14,0) -> 38000 | AS8: =VLOOKUP($C8,工资表明细!$C$2:$Q$190,15,0) -> 0 | AT8: =SUMIFS(其他补发!H:H,其他补发!B:B,C8) -> 0 | AU8: =ROUND((AR8+AS8+AT8)/21.75*(H8+O8+P8*0.3+AA8),2)-VLOOKUP(C8,工资表明细!$C$2:$U$190,19,0) -> 0 | AV8: =ROUND(AR8/21.75/8*2*(K8+L8*3/2),2)+SUMIFS(加班费!H:H,加班费!D:D,C8)-VLOOKUP(C8,工资表明细!$C$2:$W$190,21,0) -> 0 | AW8: =ROUND(AR8/21.75/8*2*(K8+L8*3/2),2) -> 0 | AX8: =ROUND(SUM(H8,O8,P8*0.3,AA8),2) -> 0 | AY8: =ROUND(1-AX8/21.75,2) -> 1 | AZ8: =COUNTIF(C:C,C8) -> 1 | BA8: =VLOOKUP(C8,工资表明细!$C$2:$P$223,13,0) -> 6214867829480822 | BB8: =BA8=AI8 -> TRUE | BC8: =ROUND(AR8/21.75/8*3*L8,2) -> 0
A9: =ROW()-2 -> 7 | B9: 2026-07-01至2026-07-31 | C9: SCX00007 | D9: 廖斌 | E9: 创想悦动 | F9: 创想悦动 | K9: 0 | L9: 0 | N9: 0 | O9: 0 | P9: 0 | Q9: 0 | R9: 0 | S9: 0 | T9: 0 | U9: 0 | V9: 0 | W9: 0 | X9: 0 | Y9: 0 | AA9: 0 | AB9: 0 | AC9: 0 | AD9: 0 | AE9: 0 | AF9: 0 | AG9: 0 | AH9: 350824199212280012 | AI9: 6214851800394657 | AJ9: 创想悦动-研发 | AK9: 15625232480 | AL9: ~@.com | AM9: 经济管理学 | AN9: 合同制人员 | AO9: 2025-08-11 | AR9: =VLOOKUP($C9,工资表明细!$C$2:$Q$190,14,0) -> 18000 | AS9: =VLOOKUP($C9,工资表明细!$C$2:$Q$190,15,0) -> 0 | AT9: =SUMIFS(其他补发!H:H,其他补发!B:B,C9) -> 0 | AU9: =ROUND((AR9+AS9+AT9)/21.75*(H9+O9+P9*0.3+AA9),2)-VLOOKUP(C9,工资表明细!$C$2:$U$190,19,0) -> 0 | AV9: =ROUND(AR9/21.75/8*2*(K9+L9*3/2),2)+SUMIFS(加班费!H:H,加班费!D:D,C9)-VLOOKUP(C9,工资表明细!$C$2:$W$190,21,0) -> 0 | AW9: =ROUND(AR9/21.75/8*2*(K9+L9*3/2),2) -> 0 | AX9: =ROUND(SUM(H9,O9,P9*0.3,AA9),2) -> 0 | AY9: =ROUND(1-AX9/21.75,2) -> 1 | AZ9: =COUNTIF(C:C,C9) -> 1 | BA9: =VLOOKUP(C9,工资表明细!$C$2:$P$223,13,0) -> 6214851800394657 | BB9: =BA9=AI9 -> TRUE | BC9: =ROUND(AR9/21.75/8*3*L9,2) -> 0
A10: =ROW()-2 -> 8 | B10: 2026-07-01至2026-07-31 | C10: SCX00008 | D10: 刘奎廷 | E10: 创想悦动 | F10: 创想悦动 | K10: 0 | L10: 0 | N10: 0 | O10: 0 | P10: 0 | Q10: 0 | R10: 0 | S10: 0 | T10: 0 | U10: 0 | V10: 0 | W10: 0 | X10: 0 | Y10: 0 | AA10: 0 | AB10: 0 | AC10: 0 | AD10: 0 | AE10: 0 | AF10: 0 | AG10: 0 | AH10: 440921198308169216 | AI10: 6214867555311811 | AJ10: 创想悦动-研发 | AK10: 18998942328 | AL10: LiuKuiTing@.com | AM10: 计算机科学与技术 | AN10: 合同制人员 | AO10: 2025-08-11 | AR10: =VLOOKUP($C10,工资表明细!$C$2:$Q$190,14,0) -> 30000 | AS10: =VLOOKUP($C10,工资表明细!$C$2:$Q$190,15,0) -> 0 | AT10: =SUMIFS(其他补发!H:H,其他补发!B:B,C10) -> 0 | AU10: =ROUND((AR10+AS10+AT10)/21.75*(H10+O10+P10*0.3+AA10),2)-VLOOKUP(C10,工资表明细!$C$2:$U$190,19,0) -> 0 | AV10: =ROUND(AR10/21.75/8*2*(K10+L10*3/2),2)+SUMIFS(加班费!H:H,加班费!D:D,C10)-VLOOKUP(C10,工资表明细!$C$2:$W$190,21,0) -> 0 | AW10: =ROUND(AR10/21.75/8*2*(K10+L10*3/2),2) -> 0 | AX10: =ROUND(SUM(H10,O10,P10*0.3,AA10),2) -> 0 | AY10: =ROUND(1-AX10/21.75,2) -> 1 | AZ10: =COUNTIF(C:C,C10) -> 1 | BA10: =VLOOKUP(C10,工资表明细!$C$2:$P$223,13,0) -> 6214867555311811 | BB10: =BA10=AI10 -> TRUE | BC10: =ROUND(AR10/21.75/8*3*L10,2) -> 0
A11: =ROW()-2 -> 9 | B11: 2026-07-01至2026-07-31 | C11: SCX00012 | D11: 张磊 | E11: 创想悦动 | F11: 创想悦动 | K11: 0 | L11: 0 | N11: 0 | O11: 0 | P11: 0 | Q11: 0 | R11: 0 | S11: 0 | T11: 0 | U11: 0 | V11: 0 | W11: 0 | X11: 0 | Y11: 0 | AA11: 0 | AB11: 0 | AC11: 0 | AD11: 0 | AE11: 0 | AF11: 0 | AG11: 0 | AH11: 610422198511200056 | AI11: 6225887837426135 | AJ11: 创想悦动-研发 | AK11: 13714109494 | AL11: Red@youdoogo.com | AM11: 计算机科学与技术 | AN11: 合同制人员 | AO11: 2025-08-11 | AR11: =VLOOKUP($C11,工资表明细!$C$2:$Q$190,14,0) -> 30000 | AS11: =VLOOKUP($C11,工资表明细!$C$2:$Q$190,15,0) -> 0 | AT11: =SUMIFS(其他补发!H:H,其他补发!B:B,C11) -> 0 | AU11: =ROUND((AR11+AS11+AT11)/21.75*(H11+O11+P11*0.3+AA11),2)-VLOOKUP(C11,工资表明细!$C$2:$U$190,19,0) -> 0 | AV11: =ROUND(AR11/21.75/8*2*(K11+L11*3/2),2)+SUMIFS(加班费!H:H,加班费!D:D,C11)-VLOOKUP(C11,工资表明细!$C$2:$W$190,21,0) -> 0 | AW11: =ROUND(AR11/21.75/8*2*(K11+L11*3/2),2) -> 0 | AX11: =ROUND(SUM(H11,O11,P11*0.3,AA11),2) -> 0 | AY11: =ROUND(1-AX11/21.75,2) -> 1 | AZ11: =COUNTIF(C:C,C11) -> 1 | BA11: =VLOOKUP(C11,工资表明细!$C$2:$P$223,13,0) -> 6225887837426135 | BB11: =BA11=AI11 -> TRUE | BC11: =ROUND(AR11/21.75/8*3*L11,2) -> 0
A12: =ROW()-2 -> 10 | B12: 2026-07-01至2026-07-31 | C12: SCX00014 | D12: 杨东升 | E12: 创想悦动 | F12: 创想悦动 | K12: 0 | L12: 0 | N12: 0 | O12: 0 | P12: 0 | Q12: 0 | R12: 0 | S12: 0 | T12: 0 | U12: 0 | V12: 0 | W12: 0 | X12: 0 | Y12: 0 | AA12: 0 | AB12: 0 | AC12: 0 | AD12: 0 | AE12: 0 | AF12: 0 | AG12: 0 | AH12: 610124199909050917 | AI12: 6214830506177103 | AJ12: 创想悦动-研发 | AK12: 17392236208 | AL12: ~@.com | AM12: 电子信息工程 | AN12: 合同制人员 | AO12: 2025-08-11 | AR12: =VLOOKUP($C12,工资表明细!$C$2:$Q$190,14,0) -> 20000 | AS12: =VLOOKUP($C12,工资表明细!$C$2:$Q$190,15,0) -> 0 | AT12: =SUMIFS(其他补发!H:H,其他补发!B:B,C12) -> 0 | AU12: =ROUND((AR12+AS12+AT12)/21.75*(H12+O12+P12*0.3+AA12),2)-VLOOKUP(C12,工资表明细!$C$2:$U$190,19,0) -> 0 | AV12: =ROUND(AR12/21.75/8*2*(K12+L12*3/2),2)+SUMIFS(加班费!H:H,加班费!D:D,C12)-VLOOKUP(C12,工资表明细!$C$2:$W$190,21,0) -> 0 | AW12: =ROUND(AR12/21.75/8*2*(K12+L12*3/2),2) -> 0 | AX12: =ROUND(SUM(H12,O12,P12*0.3,AA12),2) -> 0 | AY12: =ROUND(1-AX12/21.75,2) -> 1 | AZ12: =COUNTIF(C:C,C12) -> 1 | BA12: =VLOOKUP(C12,工资表明细!$C$2:$P$223,13,0) -> 6214830506177103 | BB12: =BA12=AI12 -> TRUE | BC12: =ROUND(AR12/21.75/8*3*L12,2) -> 0
A13: =ROW()-2 -> 11 | B13: 2026-07-01至2026-07-31 | C13: SCX00015 | D13: 陈曦 | E13: 创想悦动 | F13: 创想悦动 | K13: 0 | L13: 0 | N13: 0 | O13: 0 | P13: 0 | Q13: 0 | R13: 0 | S13: 0 | T13: 0 | U13: 0 | V13: 0 | W13: 0 | X13: 0 | Y13: 0 | AA13: 0 | AB13: 0 | AC13: 0 | AD13: 0 | AE13: 0 | AF13: 0 | AG13: 0 | AH13: 120106198508234519 | AI13: 6226096550170206 | AJ13: 创想悦动-销售 | AK13: 13751198880 | AL13: ～@.com | AM13: 计算机科学与技术 | AN13: 合同制人员 | AO13: 2025-08-11 | AR13: =VLOOKUP($C13,工资表明细!$C$2:$Q$190,14,0) -> 25000 | AS13: =VLOOKUP($C13,工资表明细!$C$2:$Q$190,15,0) -> 0 | AT13: =SUMIFS(其他补发!H:H,其他补发!B:B,C13) -> 0 | AU13: =ROUND((AR13+AS13+AT13)/21.75*(H13+O13+P13*0.3+AA13),2)-VLOOKUP(C13,工资表明细!$C$2:$U$190,19,0) -> 0 | AV13: =ROUND(AR13/21.75/8*2*(K13+L13*3/2),2)+SUMIFS(加班费!H:H,加班费!D:D,C13)-VLOOKUP(C13,工资表明细!$C$2:$W$190,21,0) -> 0 | AW13: =ROUND(AR13/21.75/8*2*(K13+L13*3/2),2) -> 0 | AX13: =ROUND(SUM(H13,O13,P13*0.3,AA13),2) -> 0 | AY13: =ROUND(1-AX13/21.75,2) -> 1 | AZ13: =COUNTIF(C:C,C13) -> 1 | BA13: =VLOOKUP(C13,工资表明细!$C$2:$P$223,13,0) -> 6226096550170206 | BB13: =BA13=AI13 -> TRUE | BC13: =ROUND(AR13/21.75/8*3*L13,2) -> 0
A14: =ROW()-2 -> 12 | B14: 2026-07-01至2026-07-31 | C14: SCX00016 | D14: 胡豪 | E14: 创想悦动 | F14: 创想悦动 | K14: 0 | L14: 0 | N14: 0 | O14: 0 | P14: 0 | Q14: 0 | R14: 0 | S14: 0 | T14: 0 | U14: 0 | V14: 0 | W14: 0 | X14: 0 | Y14: 0 | AA14: 0 | AB14: 0 | AC14: 0 | AD14: 0 | AE14: 0 | AF14: 0 | AG14: 0 | AH14: 362401199603151514 | AI14: 6214838652728835 | AJ14: 创想悦动-研发 | AK14: 18926768695 | AL14: ~@.com | AM14: 生物技术 | AN14: 合同制人员 | AO14: 2025-08-11 | AR14: =VLOOKUP($C14,工资表明细!$C$2:$Q$190,14,0) -> 23000 | AS14: =VLOOKUP($C14,工资表明细!$C$2:$Q$190,15,0) -> 0 | AT14: =SUMIFS(其他补发!H:H,其他补发!B:B,C14) -> 0 | AU14: =ROUND((AR14+AS14+AT14)/21.75*(H14+O14+P14*0.3+AA14),2)-VLOOKUP(C14,工资表明细!$C$2:$U$190,19,0) -> 0 | AV14: =ROUND(AR14/21.75/8*2*(K14+L14*3/2),2)+SUMIFS(加班费!H:H,加班费!D:D,C14)-VLOOKUP(C14,工资表明细!$C$2:$W$190,21,0) -> 0 | AW14: =ROUND(AR14/21.75/8*2*(K14+L14*3/2),2) -> 0 | AX14: =ROUND(SUM(H14,O14,P14*0.3,AA14),2) -> 0 | AY14: =ROUND(1-AX14/21.75,2) -> 1 | AZ14: =COUNTIF(C:C,C14) -> 1 | BA14: =VLOOKUP(C14,工资表明细!$C$2:$P$223,13,0) -> 6214838652728835 | BB14: =BA14=AI14 -> TRUE | BC14: =ROUND(AR14/21.75/8*3*L14,2) -> 0
... A17: =ROW()-2 -> 15 | B17: 2026-07-01至2026-07-31 | C17: SCX00019 | D17: 张文文 | E17: 创想悦动 | F17: 创想悦动 | K17: 0 | L17: 0 | N17: 0 | O17: 0 | P17: 0 | Q17: 0 | R17: 0 | S17: 0 | T17: 0 | U17: 0 | V17: 0 | W17: 0 | X17: 0 | Y17: 0 | AA17: 0 | AB17: 0 | AC17: 0 | AD17: 0 | AE17: 0 | AF17: 0 | AG17: 0 | AH17: 513029199704234064 | AI17: 6214830709967581 | AJ17: 创想悦动-研发 | AK17: 18328701198 | AL17: Cecilia@youdoogo.com | AM17: 动画 | AN17: 合同制人员 | AO17: 2025-08-25 | AR17: =VLOOKUP($C17,工资表明细!$C$2:$Q$190,14,0) -> 16000 | AS17: =VLOOKUP($C17,工资表明细!$C$2:$Q$190,15,0) -> 0 | AT17: =SUMIFS(其他补发!H:H,其他补发!B:B,C17) -> 0 | AU17: =ROUND((AR17+AS17+AT17)/21.75*(H17+O17+P17*0.3+AA17),2)-VLOOKUP(C17,工资表明细!$C$2:$U$190,19,0) -> 0 | AV17: =ROUND(AR17/21.75/8*2*(K17+L17*3/2),2)+SUMIFS(加班费!H:H,加班费!D:D,C17)-VLOOKUP(C17,工资表明细!$C$2:$W$190,21,0) -> 0 | AW17: =ROUND(AR17/21.75/8*2*(K17+L17*3/2),2) -> 0 | AX17: =ROUND(SUM(H17,O17,P17*0.3,AA17),2) -> 0 | AY17: =ROUND(1-AX17/21.75,2) -> 1 | AZ17: =COUNTIF(C:C,C17) -> 1 | BA17: =VLOOKUP(C17,工资表明细!$C$2:$P$223,13,0) -> 6214830709967581 | BB17: =BA17=AI17 -> TRUE | BC17: =ROUND(AR17/21.75/8*3*L17,2) -> 0
A18: =ROW()-2 -> 16 | B18: 2026-07-01至2026-07-31 | C18: SCX00021 | D18: 刘禹豪 | E18: 创想悦动 | F18: 创想悦动 | G18: 公共设计组 | K18: 0 | L18: 0 | N18: 0 | O18: 0 | P18: 0 | Q18: 0 | R18: 0 | S18: 0 | T18: 0 | U18: 0 | V18: 0 | W18: 0 | X18: 0 | Y18: 0 | AA18: 0 | AB18: 0 | AC18: 0 | AD18: 0 | AE18: 0 | AF18: 0 | AG18: 0 | AH18: 220402199004240017 | AI18: 6226097802044165 | AJ18: 创想悦动-销售 | AK18: 13421811800 | AL18: Yuhoooooo@youdoogo.com | AM18: 物流管理 | AN18: 合同制人员 | AO18: 2025-09-03 | AR18: =VLOOKUP($C18,工资表明细!$C$2:$Q$190,14,0) -> 27000 | AS18: =VLOOKUP($C18,工资表明细!$C$2:$Q$190,15,0) -> 0 | AT18: =SUMIFS(其他补发!H:H,其他补发!B:B,C18) -> 0 | AU18: =ROUND((AR18+AS18+AT18)/21.75*(H18+O18+P18*0.3+AA18),2)-VLOOKUP(C18,工资表明细!$C$2:$U$190,19,0) -> 0 | AV18: =ROUND(AR18/21.75/8*2*(K18+L18*3/2),2)+SUMIFS(加班费!H:H,加班费!D:D,C18)-VLOOKUP(C18,工资表明细!$C$2:$W$190,21,0) -> 0 | AW18: =ROUND(AR18/21.75/8*2*(K18+L18*3/2),2) -> 0 | AX18: =ROUND(SUM(H18,O18,P18*0.3,AA18),2) -> 0 | AY18: =ROUND(1-AX18/21.75,2) -> 1 | AZ18: =COUNTIF(C:C,C18) -> 1 | BA18: =VLOOKUP(C18,工资表明细!$C$2:$P$223,13,0) -> 6226097802044165 | BB18: =BA18=AI18 -> TRUE | BC18: =ROUND(AR18/21.75/8*3*L18,2) -> 0
A19: =ROW()-2 -> 17 | B19: 2026-07-01至2026-07-31 | C19: SCX00022 | D19: 刘锦翔 | E19: 创想悦动 | F19: 创想悦动 | G19: 公共设计组 | K19: 0 | L19: 0 | N19: 0 | O19: 0 | P19: 0 | Q19: 0 | R19: 0 | S19: 0 | T19: 0 | U19: 0 | V19: 0 | W19: 0 | X19: 0 | Y19: 0 | AA19: 0 | AB19: 0 | AC19: 0 | AD19: 0 | AE19: 0 | AF19: 0 | AG19: 0 | AH19: 440881200011294818 | AI19: 6214830634161458 | AJ19: 创想悦动-销售 | AK19: 13501513566 | AL19: allen@youdoogo.com | AM19: 环境艺术设计 | AN19: 合同制人员 | AO19: 2025-09-03 | AR19: =VLOOKUP($C19,工资表明细!$C$2:$Q$190,14,0) -> 14000 | AS19: =VLOOKUP($C19,工资表明细!$C$2:$Q$190,15,0) -> 0 | AT19: =SUMIFS(其他补发!H:H,其他补发!B:B,C19) -> 0 | AU19: =ROUND((AR19+AS19+AT19)/21.75*(H19+O19+P19*0.3+AA19),2)-VLOOKUP(C19,工资表明细!$C$2:$U$190,19,0) -> 0 | AV19: =ROUND(AR19/21.75/8*2*(K19+L19*3/2),2)+SUMIFS(加班费!H:H,加班费!D:D,C19)-VLOOKUP(C19,工资表明细!$C$2:$W$190,21,0) -> 0 | AW19: =ROUND(AR19/21.75/8*2*(K19+L19*3/2),2) -> 0 | AX19: =ROUND(SUM(H19,O19,P19*0.3,AA19),2) -> 0 | AY19: =ROUND(1-AX19/21.75,2) -> 1 | AZ19: =COUNTIF(C:C,C19) -> 1 | BA19: =VLOOKUP(C19,工资表明细!$C$2:$P$223,13,0) -> 6214830634161458 | BB19: =BA19=AI19 -> TRUE | BC19: =ROUND(AR19/21.75/8*3*L19,2) -> 0
A20: =ROW()-2 -> 18 | B20: 2026-07-01至2026-07-31 | C20: SCX00023 | D20: 刘永松 | E20: 创想悦动 | F20: 创想悦动 | G20: 游戏研发部 | K20: 0 | L20: 0 | N20: 0 | O20: 0 | P20: 5 | Q20: 0 | R20: 0 | S20: 0 | T20: 0 | U20: 0 | V20: 0 | W20: 0 | X20: 0 | Y20: 0 | AA20: 0 | AB20: 0 | AC20: 0 | AD20: 0 | AE20: 0 | AF20: 0 | AG20: 0 | AH20: 422126197808290516 | AI20: 6214866550505336 | AJ20: 创想悦动-研发 | AK20: 13554714365 | AL20: ericliu@youdoogo.com | AM20: 采矿与岩土工程 | AN20: 合同制人员 | AO20: 2025-09-04 | AR20: =VLOOKUP($C20,工资表明细!$C$2:$Q$190,14,0) -> 50000 | AS20: =VLOOKUP($C20,工资表明细!$C$2:$Q$190,15,0) -> 0 | AT20: =SUMIFS(其他补发!H:H,其他补发!B:B,C20) -> 0 | AU20: =ROUND((AR20+AS20+AT20)/21.75*(H20+O20+P20*0.3+AA20),2)-VLOOKUP(C20,工资表明细!$C$2:$U$190,19,0) -> 0 | AV20: =ROUND(AR20/21.75/8*2*(K20+L20*3/2),2)+SUMIFS(加班费!H:H,加班费!D:D,C20)-VLOOKUP(C20,工资表明细!$C$2:$W$190,21,0) -> 0 | AW20: =ROUND(AR20/21.75/8*2*(K20+L20*3/2),2) -> 0 | AX20: =ROUND(SUM(H20,O20,P20*0.3,AA20),2) -> 1.5 | AY20: =ROUND(1-AX20/21.75,2) -> 0.93 | AZ20: =COUNTIF(C:C,C20) -> 1 | BA20: =VLOOKUP(C20,工资表明细!$C$2:$P$223,13,0) -> 6214866550505336 | BB20: =BA20=AI20 -> TRUE | BC20: =ROUND(AR20/21.75/8*3*L20,2) -> 0
A21: =ROW()-2 -> 19 | B21: 2026-07-01至2026-07-31 | C21: SCX00024 | D21: 黄馨玥 | E21: 创想悦动 | F21: 创想悦动 | G21: 营销合作部 | K21: 0 | L21: 0 | N21: 0 | O21: 0 | P21: 0 | Q21: 0 | R21: 0 | S21: 0 | T21: 0 | U21: 0 | V21: 0 | W21: 0 | X21: 0 | Y21: 0 | AA21: 0 | AB21: 0 | AC21: 0 | AD21: 0 | AE21: 0 | AF21: 0 | AG21: 0 | AH21: 510107200005064246 | AI21: 6214851801328092 | AJ21: 创想悦动-销售 | AK21: 15521282339 | AL21: rachel@youdoogo.com | AM21: 金融学 | AN21: 合同制人员 | AO21: 2025-09-11 | AR21: =VLOOKUP($C21,工资表明细!$C$2:$Q$190,14,0) -> 14000 | AS21: =VLOOKUP($C21,工资表明细!$C$2:$Q$190,15,0) -> 0 | AT21: =SUMIFS(其他补发!H:H,其他补发!B:B,C21) -> 0 | AU21: =ROUND((AR21+AS21+AT21)/21.75*(H21+O21+P21*0.3+AA21),2)-VLOOKUP(C21,工资表明细!$C$2:$U$190,19,0) -> 0 | AV21: =ROUND(AR21/21.75/8*2*(K21+L21*3/2),2)+SUMIFS(加班费!H:H,加班费!D:D,C21)-VLOOKUP(C21,工资表明细!$C$2:$W$190,21,0) -> 0 | AW21: =ROUND(AR21/21.75/8*2*(K21+L21*3/2),2) -> 0 | AX21: =ROUND(SUM(H21,O21,P21*0.3,AA21),2) -> 0 | AY21: =ROUND(1-AX21/21.75,2) -> 1 | AZ21: =COUNTIF(C:C,C21) -> 1 | BA21: =VLOOKUP(C21,工资表明细!$C$2:$P$223,13,0) -> 6214851801328092 | BB21: =BA21=AI21 -> TRUE | BC21: =ROUND(AR21/21.75/8*3*L21,2) -> 0
A22: =ROW()-2 -> 20 | B22: 2026-07-01至2026-07-31 | C22: SCX00026 | D22: 彭星翰 | E22: 创想悦动 | F22: 创想悦动 | G22: 游戏研发部 | K22: 0 | L22: 0 | N22: 0 | O22: 0 | P22: 0 | Q22: 0 | R22: 0 | S22: 0 | T22: 0 | U22: 0 | V22: 0 | W22: 0 | X22: 0 | Y22: 0 | AA22: 0 | AB22: 0 | AC22: 0 | AD22: 0 | AE22: 0 | AF22: 0 | AG22: 0 | AH22: 440301199811253614 | AI22: 6214852005389823 | AJ22: 创想悦动-研发 | AK22: 17512048654 | AL22: eliber@youdoogo.com | AM22: 信息与计算科学 | AN22: 合同制人员 | AO22: 2025-09-12 | AR22: =VLOOKUP($C22,工资表明细!$C$2:$Q$190,14,0) -> 18000 | AS22: =VLOOKUP($C22,工资表明细!$C$2:$Q$190,15,0) -> 0 | AT22: =SUMIFS(其他补发!H:H,其他补发!B:B,C22) -> 0 | AU22: =ROUND((AR22+AS22+AT22)/21.75*(H22+O22+P22*0.3+AA22),2)-VLOOKUP(C22,工资表明细!$C$2:$U$190,19,0) -> 0 | AV22: =ROUND(AR22/21.75/8*2*(K22+L22*3/2),2)+SUMIFS(加班费!H:H,加班费!D:D,C22)-VLOOKUP(C22,工资表明细!$C$2:$W$190,21,0) -> 0 | AW22: =ROUND(AR22/21.75/8*2*(K22+L22*3/2),2) -> 0 | AX22: =ROUND(SUM(H22,O22,P22*0.3,AA22),2) -> 0 | AY22: =ROUND(1-AX22/21.75,2) -> 1 | AZ22: =COUNTIF(C:C,C22) -> 1 | BA22: =VLOOKUP(C22,工资表明细!$C$2:$P$223,13,0) -> 6214852005389823 | BB22: =BA22=AI22 -> TRUE | BC22: =ROUND(AR22/21.75/8*3*L22,2) -> 0
A23: =ROW()-2 -> 21 | B23: 2026-07-01至2026-07-31 | C23: SCX00027 | D23: 何泽浩 | E23: 创想悦动 | F23: 创想悦动 | G23: 游戏研发部 | K23: 0 | L23: 0 | N23: 0 | O23: 0 | P23: 0 | Q23: 0 | R23: 0 | S23: 0 | T23: 0 | U23: 0 | V23: 0 | W23: 0 | X23: 0 | Y23: 0 | AA23: 0 | AB23: 0 | AC23: 0 | AD23: 0 | AE23: 0 | AF23: 0 | AG23: 0 | AH23: 441202199712254015 | AI23: 6214851803294128 | AJ23: 创想悦动-研发 | AK23: 13760209076 | AL23: zarhhe@youdoogo.com | AM23: 计算机科学与技术 | AN23: 合同制人员 | AO23: 2025-09-15 | AR23: =VLOOKUP($C23,工资表明细!$C$2:$Q$190,14,0) -> 14000 | AS23: =VLOOKUP($C23,工资表明细!$C$2:$Q$190,15,0) -> 0 | AT23: =SUMIFS(其他补发!H:H,其他补发!B:B,C23) -> 0 | AU23: =ROUND((AR23+AS23+AT23)/21.75*(H23+O23+P23*0.3+AA23),2)-VLOOKUP(C23,工资表明细!$C$2:$U$190,19,0) -> 0 | AV23: =ROUND(AR23/21.75/8*2*(K23+L23*3/2),2)+SUMIFS(加班费!H:H,加班费!D:D,C23)-VLOOKUP(C23,工资表明细!$C$2:$W$190,21,0) -> 0 | AW23: =ROUND(AR23/21.75/8*2*(K23+L23*3/2),2) -> 0 | AX23: =ROUND(SUM(H23,O23,P23*0.3,AA23),2) -> 0 | AY23: =ROUND(1-AX23/21.75,2) -> 1 | AZ23: =COUNTIF(C:C,C23) -> 1 | BA23: =VLOOKUP(C23,工资表明细!$C$2:$P$223,13,0) -> 6214851803294128 | BB23: =BA23=AI23 -> TRUE | BC23: =ROUND(AR23/21.75/8*3*L23,2) -> 0
A24: =ROW()-2 -> 22 | B24: 2026-07-01至2026-07-31 | C24: SCX00028 | D24: 安咛 | E24: 创想悦动 | F24: 创想悦动 | G24: 游戏研发部 | K24: 0 | L24: 0 | N24: 0 | O24: 0 | P24: 0 | Q24: 0 | R24: 0 | S24: 0 | T24: 0 | U24: 0 | V24: 0 | W24: 0 | X24: 0 | Y24: 0 | AA24: 0 | AB24: 0 | AC24: 0 | AD24: 0 | AE24: 0 | AF24: 0 | AG24: 0 | AH24: 231026199302125537 | AI24: 6214837852001662 | AJ24: 创想悦动-研发 | AK24: 17620459248 | AL24: kurt@youdoogo.com | AM24: 计算机多媒体技术 | AN24: 合同制人员 | AO24: 2025-09-19 | AR24: =VLOOKUP($C24,工资表明细!$C$2:$Q$190,14,0) -> 19000 | AS24: =VLOOKUP($C24,工资表明细!$C$2:$Q$190,15,0) -> 0 | AT24: =SUMIFS(其他补发!H:H,其他补发!B:B,C24) -> 0 | AU24: =ROUND((AR24+AS24+AT24)/21.75*(H24+O24+P24*0.3+AA24),2)-VLOOKUP(C24,工资表明细!$C$2:$U$190,19,0) -> 0 | AV24: =ROUND(AR24/21.75/8*2*(K24+L24*3/2),2)+SUMIFS(加班费!H:H,加班费!D:D,C24)-VLOOKUP(C24,工资表明细!$C$2:$W$190,21,0) -> 0 | AW24: =ROUND(AR24/21.75/8*2*(K24+L24*3/2),2) -> 0 | AX24: =ROUND(SUM(H24,O24,P24*0.3,AA24),2) -> 0 | AY24: =ROUND(1-AX24/21.75,2) -> 1 | AZ24: =COUNTIF(C:C,C24) -> 1 | BA24: =VLOOKUP(C24,工资表明细!$C$2:$P$223,13,0) -> 6214837852001662 | BB24: =BA24=AI24 -> TRUE | BC24: =ROUND(AR24/21.75/8*3*L24,2) -> 0
A25: =ROW()-2 -> 23 | B25: 2026-07-01至2026-07-31 | C25: SCX00029 | D25: 邱永恒 | E25: 创想悦动 | F25: 创想悦动 | G25: 游戏研发部 | K25: 0 | L25: 0 | N25: 0 | O25: 0 | P25: 0 | Q25: 0 | R25: 0 | S25: 0 | T25: 0 | U25: 0 | V25: 0 | W25: 0 | X25: 0 | Y25: 0 | AA25: 0 | AB25: 0 | AC25: 0 | AD25: 0 | AE25: 0 | AF25: 0 | AG25: 0 | AH25: 440181198709024213 | AI25: 6226090201418122 | AJ25: 创想悦动-研发 | AK25: 13570383316 | AL25: nicholas@youdoogo.com | AM25: 给水排水工程 | AN25: 合同制人员 | AO25: 2025-09-17 | AR25: =VLOOKUP($C25,工资表明细!$C$2:$Q$190,14,0) -> 36300 | AS25: =VLOOKUP($C25,工资表明细!$C$2:$Q$190,15,0) -> 0 | AT25: =SUMIFS(其他补发!H:H,其他补发!B:B,C25) -> 0 | AU25: =ROUND((AR25+AS25+AT25)/21.75*(H25+O25+P25*0.3+AA25),2)-VLOOKUP(C25,工资表明细!$C$2:$U$190,19,0) -> 0 | AV25: =ROUND(AR25/21.75/8*2*(K25+L25*3/2),2)+SUMIFS(加班费!H:H,加班费!D:D,C25)-VLOOKUP(C25,工资表明细!$C$2:$W$190,21,0) -> 0 | AW25: =ROUND(AR25/21.75/8*2*(K25+L25*3/2),2) -> 0 | AX25: =ROUND(SUM(H25,O25,P25*0.3,AA25),2) -> 0 | AY25: =ROUND(1-AX25/21.75,2) -> 1 | AZ25: =COUNTIF(C:C,C25) -> 1 | BA25: =VLOOKUP(C25,工资表明细!$C$2:$P$223,13,0) -> 6226090201418122 | BB25: =BA25=AI25 -> TRUE | BC25: =ROUND(AR25/21.75/8*3*L25,2) -> 0
A26: =ROW()-2 -> 24 | B26: 2026-07-01至2026-07-31 | C26: SCX00030 | D26: 赵旭临 | E26: 创想悦动 | F26: 创想悦动 | G26: 游戏研发部 | K26: 0 | L26: 0 | N26: 0 | O26: 0 | P26: 0 | Q26: 0 | R26: 0 | S26: 0 | T26: 0 | U26: 0 | V26: 0 | W26: 0 | X26: 0 | Y26: 0 | AA26: 0 | AB26: 0 | AC26: 0 | AD26: 0 | AE26: 0 | AF26: 0 | AG26: 0 | AH26: 42010619890930841X | AI26: 6214830277747522 | AJ26: 创想悦动-管理 | AK26: 13971230700 | AL26: x@youdoogo.com | AM26: 金融管理 | AN26: 合同制人员 | AO26: 2025-10-09 | AR26: =VLOOKUP($C26,工资表明细!$C$2:$Q$190,14,0) -> 25000 | AS26: =VLOOKUP($C26,工资表明细!$C$2:$Q$190,15,0) -> 0 | AT26: =SUMIFS(其他补发!H:H,其他补发!B:B,C26) -> 0 | AU26: =ROUND((AR26+AS26+AT26)/21.75*(H26+O26+P26*0.3+AA26),2)-VLOOKUP(C26,工资表明细!$C$2:$U$190,19,0) -> 0 | AV26: =ROUND(AR26/21.75/8*2*(K26+L26*3/2),2)+SUMIFS(加班费!H:H,加班费!D:D,C26)-VLOOKUP(C26,工资表明细!$C$2:$W$190,21,0) -> 0 | AW26: =ROUND(AR26/21.75/8*2*(K26+L26*3/2),2) -> 0 | AX26: =ROUND(SUM(H26,O26,P26*0.3,AA26),2) -> 0 | AY26: =ROUND(1-AX26/21.75,2) -> 1 | AZ26: =COUNTIF(C:C,C26) -> 1 | BA26: =VLOOKUP(C26,工资表明细!$C$2:$P$223,13,0) -> 6214830277747522 | BB26: =BA26=AI26 -> TRUE | BC26: =ROUND(AR26/21.75/8*3*L26,2) -> 0
A27: =ROW()-2 -> 25 | B27: 2026-07-01至2026-07-31 | C27: SCX00031 | D27: 曾育辉 | E27: 创想悦动 | F27: 创想悦动 | G27: 游戏研发部 | K27: 0 | L27: 0 | N27: 0 | O27: 0 | P27: 0 | Q27: 0 | R27: 0 | S27: 0 | T27: 0 | U27: 0 | V27: 0 | W27: 0 | X27: 0 | Y27: 0 | AA27: 0 | AB27: 0 | AC27: 0 | AD27: 0 | AE27: 0 | AF27: 0 | AG27: 0 | AH27: 350681198011020558 | AI27: 6214866559216315 | AJ27: 创想悦动-研发 | AK27: 13926574164 | AL27: viczeng@youdoogo.com | AM27: 工商管理 | AN27: 合同制人员 | AO27: 2025-09-22 | AR27: =VLOOKUP($C27,工资表明细!$C$2:$Q$190,14,0) -> 30000 | AS27: =VLOOKUP($C27,工资表明细!$C$2:$Q$190,15,0) -> 0 | AT27: =SUMIFS(其他补发!H:H,其他补发!B:B,C27) -> 0 | AU27: =ROUND((AR27+AS27+AT27)/21.75*(H27+O27+P27*0.3+AA27),2)-VLOOKUP(C27,工资表明细!$C$2:$U$190,19,0) -> 0 | AV27: =ROUND(AR27/21.75/8*2*(K27+L27*3/2),2)+SUMIFS(加班费!H:H,加班费!D:D,C27)-VLOOKUP(C27,工资表明细!$C$2:$W$190,21,0) -> 0 | AW27: =ROUND(AR27/21.75/8*2*(K27+L27*3/2),2) -> 0 | AX27: =ROUND(SUM(H27,O27,P27*0.3,AA27),2) -> 0 | AY27: =ROUND(1-AX27/21.75,2) -> 1 | AZ27: =COUNTIF(C:C,C27) -> 1 | BA27: =VLOOKUP(C27,工资表明细!$C$2:$P$223,13,0) -> 6214866559216315 | BB27: =BA27=AI27 -> TRUE | BC27: =ROUND(AR27/21.75/8*3*L27,2) -> 0
A28: =ROW()-2 -> 26 | B28: 2026-07-01至2026-07-31 | C28: SCX00032 | D28: 杨昭桦 | E28: 创想悦动 | F28: 创想悦动 | G28: 基础产品部 | K28: 0 | L28: 0 | N28: 0 | O28: 0 | P28: 0 | Q28: 0 | R28: 0 | S28: 0 | T28: 0 | U28: 0 | V28: 0 | W28: 0 | X28: 0 | Y28: 0 | AA28: 0 | AB28: 0 | AC28: 0 | AD28: 0 | AE28: 0 | AF28: 0 | AG28: 0 | AH28: 440508199112122012 | AI28: 6212264000018455804 | AJ28: 创想悦动-研发 | AK28: 13535278400 | AL28: holden@youdoogo.com | AM28: 物流管理 | AN28: 合同制人员 | AO28: 2025-09-22 | AR28: =VLOOKUP($C28,工资表明细!$C$2:$Q$190,14,0) -> 20000 | AS28: =VLOOKUP($C28,工资表明细!$C$2:$Q$190,15,0) -> 0 | AT28: =SUMIFS(其他补发!H:H,其他补发!B:B,C28) -> 0 | AU28: =ROUND((AR28+AS28+AT28)/21.75*(H28+O28+P28*0.3+AA28),2)-VLOOKUP(C28,工资表明细!$C$2:$U$190,19,0) -> 0 | AV28: =ROUND(AR28/21.75/8*2*(K28+L28*3/2),2)+SUMIFS(加班费!H:H,加班费!D:D,C28)-VLOOKUP(C28,工资表明细!$C$2:$W$190,21,0) -> 0 | AW28: =ROUND(AR28/21.75/8*2*(K28+L28*3/2),2) -> 0 | AX28: =ROUND(SUM(H28,O28,P28*0.3,AA28),2) -> 0 | AY28: =ROUND(1-AX28/21.75,2) -> 1 | AZ28: =COUNTIF(C:C,C28) -> 1 | BA28: =VLOOKUP(C28,工资表明细!$C$2:$P$223,13,0) -> 6212264000018455804 | BB28: =BA28=AI28 -> TRUE | BC28: =ROUND(AR28/21.75/8*3*L28,2) -> 0
A29: =ROW()-2 -> 27 | B29: 2026-07-01至2026-07-31 | C29: SCX00034 | D29: 谢同 | E29: 创想悦动 | F29: 创想悦动 | G29: 游戏研发部 | K29: 0 | L29: 0 | N29: 0 | O29: 0 | P29: 0 | Q29: 0 | R29: 0 | S29: 0 | T29: 0 | U29: 0 | V29: 0 | W29: 0 | X29: 0 | Y29: 0 | AA29: 0 | AB29: 0 | AC29: 0 | AD29: 0 | AE29: 0 | AF29: 0 | AG29: 0 | AH29: 44068319950602471X | AI29: 6228480096759954777 | AJ29: 创想悦动-研发 | AK29: 15669189562 | AL29: atomsam@youdoogo.com | AM29: 运动表现分析 | AN29: 合同制人员 | AO29: 2025-10-09 | AR29: =VLOOKUP($C29,工资表明细!$C$2:$Q$190,14,0) -> 24500 | AS29: =VLOOKUP($C29,工资表明细!$C$2:$Q$190,15,0) -> 0 | AT29: =SUMIFS(其他补发!H:H,其他补发!B:B,C29) -> 0 | AU29: =ROUND((AR29+AS29+AT29)/21.75*(H29+O29+P29*0.3+AA29),2)-VLOOKUP(C29,工资表明细!$C$2:$U$190,19,0) -> 0 | AV29: =ROUND(AR29/21.75/8*2*(K29+L29*3/2),2)+SUMIFS(加班费!H:H,加班费!D:D,C29)-VLOOKUP(C29,工资表明细!$C$2:$W$190,21,0) -> 0 | AW29: =ROUND(AR29/21.75/8*2*(K29+L29*3/2),2) -> 0 | AX29: =ROUND(SUM(H29,O29,P29*0.3,AA29),2) -> 0 | AY29: =ROUND(1-AX29/21.75,2) -> 1 | AZ29: =COUNTIF(C:C,C29) -> 1 | BA29: =VLOOKUP(C29,工资表明细!$C$2:$P$223,13,0) -> 6228480096759954777 | BB29: =BA29=AI29 -> TRUE | BC29: =ROUND(AR29/21.75/8*3*L29,2) -> 0
... A66: =ROW()-2 -> 64 | B66: 2026-07-01至2026-07-31 | C66: SCX00080 | D66: 刘临风 | E66: 创想悦动 | F66: 创想悦动 | G66: 品牌宣传组 | K66: 0 | L66: 0 | N66: 0 | O66: 0 | P66: 0 | Q66: 0 | R66: 0 | S66: 0 | T66: 0 | U66: 0 | V66: 0 | W66: 0 | X66: 0 | Y66: 0 | AA66: 0 | AB66: 0 | AC66: 0 | AD66: 0 | AE66: 0 | AF66: 0 | AG66: 0 | AH66: 420602199809040010 | AI66: 6214830053359963 | AJ66: 创想悦动-研发 | AK66: 15071555585 | AL66: ryan@youdoogo.com | AM66: 整合营销传播 | AN66: 合同制人员 | AO66: 2026-06-15 | AR66: =VLOOKUP($C66,工资表明细!$C$2:$Q$190,14,0) -> 19000 | AS66: =VLOOKUP($C66,工资表明细!$C$2:$Q$190,15,0) -> 0 | AT66: =SUMIFS(其他补发!H:H,其他补发!B:B,C66) -> 0 | AU66: =ROUND((AR66+AS66+AT66)/21.75*(H66+O66+P66*0.3+AA66),2)-VLOOKUP(C66,工资表明细!$C$2:$U$190,19,0) -> 0 | AV66: =ROUND(AR66/21.75/8*2*(K66+L66*3/2),2)+SUMIFS(加班费!H:H,加班费!D:D,C66)-VLOOKUP(C66,工资表明细!$C$2:$W$190,21,0) -> 0 | AW66: =ROUND(AR66/21.75/8*2*(K66+L66*3/2),2) -> 0 | AX66: =ROUND(SUM(H66,O66,P66*0.3,AA66),2) -> 0 | AY66: =ROUND(1-AX66/21.75,2) -> 1 | AZ66: =COUNTIF(C:C,C66) -> 1 | BA66: =VLOOKUP(C66,工资表明细!$C$2:$P$223,13,0) -> 6214830053359963 | BB66: =BA66=AI66 -> TRUE | BC66: =ROUND(AR66/21.75/8*3*L66,2) -> 0
B67: 2026-07-01至2026-07-31 | C67: SCX00081 | D67: 岑兴满 | E67: 创想悦动 | F67: 创想悦动 | G67: 公共设计组 | K67: 0 | L67: 0 | N67: 0 | O67: 0 | P67: 0 | Q67: 0 | R67: 0 | S67: 0 | T67: 0 | U67: 0 | V67: 0 | W67: 0 | X67: 0 | Y67: 0 | AA67: 0 | AB67: 0 | AC67: 0 | AD67: 0 | AE67: 0 | AF67: 0 | AG67: 0 | AH67: 450881199504035036 | AI67: 6214837853537516 | AJ67: 创想悦动-研发 | AK67: 17512077299 | AL67: kevin@youdoogo.com | AM67: 视觉传达设计 | AN67: 合同制人员 | AO67: 2026-06-15 | AR67: =VLOOKUP($C67,工资表明细!$C$2:$Q$190,14,0) -> 20000 | AS67: =VLOOKUP($C67,工资表明细!$C$2:$Q$190,15,0) -> 0 | AT67: =SUMIFS(其他补发!H:H,其他补发!B:B,C67) -> 0 | AU67: =ROUND((AR67+AS67+AT67)/21.75*(H67+O67+P67*0.3+AA67),2)-VLOOKUP(C67,工资表明细!$C$2:$U$190,19,0) -> 0 | AV67: =ROUND(AR67/21.75/8*2*(K67+L67*3/2),2)+SUMIFS(加班费!H:H,加班费!D:D,C67)-VLOOKUP(C67,工资表明细!$C$2:$W$190,21,0) -> 0 | AW67: =ROUND(AR67/21.75/8*2*(K67+L67*3/2),2) -> 0 | AX67: =ROUND(SUM(H67,O67,P67*0.3,AA67),2) -> 0 | AY67: =ROUND(1-AX67/21.75,2) -> 1 | AZ67: =COUNTIF(C:C,C67) -> 1 | BA67: =VLOOKUP(C67,工资表明细!$C$2:$P$223,13,0) -> 6214837853537516 | BB67: =BA67=AI67 -> TRUE | BC67: =ROUND(AR67/21.75/8*3*L67,2) -> 0
B68: 2026-07-01至2026-07-31 | C68: SCX00082 | D68: 韩亮 | E68: 创想悦动 | F68: 创想悦动 | G68: 游戏研发部 | K68: 0 | L68: 0 | N68: 0 | O68: 0 | P68: 0 | Q68: 0 | R68: 0 | S68: 0 | T68: 0 | U68: 0 | V68: 0 | W68: 0 | X68: 0 | Y68: 0 | AA68: 0 | AB68: 0 | AC68: 0 | AD68: 0 | AE68: 0 | AF68: 0 | AG68: 0 | AH68: 320382198909130432 | AI68: 6214866556479692 | AJ68: 创想悦动-研发 | AK68: 13580917606 | AL68: leonhan@youdoogo.com | AM68: 电气工程与自动化 | AN68: 合同制人员 | AO68: 2026-06-22 | AR68: =VLOOKUP($C68,工资表明细!$C$2:$Q$190,14,0) -> 40000 | AS68: =VLOOKUP($C68,工资表明细!$C$2:$Q$190,15,0) -> 0 | AT68: =SUMIFS(其他补发!H:H,其他补发!B:B,C68) -> 0 | AU68: =ROUND((AR68+AS68+AT68)/21.75*(H68+O68+P68*0.3+AA68),2)-VLOOKUP(C68,工资表明细!$C$2:$U$190,19,0) -> 0 | AV68: =ROUND(AR68/21.75/8*2*(K68+L68*3/2),2)+SUMIFS(加班费!H:H,加班费!D:D,C68)-VLOOKUP(C68,工资表明细!$C$2:$W$190,21,0) -> 0 | AW68: =ROUND(AR68/21.75/8*2*(K68+L68*3/2),2) -> 0 | AX68: =ROUND(SUM(H68,O68,P68*0.3,AA68),2) -> 0 | AY68: =ROUND(1-AX68/21.75,2) -> 1 | AZ68: =COUNTIF(C:C,C68) -> 1 | BA68: =VLOOKUP(C68,工资表明细!$C$2:$P$223,13,0) -> 6214866556479692 | BB68: =BA68=AI68 -> TRUE | BC68: =ROUND(AR68/21.75/8*3*L68,2) -> 0
B69: 2026-07-01至2026-07-31 | C69: SCX00083 | D69: 黄依婷 | E69: 创想悦动 | F69: 创想悦动 | G69: 公共设计组 | K69: 0 | L69: 0 | N69: 0 | O69: 0 | P69: 0 | Q69: 0 | R69: 0 | S69: 0 | T69: 0 | U69: 0 | V69: 0 | W69: 0 | X69: 0 | Y69: 0 | AA69: 0 | AB69: 0 | AC69: 0 | AD69: 0 | AE69: 0 | AF69: 0 | AG69: 0 | AH69: 441581199812260027 | AI69: 6214832023608339 | AJ69: 创想悦动-研发 | AK69: 19520895193 | AL69: eating@youdoogo.com | AM69: 数字媒体应用 | AN69: 合同制人员 | AO69: 2026-06-25 | AR69: =VLOOKUP($C69,工资表明细!$C$2:$Q$190,14,0) -> 19000 | AS69: =VLOOKUP($C69,工资表明细!$C$2:$Q$190,15,0) -> 0 | AT69: =SUMIFS(其他补发!H:H,其他补发!B:B,C69) -> 0 | AU69: =ROUND((AR69+AS69+AT69)/21.75*(H69+O69+P69*0.3+AA69),2)-VLOOKUP(C69,工资表明细!$C$2:$U$190,19,0) -> 0 | AV69: =ROUND(AR69/21.75/8*2*(K69+L69*3/2),2)+SUMIFS(加班费!H:H,加班费!D:D,C69)-VLOOKUP(C69,工资表明细!$C$2:$W$190,21,0) -> 0 | AW69: =ROUND(AR69/21.75/8*2*(K69+L69*3/2),2) -> 0 | AX69: =ROUND(SUM(H69,O69,P69*0.3,AA69),2) -> 0 | AY69: =ROUND(1-AX69/21.75,2) -> 1 | AZ69: =COUNTIF(C:C,C69) -> 1 | BA69: =VLOOKUP(C69,工资表明细!$C$2:$P$223,13,0) -> 6214832023608339 | BB69: =BA69=AI69 -> TRUE | BC69: =ROUND(AR69/21.75/8*3*L69,2) -> 0
B70: 2026-07-01至2026-07-31 | C70: SCX00084 | D70: 彭佳睿 | E70: 创想悦动 | F70: 创想悦动 | G70: 营销合作部 | K70: 0 | L70: 0 | N70: 0 | O70: 1 | P70: 0 | Q70: 0 | R70: 0 | S70: 0 | T70: 0 | U70: 0 | V70: 0 | W70: 0 | X70: 0 | Y70: 0 | AA70: 0 | AB70: 0 | AC70: 0 | AD70: 0 | AE70: 0 | AF70: 0 | AG70: 0 | AH70: 362429200311250029 | AI70: 6214831106316695 | AJ70: 创想悦动-销售 | AK70: 18807960943 | AL70: Parry@youdoogo.com | AM70: 新闻学 | AN70: 实习人员 | AO70: 2026-06-26 | AR70: =VLOOKUP($C70,工资表明细!$C$2:$Q$190,14,0) -> 4000 | AS70: =VLOOKUP($C70,工资表明细!$C$2:$Q$190,15,0) -> 0 | AT70: =SUMIFS(其他补发!H:H,其他补发!B:B,C70) -> 0 | AU70: =ROUND((AR70+AS70+AT70)/21.75*(H70+O70+P70*0.3+AA70),2)-VLOOKUP(C70,工资表明细!$C$2:$U$190,19,0) -> 0 | AV70: =ROUND(AR70/21.75/8*2*(K70+L70*3/2),2)+SUMIFS(加班费!H:H,加班费!D:D,C70)-VLOOKUP(C70,工资表明细!$C$2:$W$190,21,0) -> 0 | AW70: =ROUND(AR70/21.75/8*2*(K70+L70*3/2),2) -> 0 | AX70: =ROUND(SUM(H70,O70,P70*0.3,AA70),2) -> 1 | AY70: =ROUND(1-AX70/21.75,2) -> 0.95 | AZ70: =COUNTIF(C:C,C70) -> 1 | BA70: =VLOOKUP(C70,工资表明细!$C$2:$P$223,13,0) -> 6214831106316695 | BB70: =BA70=AI70 -> TRUE | BC70: =ROUND(AR70/21.75/8*3*L70,2) -> 0
B71: 2026-07-01至2026-07-31 | C71: SCX00085 | D71: 丘深壬 | E71: 创想悦动 | F71: 创想悦动 | G71: 游戏研发部 | K71: 0 | L71: 0 | N71: 0 | O71: 0 | P71: 0 | Q71: 0 | R71: 0 | S71: 0 | T71: 0 | U71: 0 | V71: 0 | W71: 0 | X71: 0 | Y71: 0 | AA71: 0 | AB71: 0 | AC71: 0 | AD71: 0 | AE71: 0 | AF71: 0 | AG71: 0 | AH71: 440306199306280437 | AI71: 6214837842008827 | AJ71: 创想悦动-研发 | AK71: 13249827257 | AL71: paul@youdoogo.com | AM71: 自动化 | AN71: 合同制人员 | AO71: 2026-06-29 | AR71: =VLOOKUP($C71,工资表明细!$C$2:$Q$190,14,0) -> 25000 | AS71: =VLOOKUP($C71,工资表明细!$C$2:$Q$190,15,0) -> 0 | AT71: =SUMIFS(其他补发!H:H,其他补发!B:B,C71) -> 0 | AU71: =ROUND((AR71+AS71+AT71)/21.75*(H71+O71+P71*0.3+AA71),2)-VLOOKUP(C71,工资表明细!$C$2:$U$190,19,0) -> 0 | AV71: =ROUND(AR71/21.75/8*2*(K71+L71*3/2),2)+SUMIFS(加班费!H:H,加班费!D:D,C71)-VLOOKUP(C71,工资表明细!$C$2:$W$190,21,0) -> 0 | AW71: =ROUND(AR71/21.75/8*2*(K71+L71*3/2),2) -> 0 | AX71: =ROUND(SUM(H71,O71,P71*0.3,AA71),2) -> 0 | AY71: =ROUND(1-AX71/21.75,2) -> 1 | AZ71: =COUNTIF(C:C,C71) -> 1 | BA71: =VLOOKUP(C71,工资表明细!$C$2:$P$223,13,0) -> 6214837842008827 | BB71: =BA71=AI71 -> TRUE | BC71: =ROUND(AR71/21.75/8*3*L71,2) -> 0
B72: 2026-07-01至2026-07-31 | C72: SCX00086 | D72: 赵敬亭 | E72: 创想悦动 | F72: 创想悦动 | G72: 营销合作部 | K72: 0 | L72: 0 | N72: 0 | O72: 0 | P72: 0 | Q72: 0 | R72: 0 | S72: 0 | T72: 0 | U72: 0 | V72: 0 | W72: 0 | X72: 0 | Y72: 0 | AA72: 0 | AB72: 0 | AC72: 0 | AD72: 0 | AE72: 0 | AF72: 0 | AG72: 0 | AH72: 632826199006220029 | AI72: 6214831134217303 | AJ72: 创想悦动-销售 | AK72: 19396389848 | AL72: JT@youdoogo.com | AM72: 会计 | AN72: 合同制人员 | AO72: 2026-06-29 | AR72: =VLOOKUP($C72,工资表明细!$C$2:$Q$190,14,0) -> 28000 | AS72: =VLOOKUP($C72,工资表明细!$C$2:$Q$190,15,0) -> 0 | AT72: =SUMIFS(其他补发!H:H,其他补发!B:B,C72) -> 0 | AU72: =ROUND((AR72+AS72+AT72)/21.75*(H72+O72+P72*0.3+AA72),2)-VLOOKUP(C72,工资表明细!$C$2:$U$190,19,0) -> 0 | AV72: =ROUND(AR72/21.75/8*2*(K72+L72*3/2),2)+SUMIFS(加班费!H:H,加班费!D:D,C72)-VLOOKUP(C72,工资表明细!$C$2:$W$190,21,0) -> 0 | AW72: =ROUND(AR72/21.75/8*2*(K72+L72*3/2),2) -> 0 | AX72: =ROUND(SUM(H72,O72,P72*0.3,AA72),2) -> 0 | AY72: =ROUND(1-AX72/21.75,2) -> 1 | AZ72: =COUNTIF(C:C,C72) -> 1 | BA72: =VLOOKUP(C72,工资表明细!$C$2:$P$223,13,0) -> 6214831134217303 | BB72: =BA72=AI72 -> TRUE | BC72: =ROUND(AR72/21.75/8*3*L72,2) -> 0
B73: 2026-07-01至2026-07-31 | C73: SCX00087 | D73: 陈小玲 | E73: 创想悦动 | F73: 创想悦动 | G73: 基础产品部 | K73: 0 | L73: 0 | N73: 0 | O73: 0 | P73: 0 | Q73: 0 | R73: 0 | S73: 0 | T73: 0 | U73: 0 | V73: 0 | W73: 0 | X73: 0 | Y73: 0 | AA73: 0 | AB73: 0 | AC73: 0 | AD73: 0 | AE73: 0 | AF73: 0 | AG73: 0 | AH73: 511124198608204620 | AI73: 6214856553012398 | AJ73: 创想悦动-研发 | AK73: 18922802027 | AL73: Amy@youdoogo.com | AM73: 针织技术与针织服装 | AN73: 合同制人员 | AO73: 2026-06-26 | AR73: =VLOOKUP($C73,工资表明细!$C$2:$Q$190,14,0) -> 24000 | AS73: =VLOOKUP($C73,工资表明细!$C$2:$Q$190,15,0) -> 0 | AT73: =SUMIFS(其他补发!H:H,其他补发!B:B,C73) -> 0 | AU73: =ROUND((AR73+AS73+AT73)/21.75*(H73+O73+P73*0.3+AA73),2)-VLOOKUP(C73,工资表明细!$C$2:$U$190,19,0) -> 0 | AV73: =ROUND(AR73/21.75/8*2*(K73+L73*3/2),2)+SUMIFS(加班费!H:H,加班费!D:D,C73)-VLOOKUP(C73,工资表明细!$C$2:$W$190,21,0) -> 0 | AW73: =ROUND(AR73/21.75/8*2*(K73+L73*3/2),2) -> 0 | AX73: =ROUND(SUM(H73,O73,P73*0.3,AA73),2) -> 0 | AY73: =ROUND(1-AX73/21.75,2) -> 1 | AZ73: =COUNTIF(C:C,C73) -> 1 | BA73: =VLOOKUP(C73,工资表明细!$C$2:$P$223,13,0) -> 6214856553012398 | BB73: =BA73=AI73 -> TRUE | BC73: =ROUND(AR73/21.75/8*3*L73,2) -> 0
B74: 2026-07-01至2026-07-31 | C74: SCX00088 | D74: 郑立文 | E74: 创想悦动 | F74: 创想悦动 | G74: 品牌宣传组 | H74: 2 | K74: 0 | L74: 0 | N74: 0 | O74: 0 | P74: 0 | Q74: 0 | R74: 0 | S74: 0 | T74: 0 | U74: 0 | V74: 0 | W74: 0 | X74: 0 | Y74: 0 | AA74: 0 | AB74: 0 | AC74: 0 | AD74: 0 | AE74: 0 | AF74: 0 | AG74: 0 | AH74: 440103198110182443 | AI74: 6214850206505908 | AJ74: 创想悦动-销售 | AK74: 13824413431 | AL74: Cathy@youdoogo.com | AM74: 汉语言文学 | AN74: 合同制人员 | AO74: 2026-07-03 | AR74: =VLOOKUP($C74,工资表明细!$C$2:$Q$190,14,0) -> 24000 | AS74: =VLOOKUP($C74,工资表明细!$C$2:$Q$190,15,0) -> 0 | AT74: =SUMIFS(其他补发!H:H,其他补发!B:B,C74) -> 0 | AU74: =ROUND((AR74+AS74+AT74)/21.75*(H74+O74+P74*0.3+AA74),2)-VLOOKUP(C74,工资表明细!$C$2:$U$190,19,0) -> 0 | AV74: =ROUND(AR74/21.75/8*2*(K74+L74*3/2),2)+SUMIFS(加班费!H:H,加班费!D:D,C74)-VLOOKUP(C74,工资表明细!$C$2:$W$190,21,0) -> 0 | AW74: =ROUND(AR74/21.75/8*2*(K74+L74*3/2),2) -> 0 | AX74: =ROUND(SUM(H74,O74,P74*0.3,AA74),2) -> 2 | AY74: =ROUND(1-AX74/21.75,2) -> 0.91 | AZ74: =COUNTIF(C:C,C74) -> 1 | BA74: =VLOOKUP(C74,工资表明细!$C$2:$P$223,13,0) -> 6214850206505908 | BB74: =BA74=AI74 -> TRUE | BC74: =ROUND(AR74/21.75/8*3*L74,2) -> 0
B75: 2026-07-01至2026-07-31 | C75: SCX00089 | D75: 麦汝琪 | E75: 创想悦动 | F75: 创想悦动 | G75: 营销合作部 | H75: 0 | K75: 0 | L75: 0 | N75: 0 | O75: 0 | P75: 0 | Q75: 0 | R75: 0 | S75: 0 | T75: 0 | U75: 0 | V75: 0 | W75: 0 | X75: 0 | Y75: 0 | AA75: 0 | AB75: 0 | AC75: 0 | AD75: 0 | AE75: 0 | AF75: 0 | AG75: 0 | AH75: 440306200211143224 | AI75: 6214837889289025 | AJ75: 创想悦动-销售 | AK75: 18123802382 | AL75: Yuki@youdoogo.com | AM75: 市场营销 | AN75: 合同制人员 | AO75: 2026-07-01 | AR75: =VLOOKUP($C75,工资表明细!$C$2:$Q$190,14,0) -> 8000 | AS75: =VLOOKUP($C75,工资表明细!$C$2:$Q$190,15,0) -> 0 | AT75: =SUMIFS(其他补发!H:H,其他补发!B:B,C75) -> 0 | AU75: =ROUND((AR75+AS75+AT75)/21.75*(H75+O75+P75*0.3+AA75),2)-VLOOKUP(C75,工资表明细!$C$2:$U$190,19,0) -> 0 | AV75: =ROUND(AR75/21.75/8*2*(K75+L75*3/2),2)+SUMIFS(加班费!H:H,加班费!D:D,C75)-VLOOKUP(C75,工资表明细!$C$2:$W$190,21,0) -> 0 | AW75: =ROUND(AR75/21.75/8*2*(K75+L75*3/2),2) -> 0 | AX75: =ROUND(SUM(H75,O75,P75*0.3,AA75),2) -> 0 | AY75: =ROUND(1-AX75/21.75,2) -> 1 | AZ75: =COUNTIF(C:C,C75) -> 1 | BA75: =VLOOKUP(C75,工资表明细!$C$2:$P$223,13,0) -> 6214837889289025 | BB75: =BA75=AI75 -> TRUE | BC75: =ROUND(AR75/21.75/8*3*L75,2) -> 0
B76: 2026-07-01至2026-07-31 | C76: SCX00090 | D76: 杨植清 | E76: 创想悦动 | F76: 创想悦动 | G76: 游戏研发部 | H76: 10 | K76: 0 | L76: 0 | N76: 0 | O76: 0 | P76: 0 | Q76: 0 | R76: 0 | S76: 0 | T76: 0 | U76: 0 | V76: 0 | W76: 0 | X76: 0 | Y76: 0 | AA76: 0 | AB76: 0 | AC76: 0 | AD76: 0 | AE76: 0 | AF76: 0 | AG76: 0 | AH76: 34118119951106182X | AI76: 6214856552716569 | AJ76: 创想悦动-研发 | AK76: 13713799617 | AL76: Yangzte@youdoogo.com | AM76: 美术 | AN76: 合同制人员 | AO76: 2026-07-15 | AR76: =VLOOKUP($C76,工资表明细!$C$2:$Q$190,14,0) -> 22000 | AS76: =VLOOKUP($C76,工资表明细!$C$2:$Q$190,15,0) -> 0 | AT76: =SUMIFS(其他补发!H:H,其他补发!B:B,C76) -> 0 | AU76: =ROUND((AR76+AS76+AT76)/21.75*(H76+O76+P76*0.3+AA76),2)-VLOOKUP(C76,工资表明细!$C$2:$U$190,19,0) -> 0 | AV76: =ROUND(AR76/21.75/8*2*(K76+L76*3/2),2)+SUMIFS(加班费!H:H,加班费!D:D,C76)-VLOOKUP(C76,工资表明细!$C$2:$W$190,21,0) -> 0 | AW76: =ROUND(AR76/21.75/8*2*(K76+L76*3/2),2) -> 0 | AX76: =ROUND(SUM(H76,O76,P76*0.3,AA76),2) -> 10 | AY76: =ROUND(1-AX76/21.75,2) -> 0.54 | AZ76: =COUNTIF(C:C,C76) -> 1 | BA76: =VLOOKUP(C76,工资表明细!$C$2:$P$223,13,0) -> 6214856552716569 | BB76: =BA76=AI76 -> TRUE | BC76: =ROUND(AR76/21.75/8*3*L76,2) -> 0
B77: 2026-07-01至2026-07-31 | C77: SCX00092 | D77: 罗凯成 | E77: 创想悦动 | F77: 创想悦动 | G77: 基础产品部 | H77: 9.75 | K77: 0 | L77: 0 | N77: 0 | O77: 0 | P77: 0 | Q77: 0 | R77: 0 | S77: 0 | T77: 0 | U77: 0 | V77: 0 | W77: 0 | X77: 0 | Y77: 0 | AA77: 0 | AB77: 0 | AC77: 0 | AD77: 0 | AE77: 0 | AF77: 0 | AG77: 0 | AH77: 440305200007093032 | AI77: 6214851805509192 | AJ77: 创想悦动-研发 | AK77: 18926598212 | AL77: pauluo@youdoogo.com | AM77: 控制工程 | AN77: 合同制人员 | AO77: 2026-07-16 | AR77: =VLOOKUP($C77,工资表明细!$C$2:$Q$190,14,0) -> 20000 | AS77: =VLOOKUP($C77,工资表明细!$C$2:$Q$190,15,0) -> 0 | AT77: =SUMIFS(其他补发!H:H,其他补发!B:B,C77) -> 0 | AU77: =ROUND((AR77+AS77+AT77)/21.75*(H77+O77+P77*0.3+AA77),2)-VLOOKUP(C77,工资表明细!$C$2:$U$190,19,0) -> 0 | AV77: =ROUND(AR77/21.75/8*2*(K77+L77*3/2),2)+SUMIFS(加班费!H:H,加班费!D:D,C77)-VLOOKUP(C77,工资表明细!$C$2:$W$190,21,0) -> 0 | AW77: =ROUND(AR77/21.75/8*2*(K77+L77*3/2),2) -> 0 | AX77: =ROUND(SUM(H77,O77,P77*0.3,AA77),2) -> 9.75 | AY77: =ROUND(1-AX77/21.75,2) -> 0.55 | AZ77: =COUNTIF(C:C,C77) -> 1 | BA77: =VLOOKUP(C77,工资表明细!$C$2:$P$223,13,0) -> 6214851805509192 | BB77: =BA77=AI77 -> TRUE | BC77: =ROUND(AR77/21.75/8*3*L77,2) -> 0
B78: 2026-07-01至2026-07-31 | C78: SCX00094 | D78: 余宏伟 | E78: 创想悦动 | F78: 创想悦动 | G78: 基础产品部 | H78: 16.75 | K78: 0 | L78: 0 | N78: 0 | O78: 0 | P78: 0 | Q78: 0 | R78: 0 | S78: 0 | T78: 0 | U78: 0 | V78: 0 | W78: 0 | X78: 0 | Y78: 0 | AA78: 0 | AB78: 0 | AC78: 0 | AD78: 0 | AE78: 0 | AF78: 0 | AG78: 0 | AH78: 441802199009226912 | AI78: 6214830700285595 | AJ78: 创想悦动-研发 | AK78: 18823858181 | AL78: homway@youdoogo.com | AM78: 商务管理 | AN78: 合同制人员 | AO78: 2026-07-27 | AR78: =VLOOKUP($C78,工资表明细!$C$2:$Q$190,14,0) -> 26000 | AS78: =VLOOKUP($C78,工资表明细!$C$2:$Q$190,15,0) -> 0 | AT78: =SUMIFS(其他补发!H:H,其他补发!B:B,C78) -> 0 | AU78: =ROUND((AR78+AS78+AT78)/21.75*(H78+O78+P78*0.3+AA78),2)-VLOOKUP(C78,工资表明细!$C$2:$U$190,19,0) -> 0 | AV78: =ROUND(AR78/21.75/8*2*(K78+L78*3/2),2)+SUMIFS(加班费!H:H,加班费!D:D,C78)-VLOOKUP(C78,工资表明细!$C$2:$W$190,21,0) -> 0 | AW78: =ROUND(AR78/21.75/8*2*(K78+L78*3/2),2) -> 0 | AX78: =ROUND(SUM(H78,O78,P78*0.3,AA78),2) -> 16.75 | AY78: =ROUND(1-AX78/21.75,2) -> 0.23 | AZ78: =COUNTIF(C:C,C78) -> 1 | BA78: =VLOOKUP(C78,工资表明细!$C$2:$P$223,13,0) -> 6214830700285595 | BB78: =BA78=AI78 -> TRUE | BC78: =ROUND(AR78/21.75/8*3*L78,2) -> 0
B79: 2026-07-01至2026-07-31 | C79: SCX00075 | D79: 王凡 | E79: 创想悦动 | F79: 创想悦动 | G79: 游戏研发部 | K79: 0 | L79: 0 | N79: 0 | O79: 0 | P79: 0 | Q79: 0 | R79: 0 | S79: 0 | T79: 0 | U79: 0 | V79: 0 | W79: 0 | X79: 0 | Y79: 0 | AA79: 0 | AB79: 0 | AC79: 0 | AD79: 0 | AE79: 0 | AF79: 0 | AG79: 0 | AH79: 362103198208300032 | AI79: 6225887832374785 | AJ79: 创想悦动-研发 | AK79: 13723412943 | AL79: Steven@youdoogo.com | AM79: 工商管理 | AN79: 合同制人员 | AO79: 2026-06-02 | AR79: =VLOOKUP($C79,工资表明细!$C$2:$Q$190,14,0) -> 28000 | AS79: =VLOOKUP($C79,工资表明细!$C$2:$Q$190,15,0) -> 0 | AT79: =SUMIFS(其他补发!H:H,其他补发!B:B,C79) -> 0 | AU79: =ROUND((AR79+AS79+AT79)/21.75*(H79+O79+P79*0.3+AA79),2)-VLOOKUP(C79,工资表明细!$C$2:$U$190,19,0) -> 0 | AV79: =ROUND(AR79/21.75/8*2*(K79+L79*3/2),2)+SUMIFS(加班费!H:H,加班费!D:D,C79)-VLOOKUP(C79,工资表明细!$C$2:$W$190,21,0) -> 0 | AW79: =ROUND(AR79/21.75/8*2*(K79+L79*3/2),2) -> 0 | AX79: =ROUND(SUM(H79,O79,P79*0.3,AA79),2) -> 0 | AY79: =ROUND(1-AX79/21.75,2) -> 1 | AZ79: =COUNTIF(C:C,C79) -> 1 | BA79: =VLOOKUP(C79,工资表明细!$C$2:$P$223,13,0) -> 6225887832374785 | BB79: =BA79=AI79 -> TRUE | BC79: =ROUND(AR79/21.75/8*3*L79,2) -> 0
B80: 2026-07-01至2026-07-31 | C80: SCX00096 | D80: 谢琰 | E80: 创想悦动 | F80: 创想悦动 | G80: 平台运营部 | H80: 20.75 | K80: 0 | L80: 0 | N80: 0 | O80: 0 | P80: 0 | Q80: 0 | R80: 0 | S80: 0 | T80: 0 | U80: 0 | V80: 0 | W80: 0 | X80: 0 | Y80: 0 | AA80: 0 | AB80: 0 | AC80: 0 | AD80: 0 | AE80: 0 | AF80: 0 | AG80: 0 | AH80: 441827200202063628 | AI80: 6214833691023108 | AJ80: 创想悦动-销售 | AK80: 13028890431 | AL80: Wind@youdoogo.com | AM80: 材料科学与工程 | AN80: 实习人员 | AO80: 46234 | AR80: =VLOOKUP($C80,工资表明细!$C$2:$Q$190,14,0) -> 4000 | AS80: =VLOOKUP($C80,工资表明细!$C$2:$Q$190,15,0) -> 0 | AT80: =SUMIFS(其他补发!H:H,其他补发!B:B,C80) -> 0 | AU80: =ROUND((AR80+AS80+AT80)/21.75*(H80+O80+P80*0.3+AA80),2)-VLOOKUP(C80,工资表明细!$C$2:$U$190,19,0) -> 0 | AV80: =ROUND(AR80/21.75/8*2*(K80+L80*3/2),2)+SUMIFS(加班费!H:H,加班费!D:D,C80)-VLOOKUP(C80,工资表明细!$C$2:$W$190,21,0) -> 0 | AW80: =ROUND(AR80/21.75/8*2*(K80+L80*3/2),2) -> 0 | AX80: =ROUND(SUM(H80,O80,P80*0.3,AA80),2) -> 20.75 | AY80: =ROUND(1-AX80/21.75,2) -> 0.05 | AZ80: =COUNTIF(C:C,C80) -> 1 | BA80: =VLOOKUP(C80,工资表明细!$C$2:$P$223,13,0) -> 6214833691023108 | BB80: =BA80=AI80 -> TRUE | BC80: =ROUND(AR80/21.75/8*3*L80,2) -> 0
G87: 合计 | H87: =SUM(H3:H86) -> 59.25 | K87: =SUM(K2:K86) -> 0 | L87: =SUM(L3:L86) -> 0 | M87: =SUM(M3:M86) -> 0 | N87: =SUM(N3:N86) -> 0 | O87: =SUM(O3:O86) -> 5 | P87: =SUM(P3:P86) -> 5 | Q87: =SUM(Q3:Q86) -> 0 | R87: =SUM(R3:R86) -> 0 | S87: =SUM(S3:S86) -> 0 | T87: =SUM(T3:T86) -> 0 | W87: =SUM(W3:W86) -> 0 | X87: =SUM(X3:X86) -> 0 | Y87: =SUM(Y3:Y86) -> 0 | Z87: =SUM(Z3:Z86) -> 0 | AA87: =SUM(AA3:AA86) -> 0 | AR87: =SUM(AR3:AR86) -> 1790300 | AS87: =SUM(AS3:AS86) -> 0 | AU87: =SUM(AU3:AU86) -> 0 | AV87: =SUM(AV3:AV86) -> 0 | AW87: =SUM(AW3:AW86) -> 0 | BC87: =SUM(BC3:BC86) -> 0
G88: 检查 | H88: =H87-动态表!T12 -> 0

Sheet 加班费
A1: 序号 | B1: 项目 | C1: 部门 | D1: 工号 | E1: 姓名 | F1: 加班费标准 | G1: 出勤系数 | H1: 加班费 | I1: 备注 | J1: 陈燕 | K1: 检查1 | L1: 检查2 | M1: 检查3 | P1: 基本工资 | Q1: 周末加班小时 | R1: 法定加班小时 | S1: 加班费 | T1: 加班费合计
A2: 1 | H2: =ROUND(F2*G2,2) -> 0 | K2: =VLOOKUP(D2,考勤!$C$2:$D$189,2,0) -> #N/A | L2: =IF(E2=K2,1) -> #N/A | M2: =COUNTIF(D:D,D2) -> 0 | P2: =VLOOKUP(D2,工资表明细!$C$2:$P$290,14,0) -> 0 | Q2: =VLOOKUP($D2,考勤!$C$2:$L$100,9,0) -> #N/A | R2: =VLOOKUP($D2,考勤!$C$2:$L$100,10,0) -> #N/A | S2: =ROUND((P2/21.75/8*2*Q2)+(P2/21.75/8*3*R2),2) -> #N/A | T2: =H2+S2 -> #N/A | V2: =COUNTIF(D:D,D2) -> 0
A3: 2 | H3: =ROUND(F3*G3,2) -> 0 | K3: =VLOOKUP(D3,考勤!$C$2:$D$189,2,0) -> #N/A | L3: =IF(E3=K3,1) -> #N/A | M3: =COUNTIF(D:D,D3) -> 0 | P3: =VLOOKUP(D3,工资表明细!$C$2:$P$290,14,0) -> 0 | Q3: =VLOOKUP($D3,考勤!$C$2:$L$100,9,0) -> #N/A | R3: =VLOOKUP($D3,考勤!$C$2:$L$100,10,0) -> #N/A | S3: =ROUND((P3/21.75/8*2*Q3)+(P3/21.75/8*3*R3),2) -> #N/A | T3: =H3+S3 -> #N/A | V3: =COUNTIF(D:D,D3) -> 0
A4: 3 | H4: =ROUND(F4*G4,2) -> 0 | K4: =VLOOKUP(D4,考勤!$C$2:$D$189,2,0) -> #N/A | L4: =IF(E4=K4,1) -> #N/A | M4: =COUNTIF(D:D,D4) -> 0 | P4: =VLOOKUP(D4,工资表明细!$C$2:$P$290,14,0) -> 0 | Q4: =VLOOKUP($D4,考勤!$C$2:$L$100,9,0) -> #N/A | R4: =VLOOKUP($D4,考勤!$C$2:$L$100,10,0) -> #N/A | S4: =ROUND((P4/21.75/8*2*Q4)+(P4/21.75/8*3*R4),2) -> #N/A | T4: =H4+S4 -> #N/A | V4: =COUNTIF(D:D,D4) -> 0
A5: 4 | H5: =ROUND(F5*G5,2) -> 0 | K5: =VLOOKUP(D5,考勤!$C$2:$D$189,2,0) -> #N/A | L5: =IF(E5=K5,1) -> #N/A | M5: =COUNTIF(D:D,D5) -> 0 | P5: =VLOOKUP(D5,工资表明细!$C$2:$P$290,14,0) -> 0 | Q5: =VLOOKUP($D5,考勤!$C$2:$L$100,9,0) -> #N/A | R5: =VLOOKUP($D5,考勤!$C$2:$L$100,10,0) -> #N/A | S5: =ROUND((P5/21.75/8*2*Q5)+(P5/21.75/8*3*R5),2) -> #N/A | T5: =H5+S5 -> #N/A | V5: =COUNTIF(D:D,D5) -> 0
V7: =COUNTIF(D:D,D7) -> 0
G10: 合计 | H10: =SUM(H2:H9) -> 0
G11: 检查 | H11: =工资表明细!W83-H10-考勤!AW87 -> 0

Sheet 其他补发
A1: 序号 | B1: 工号 | C1: 姓名 | D1: 绩效工资 | E1: 通讯补贴 | F1: 伙食补贴 | G1: 住房补贴 | H1: 岗位津贴 | I1: 节日福利 | J1: 其他奖金 | K1: 其他补发 | L1: 其他扣款 | M1: 司机补贴 | N1: 专利奖 | P1: 备注 | Q1: 检查1 | R1: 检查2 | S1: 检查2 | T1: 工资表 | U1: 离职日期
A2: 1 | B2: SCX00058 | C2: 吴润泽 | K2: 200 | O2: 1 | P2: 生日福利（已发京东购物卡）随2026年7月工资报税 | Q2: =VLOOKUP(B2,考勤!C:F,2,0) -> 吴润泽 | R2: =IF(C2=Q2,1) -> 1 | S2: =COUNTIF(B:B,B2) -> 1 | T2: =VLOOKUP(B2,工资表明细!$C$2:$D$282,2,0)=C2 -> TRUE | U2: =VLOOKUP(B2,工资表明细!$C$2:$I$282,7,0) -> 0
A3: 2 | B3: SCX00070 | C3: 陈碧云 | K3: 200 | O3: 1 | P3: 生日福利（已发京东购物卡）随2026年7月工资报税 | Q3: =VLOOKUP(B3,考勤!C:F,2,0) -> 陈碧云 | R3: =IF(C3=Q3,1) -> 1 | S3: =COUNTIF(B:B,B3) -> 1 | T3: =VLOOKUP(B3,工资表明细!$C$2:$D$282,2,0)=C3 -> TRUE | U3: =VLOOKUP(B3,工资表明细!$C$2:$I$282,7,0) -> 0
A4: 3 | B4: SCX00071 | C4: 陈志鹏 | K4: 200 | O4: 1 | P4: 生日福利（已发京东购物卡）随2026年7月工资报税 | Q4: =VLOOKUP(B4,考勤!C:F,2,0) -> 陈志鹏 | R4: =IF(C4=Q4,1) -> 1 | S4: =COUNTIF(B:B,B4) -> 1 | T4: =VLOOKUP(B4,工资表明细!$C$2:$D$282,2,0)=C4 -> TRUE | U4: =VLOOKUP(B4,工资表明细!$C$2:$I$282,7,0) -> 0
A5: 4 | B5: SCX00092 | C5: 罗凯成 | K5: 200 | O5: 1 | P5: 生日福利（已发京东购物卡）随2026年7月工资报税 | Q5: =VLOOKUP(B5,考勤!C:F,2,0) -> 罗凯成 | R5: =IF(C5=Q5,1) -> 1 | S5: =COUNTIF(B:B,B5) -> 1 | T5: =VLOOKUP(B5,工资表明细!$C$2:$D$282,2,0)=C5 -> TRUE | U5: =VLOOKUP(B5,工资表明细!$C$2:$I$282,7,0) -> 0
A6: 1 | P6: ="剩余"&W6&"天剩余年假工资结算" -> 剩余天剩余年假工资结算 | Q6: =VLOOKUP(B6,考勤!C:F,2,0) -> #N/A | R6: =IF(C6=Q6,1) -> #N/A | S6: =COUNTIF(B:B,B6) -> 0 | T6: =VLOOKUP(B6,工资表明细!$C$2:$D$282,2,0)=C6 -> TRUE | U6: =VLOOKUP(B6,工资表明细!$C$2:$I$282,7,0) -> 0 | V6: =VLOOKUP(B6,工资表明细!$C$2:$P$59,14,0) -> #N/A | X6: =ROUND(V6/21.75*W6,2) -> #N/A | Y6: =X6-K6 -> #N/A
A7: 2 | P7: ="剩余"&W7&"天剩余年假工资结算" -> 剩余天剩余年假工资结算 | Q7: =VLOOKUP(B7,考勤!C:F,2,0) -> #N/A | R7: =IF(C7=Q7,1) -> #N/A | S7: =COUNTIF(B:B,B7) -> 0 | T7: =VLOOKUP(B7,工资表明细!$C$2:$D$282,2,0)=C7 -> TRUE | U7: =VLOOKUP(B7,工资表明细!$C$2:$I$282,7,0) -> 0 | V7: =VLOOKUP(B7,工资表明细!$C$2:$P$59,14,0) -> #N/A | X7: =ROUND(V7/21.75*W7,2) -> #N/A | Y7: =X7-K7 -> #N/A
A8: 1 | P8: ="剩余"&W8&"小时加班调休结算" -> 剩余小时加班调休结算 | Q8: =VLOOKUP(B8,考勤!C:F,2,0) -> #N/A | R8: =IF(C8=Q8,1) -> #N/A | S8: =COUNTIF(B:B,B8) -> 0 | T8: =VLOOKUP(B8,工资表明细!$C$2:$D$282,2,0)=C8 -> TRUE | U8: =VLOOKUP(B8,工资表明细!$C$2:$I$282,7,0) -> 0 | V8: =VLOOKUP(B8,工资表明细!$C$2:$P$59,14,0) -> #N/A | X8: =ROUND(V8/21.75/8*W8,2) -> #N/A | Y8: =X8-K8 -> #N/A
A9: 2 | P9: ="剩余"&W9&"小时加班调休结算" -> 剩余小时加班调休结算 | Q9: =VLOOKUP(B9,考勤!C:F,2,0) -> #N/A | R9: =IF(C9=Q9,1) -> #N/A | S9: =COUNTIF(B:B,B9) -> 0 | T9: =VLOOKUP(B9,工资表明细!$C$2:$D$282,2,0)=C9 -> TRUE | U9: =VLOOKUP(B9,工资表明细!$C$2:$I$282,7,0) -> 0 | V9: =VLOOKUP(B9,工资表明细!$C$2:$P$59,14,0) -> #N/A | X9: =ROUND(V9/21.75/8*W9,2) -> #N/A | Y9: =X9-K9 -> #N/A
C14: 合计 | D14: =SUM(D2:D13) -> 0 | E14: =SUM(E2:E13) -> 0 | F14: =SUM(F2:F13) -> 0 | G14: =SUM(G2:G13) -> 0 | H14: =SUM(H2:H13) -> 0 | I14: =SUM(I2:I13) -> 0 | J14: =SUM(J2:J13) -> 0 | K14: =SUM(K2:K13) -> 800 | ... N14: =SUM(N2:N13) -> 0 | S14: =ROUND(V6/21.75,2) -> #N/A | T14: =S14-X6 -> #N/A | U14: =S14*3-X8 -> #N/A
C15: 检查 | D15: =D14-工资表明细!Q83 -> 0 | E15: =E14-工资表明细!T83 -> 0 | F15: =F14-工资表明细!Z83 -> 0 | G15: =G14-工资表明细!AA83 -> 0 | H15: =H14-工资表明细!R83 -> 0 | I15: =I14-工资表明细!S83 -> 0 | J15: =J14-工资表明细!Y83 -> 0 | K15: =K14-工资表明细!AD83 -> 0 | L15: =工资表明细!V83-动态表!AA12-L14 -> 0 | M15: =M14-工资表明细!AB83 -> 0 | N15: =N14-工资表明细!AC83 -> 0 | S15: =ROUND(V7/21.75,2) -> #N/A | T15: =S15-X7 -> #N/A | U15: =V9/21.75*0.5-X9 -> #N/A

Sheet 奖金
A2: 序号 | B2: 项目 | C2: 部门 | D2: 工号 | E2: 姓名 | F2: 季度奖分摊 | G2: 备注 | H2: 陈燕 | I2: 检查1 | J2: 检查2 | K2: 检查3 | L2: 工资 | M2: 离职日期 | N2: 加班费分拆 | O2: 次数
A3: 1 | I3: =VLOOKUP(D3,考勤!C:F,2,0) -> #N/A | J3: =IF(E3=I3,1) -> #N/A | K3: =COUNTIF(D:D,D3) -> 0 | L3: =VLOOKUP(D3,工资表明细!$C$2:$D$116,2,0)=E3 -> TRUE | M3: =VLOOKUP(D3,工资表明细!$C$2:$I$116,7,0) -> 0 | O3: =COUNTIF(D:D,D3) -> 0 | P3: =VLOOKUP(D3,#REF!,2,0) -> #REF!
A4: 2 | I4: =VLOOKUP(D4,考勤!C:F,2,0) -> #N/A | J4: =IF(E4=I4,1) -> #N/A | K4: =COUNTIF(D:D,D4) -> 0 | L4: =VLOOKUP(D4,工资表明细!$C$2:$D$116,2,0)=E4 -> TRUE | M4: =VLOOKUP(D4,工资表明细!$C$2:$I$116,7,0) -> 0 | O4: =COUNTIF(D:D,D4) -> 0 | P4: =VLOOKUP(D4,#REF!,2,0) -> #REF!
A5: 3 | I5: =VLOOKUP(D5,考勤!C:F,2,0) -> #N/A | J5: =IF(E5=I5,1) -> #N/A | K5: =COUNTIF(D:D,D5) -> 0 | L5: =VLOOKUP(D5,工资表明细!$C$2:$D$116,2,0)=E5 -> TRUE | M5: =VLOOKUP(D5,工资表明细!$C$2:$I$116,7,0) -> 0 | O5: =COUNTIF(D:D,D5) -> 0 | P5: =VLOOKUP(D5,#REF!,2,0) -> #REF!
A6: 4 | I6: =VLOOKUP(D6,考勤!C:F,2,0) -> #N/A | J6: =IF(E6=I6,1) -> #N/A | K6: =COUNTIF(D:D,D6) -> 0 | L6: =VLOOKUP(D6,工资表明细!$C$2:$D$116,2,0)=E6 -> TRUE | M6: =VLOOKUP(D6,工资表明细!$C$2:$I$116,7,0) -> 0 | O6: =COUNTIF(D:D,D6) -> 0 | P6: =VLOOKUP(D6,#REF!,2,0) -> #REF!
A7: 5 | I7: =VLOOKUP(D7,考勤!C:F,2,0) -> #N/A | J7: =IF(E7=I7,1) -> #N/A | K7: =COUNTIF(D:D,D7) -> 0 | L7: =VLOOKUP(D7,工资表明细!$C$2:$D$116,2,0)=E7 -> TRUE | M7: =VLOOKUP(D7,工资表明细!$C$2:$I$116,7,0) -> 0 | O7: =COUNTIF(D:D,D7) -> 0 | P7: =VLOOKUP(D7,#REF!,2,0) -> #REF!
A8: 6 | I8: =VLOOKUP(D8,考勤!C:F,2,0) -> #N/A | J8: =IF(E8=I8,1) -> #N/A | K8: =COUNTIF(D:D,D8) -> 0 | L8: =VLOOKUP(D8,工资表明细!$C$2:$D$116,2,0)=E8 -> TRUE | M8: =VLOOKUP(D8,工资表明细!$C$2:$I$116,7,0) -> 0 | O8: =COUNTIF(D:D,D8) -> 0 | P8: =VLOOKUP(D8,#REF!,2,0) -> #REF!
A9: 7 | I9: =VLOOKUP(D9,考勤!C:F,2,0) -> #N/A | J9: =IF(E9=I9,1) -> #N/A | K9: =COUNTIF(D:D,D9) -> 0 | L9: =VLOOKUP(D9,工资表明细!$C$2:$D$116,2,0)=E9 -> TRUE | M9: =VLOOKUP(D9,工资表明细!$C$2:$I$116,7,0) -> 0 | O9: =COUNTIF(D:D,D9) -> 0 | P9: =VLOOKUP(D9,#REF!,2,0) -> #REF!
A10: 8 | I10: =VLOOKUP(D10,考勤!C:F,2,0) -> #N/A | J10: =IF(E10=I10,1) -> #N/A | K10: =COUNTIF(D:D,D10) -> 0 | L10: =VLOOKUP(D10,工资表明细!$C$2:$D$116,2,0)=E10 -> TRUE | M10: =VLOOKUP(D10,工资表明细!$C$2:$I$116,7,0) -> 0 | O10: =COUNTIF(D:D,D10) -> 0 | P10: =VLOOKUP(D10,#REF!,2,0) -> #REF!
A11: 9 | I11: =VLOOKUP(D11,考勤!C:F,2,0) -> #N/A | J11: =IF(E11=I11,1) -> #N/A | K11: =COUNTIF(D:D,D11) -> 0 | L11: =VLOOKUP(D11,工资表明细!$C$2:$D$116,2,0)=E11 -> TRUE | M11: =VLOOKUP(D11,工资表明细!$C$2:$I$116,7,0) -> 0 | O11: =COUNTIF(D:D,D11) -> 0 | P11: =VLOOKUP(D11,#REF!,2,0) -> #REF!
A12: 10 | I12: =VLOOKUP(D12,考勤!C:F,2,0) -> #N/A | J12: =IF(E12=I12,1) -> #N/A | K12: =COUNTIF(D:D,D12) -> 0 | L12: =VLOOKUP(D12,工资表明细!$C$2:$D$116,2,0)=E12 -> TRUE | M12: =VLOOKUP(D12,工资表明细!$C$2:$I$116,7,0) -> 0 | O12: =COUNTIF(D:D,D12) -> 0 | P12: =VLOOKUP(D12,#REF!,2,0) -> #REF!
A13: 11 | I13: =VLOOKUP(D13,考勤!C:F,2,0) -> #N/A | J13: =IF(E13=I13,1) -> #N/A | K13: =COUNTIF(D:D,D13) -> 0 | L13: =VLOOKUP(D13,工资表明细!$C$2:$D$116,2,0)=E13 -> TRUE | M13: =VLOOKUP(D13,工资表明细!$C$2:$I$116,7,0) -> 0 | O13: =COUNTIF(D:D,D13) -> 0 | P13: =VLOOKUP(D13,#REF!,2,0) -> #REF!
A14: 12 | I14: =VLOOKUP(D14,考勤!C:F,2,0) -> #N/A | J14: =IF(E14=I14,1) -> #N/A | K14: =COUNTIF(D:D,D14) -> 0 | L14: =VLOOKUP(D14,工资表明细!$C$2:$D$116,2,0)=E14 -> TRUE | M14: =VLOOKUP(D14,工资表明细!$C$2:$I$116,7,0) -> 0 | O14: =COUNTIF(D:D,D14) -> 0 | P14: =VLOOKUP(D14,#REF!,2,0) -> #REF!
A15: 13 | I15: =VLOOKUP(D15,考勤!C:F,2,0) -> #N/A | J15: =IF(E15=I15,1) -> #N/A | K15: =COUNTIF(D:D,D15) -> 0 | L15: =VLOOKUP(D15,工资表明细!$C$2:$D$116,2,0)=E15 -> TRUE | M15: =VLOOKUP(D15,工资表明细!$C$2:$I$116,7,0) -> 0 | O15: =COUNTIF(D:D,D15) -> 0 | P15: =VLOOKUP(D15,#REF!,2,0) -> #REF!
E17: 合计 | F17: =SUM(F3:F16) -> 0
E18: 检查1 | F18: =F17-工资表明细!X83 -> 0

Sheet 房租水电
A1: 工号 | B1: 姓名 | C1: 水电费（制造类） | D1: 水电费（数字公寓） | E1: 陈燕 | F1: 备注 | G1: 考勤表名字 | H1: 名字核对 | I1: 重复项 | J1: 工资表 | K1: 核对 | L1: 离职日期
G2: =VLOOKUP(A2,考勤!C:F,2,0) -> #N/A | H2: =IF(B2=G2,1) -> #N/A | I2: =COUNTIF(A:A,A2) -> 0 | J2: =VLOOKUP(A2,工资表明细!$C$2:$D$116,2,0) -> 0 | K2: =J2=B2 -> TRUE | L2: =VLOOKUP(A2,工资表明细!$C$2:$I$116,7,0) -> 0
G3: =VLOOKUP(A3,考勤!C:F,2,0) -> #N/A | H3: =IF(B3=G3,1) -> #N/A | I3: =COUNTIF(A:A,A3) -> 0 | J3: =VLOOKUP(A3,工资表明细!$C$2:$D$116,2,0) -> 0 | K3: =J3=B3 -> TRUE | L3: =VLOOKUP(A3,工资表明细!$C$2:$I$116,7,0) -> 0
G4: =VLOOKUP(A4,考勤!C:F,2,0) -> #N/A | H4: =IF(B4=G4,1) -> #N/A | I4: =COUNTIF(A:A,A4) -> 0 | J4: =VLOOKUP(A4,工资表明细!$C$2:$D$116,2,0) -> 0 | K4: =J4=B4 -> TRUE | L4: =VLOOKUP(A4,工资表明细!$C$2:$I$116,7,0) -> 0
G5: =VLOOKUP(A5,考勤!C:F,2,0) -> #N/A | H5: =IF(B5=G5,1) -> #N/A | I5: =COUNTIF(A:A,A5) -> 0 | J5: =VLOOKUP(A5,工资表明细!$C$2:$D$116,2,0) -> 0 | K5: =J5=B5 -> TRUE | L5: =VLOOKUP(A5,工资表明细!$C$2:$I$116,7,0) -> 0
G6: =VLOOKUP(A6,考勤!C:F,2,0) -> #N/A | H6: =IF(B6=G6,1) -> #N/A | I6: =COUNTIF(A:A,A6) -> 0 | J6: =VLOOKUP(A6,工资表明细!$C$2:$D$116,2,0) -> 0 | K6: =J6=B6 -> TRUE | L6: =VLOOKUP(A6,工资表明细!$C$2:$I$116,7,0) -> 0
G7: =VLOOKUP(A7,考勤!C:F,2,0) -> #N/A | H7: =IF(B7=G7,1) -> #N/A | I7: =COUNTIF(A:A,A7) -> 0 | J7: =VLOOKUP(A7,工资表明细!$C$2:$D$116,2,0) -> 0 | K7: =J7=B7 -> TRUE | L7: =VLOOKUP(A7,工资表明细!$C$2:$I$116,7,0) -> 0
G8: =VLOOKUP(A8,考勤!C:F,2,0) -> #N/A | H8: =IF(B8=G8,1) -> #N/A | I8: =COUNTIF(A:A,A8) -> 0 | J8: =VLOOKUP(A8,工资表明细!$C$2:$D$116,2,0) -> 0 | K8: =J8=B8 -> TRUE | L8: =VLOOKUP(A8,工资表明细!$C$2:$I$116,7,0) -> 0
G9: =VLOOKUP(A9,考勤!C:F,2,0) -> #N/A | H9: =IF(B9=G9,1) -> #N/A | I9: =COUNTIF(A:A,A9) -> 0 | J9: =VLOOKUP(A9,工资表明细!$C$2:$D$116,2,0) -> 0 | K9: =J9=B9 -> TRUE | L9: =VLOOKUP(A9,工资表明细!$C$2:$I$116,7,0) -> 0
B13: 合计 | C13: =SUM(C2:C12) -> 0 | D13: =SUM(D2:D12) -> 0
B14: 检查1 | C14: =C13-工资表明细!AH83 -> 0 | D14: =D13-工资表明细!AI83 -> 0

Sheet 税后扣款
A1: 序号 | B1: 工号 | C1: 姓名 | D1: 其他税后扣款 | E1: 借款逾期扣款 | G1: 备注 | H1: 公司 | I1: 考勤1表名字 | J1: 名字核对 | K1: 重复项 | L1: 工资表 | M1: 离职日期
A2: 1 | B2: SCX00058 | C2: 吴润泽 | D2: 200 | F2: 1 | G2: 生日福利（已发京东购物卡）随2026年7月工资报税 | H2: =VLOOKUP(B2,考勤!C:E,3,0) -> 创想悦动 | I2: =VLOOKUP(B2,考勤!C:F,2,0) -> 吴润泽 | J2: =IF(I2=C2,1) -> 1 | K2: =COUNTIF(B:B,B2) -> 2 | L2: =VLOOKUP(B2,工资表明细!$C$2:$D$352,2,0)=C2 -> TRUE | M2: =VLOOKUP(B2,工资表明细!$C$2:$I$352,7,0) -> 0
A3: 2 | B3: SCX00070 | C3: 陈碧云 | D3: 200 | F3: 1 | G3: 生日福利（已发京东购物卡）随2026年7月工资报税 | H3: =VLOOKUP(B3,考勤!C:E,3,0) -> 创想悦动 | I3: =VLOOKUP(B3,考勤!C:F,2,0) -> 陈碧云 | J3: =IF(I3=C3,1) -> 1 | K3: =COUNTIF(B:B,B3) -> 2 | L3: =VLOOKUP(B3,工资表明细!$C$2:$D$352,2,0)=C3 -> TRUE | M3: =VLOOKUP(B3,工资表明细!$C$2:$I$352,7,0) -> 0
A4: 3 | B4: SCX00071 | C4: 陈志鹏 | D4: 200 | F4: 1 | G4: 生日福利（已发京东购物卡）随2026年7月工资报税 | H4: =VLOOKUP(B4,考勤!C:E,3,0) -> 创想悦动 | I4: =VLOOKUP(B4,考勤!C:F,2,0) -> 陈志鹏 | J4: =IF(I4=C4,1) -> 1 | K4: =COUNTIF(B:B,B4) -> 1 | L4: =VLOOKUP(B4,工资表明细!$C$2:$D$352,2,0)=C4 -> TRUE | M4: =VLOOKUP(B4,工资表明细!$C$2:$I$352,7,0) -> 0
A5: 4 | B5: SCX00092 | C5: 罗凯成 | D5: 200 | F5: 1 | G5: 生日福利（已发京东购物卡）随2026年7月工资报税 | H5: =VLOOKUP(B5,考勤!C:E,3,0) -> 创想悦动 | I5: =VLOOKUP(B5,考勤!C:F,2,0) -> 罗凯成 | J5: =IF(I5=C5,1) -> 1 | K5: =COUNTIF(B:B,B5) -> 1 | L5: =VLOOKUP(B5,工资表明细!$C$2:$D$352,2,0)=C5 -> TRUE | M5: =VLOOKUP(B5,工资表明细!$C$2:$I$352,7,0) -> 0
A6: 1 | B6: SCX00038 | C6: 刘培琳 | D6: 1859.76 | F6: 1 | G6: 2026年7月人才房房租 | H6: =VLOOKUP(B6,考勤!C:E,3,0) -> 创想悦动 | I6: =VLOOKUP(B6,考勤!C:F,2,0) -> 刘培琳 | J6: =IF(I6=C6,1) -> 1 | K6: =COUNTIF(B:B,B6) -> 2 | L6: =VLOOKUP(B6,工资表明细!$C$2:$D$352,2,0)=C6 -> TRUE | M6: =VLOOKUP(B6,工资表明细!$C$2:$I$352,7,0) -> 0
A7: 2 | B7: SCX00029 | C7: 邱永恒 | D7: 4960.25 | F7: 1 | G7: 2026年7月人才房房租 | H7: =VLOOKUP(B7,考勤!C:E,3,0) -> 创想悦动 | I7: =VLOOKUP(B7,考勤!C:F,2,0) -> 邱永恒 | J7: =IF(I7=C7,1) -> 1 | K7: =COUNTIF(B:B,B7) -> 2 | L7: =VLOOKUP(B7,工资表明细!$C$2:$D$352,2,0)=C7 -> TRUE | M7: =VLOOKUP(B7,工资表明细!$C$2:$I$352,7,0) -> 0
A8: 1 | B8: SCX00001 | C8: 刘丹 | D8: -240 | G8: 2026年7月珠海发布会差旅补贴 | H8: =VLOOKUP(B8,考勤!C:E,3,0) -> 创想悦动 | I8: =VLOOKUP(B8,考勤!C:F,2,0) -> 刘丹 | J8: =IF(I8=C8,1) -> 1 | K8: =COUNTIF(B:B,B8) -> 1 | L8: =VLOOKUP(B8,工资表明细!$C$2:$D$352,2,0)=C8 -> TRUE | M8: =VLOOKUP(B8,工资表明细!$C$2:$I$352,7,0) -> 0
A9: 2 | B9: SCX00002 | C9: 李奕佳 | D9: -240 | G9: 2026年7月珠海发布会差旅补贴 | H9: =VLOOKUP(B9,考勤!C:E,3,0) -> 创想悦动 | I9: =VLOOKUP(B9,考勤!C:F,2,0) -> 李奕佳 | J9: =IF(I9=C9,1) -> 1 | K9: =COUNTIF(B:B,B9) -> 1 | L9: =VLOOKUP(B9,工资表明细!$C$2:$D$352,2,0)=C9 -> TRUE | M9: =VLOOKUP(B9,工资表明细!$C$2:$I$352,7,0) -> 0
A10: 3 | B10: SCX00003 | C10: 申华 | D10: -240 | G10: 2026年7月珠海发布会差旅补贴 | H10: =VLOOKUP(B10,考勤!C:E,3,0) -> 创想悦动 | I10: =VLOOKUP(B10,考勤!C:F,2,0) -> 申华 | J10: =IF(I10=C10,1) -> 1 | K10: =COUNTIF(B:B,B10) -> 1 | L10: =VLOOKUP(B10,工资表明细!$C$2:$D$352,2,0)=C10 -> TRUE | M10: =VLOOKUP(B10,工资表明细!$C$2:$I$352,7,0) -> 0
A11: 4 | B11: SCX00004 | C11: 杨晓波 | D11: -240 | G11: 2026年7月珠海发布会差旅补贴 | H11: =VLOOKUP(B11,考勤!C:E,3,0) -> 创想悦动 | I11: =VLOOKUP(B11,考勤!C:F,2,0) -> 杨晓波 | J11: =IF(I11=C11,1) -> 1 | K11: =COUNTIF(B:B,B11) -> 1 | L11: =VLOOKUP(B11,工资表明细!$C$2:$D$352,2,0)=C11 -> TRUE | M11: =VLOOKUP(B11,工资表明细!$C$2:$I$352,7,0) -> 0
A12: 5 | B12: SCX00005 | C12: 杨振 | D12: -160 | G12: 2026年7月珠海发布会差旅补贴 | H12: =VLOOKUP(B12,考勤!C:E,3,0) -> 创想悦动 | I12: =VLOOKUP(B12,考勤!C:F,2,0) -> 杨振 | J12: =IF(I12=C12,1) -> 1 | K12: =COUNTIF(B:B,B12) -> 1 | L12: =VLOOKUP(B12,工资表明细!$C$2:$D$352,2,0)=C12 -> TRUE | M12: =VLOOKUP(B12,工资表明细!$C$2:$I$352,7,0) -> 0
A13: 6 | B13: SCX00006 | C13: 蔡昕宇 | D13: -160 | G13: 2026年7月珠海发布会差旅补贴 | H13: =VLOOKUP(B13,考勤!C:E,3,0) -> 创想悦动 | I13: =VLOOKUP(B13,考勤!C:F,2,0) -> 蔡昕宇 | J13: =IF(I13=C13,1) -> 1 | K13: =COUNTIF(B:B,B13) -> 1 | L13: =VLOOKUP(B13,工资表明细!$C$2:$D$352,2,0)=C13 -> TRUE | M13: =VLOOKUP(B13,工资表明细!$C$2:$I$352,7,0) -> 0
A14: 7 | B14: SCX00016 | C14: 胡豪 | D14: -160 | G14: 2026年7月珠海发布会差旅补贴 | H14: =VLOOKUP(B14,考勤!C:E,3,0) -> 创想悦动 | I14: =VLOOKUP(B14,考勤!C:F,2,0) -> 胡豪 | J14: =IF(I14=C14,1) -> 1 | K14: =COUNTIF(B:B,B14) -> 1 | L14: =VLOOKUP(B14,工资表明细!$C$2:$D$352,2,0)=C14 -> TRUE | M14: =VLOOKUP(B14,工资表明细!$C$2:$I$352,7,0) -> 0
A15: 8 | B15: SCX00017 | C15: 谢华明 | D15: -160 | G15: 2026年7月珠海发布会差旅补贴 | H15: =VLOOKUP(B15,考勤!C:E,3,0) -> 创想悦动 | I15: =VLOOKUP(B15,考勤!C:F,2,0) -> 谢华明 | J15: =IF(I15=C15,1) -> 1 | K15: =COUNTIF(B:B,B15) -> 1 | L15: =VLOOKUP(B15,工资表明细!$C$2:$D$352,2,0)=C15 -> TRUE | M15: =VLOOKUP(B15,工资表明细!$C$2:$I$352,7,0) -> 0
A16: 9 | B16: SCX00019 | C16: 张文文 | D16: -160 | G16: 2026年7月珠海发布会差旅补贴 | H16: =VLOOKUP(B16,考勤!C:E,3,0) -> 创想悦动 | I16: =VLOOKUP(B16,考勤!C:F,2,0) -> 张文文 | J16: =IF(I16=C16,1) -> 1 | K16: =COUNTIF(B:B,B16) -> 1 | L16: =VLOOKUP(B16,工资表明细!$C$2:$D$352,2,0)=C16 -> TRUE | M16: =VLOOKUP(B16,工资表明细!$C$2:$I$352,7,0) -> 0
A17: 10 | B17: SCX00021 | C17: 刘禹豪 | D17: -240 | G17: 2026年7月珠海发布会差旅补贴 | H17: =VLOOKUP(B17,考勤!C:E,3,0) -> 创想悦动 | I17: =VLOOKUP(B17,考勤!C:F,2,0) -> 刘禹豪 | J17: =IF(I17=C17,1) -> 1 | K17: =COUNTIF(B:B,B17) -> 1 | L17: =VLOOKUP(B17,工资表明细!$C$2:$D$352,2,0)=C17 -> TRUE | M17: =VLOOKUP(B17,工资表明细!$C$2:$I$352,7,0) -> 0
A18: 11 | B18: SCX00022 | C18: 刘锦翔 | D18: -160 | G18: 2026年7月珠海发布会差旅补贴 | H18: =VLOOKUP(B18,考勤!C:E,3,0) -> 创想悦动 | I18: =VLOOKUP(B18,考勤!C:F,2,0) -> 刘锦翔 | J18: =IF(I18=C18,1) -> 1 | K18: =COUNTIF(B:B,B18) -> 1 | L18: =VLOOKUP(B18,工资表明细!$C$2:$D$352,2,0)=C18 -> TRUE | M18: =VLOOKUP(B18,工资表明细!$C$2:$I$352,7,0) -> 0
A19: 12 | B19: SCX00024 | C19: 黄馨玥 | D19: -160 | G19: 2026年7月珠海发布会差旅补贴 | H19: =VLOOKUP(B19,考勤!C:E,3,0) -> 创想悦动 | I19: =VLOOKUP(B19,考勤!C:F,2,0) -> 黄馨玥 | J19: =IF(I19=C19,1) -> 1 | K19: =COUNTIF(B:B,B19) -> 1 | L19: =VLOOKUP(B19,工资表明细!$C$2:$D$352,2,0)=C19 -> TRUE | M19: =VLOOKUP(B19,工资表明细!$C$2:$I$352,7,0) -> 0
... A55: 48 | B55: SCX00088 | C55: 郑立文 | D55: -160 | G55: 2026年7月珠海发布会差旅补贴 | H55: =VLOOKUP(B55,考勤!C:E,3,0) -> 创想悦动 | I55: =VLOOKUP(B55,考勤!C:F,2,0) -> 郑立文 | J55: =IF(I55=C55,1) -> 1 | K55: =COUNTIF(B:B,B55) -> 1 | L55: =VLOOKUP(B55,工资表明细!$C$2:$D$352,2,0)=C55 -> TRUE | M55: =VLOOKUP(B55,工资表明细!$C$2:$I$352,7,0) -> 0
C59: 合计 | D59: =SUM(D2:D58) -> -699.99 | E59: =SUM(E2:E58) -> 0
C60: 检查1 | D60: =D59-工资表明细!AJ83 -> 0 | E60: =E59-工资表明细!AG83 -> 0

Sheet 社会保险
A1: 序号 | B1: 电脑号 | C1: 姓名 | D1: 身份证号 | E1: 应收合计 | F1: 个人合计 | G1: 单位合计 | H1: 养老缴费基数 | I1: 养老个人交 | J1: 医疗个人交 | K1: 失业个人交 | L1: 缴纳公司 | M1: 备注 | O1: 检查1 | P1: 检查3 | Q1: 检查4 | R1: 员工状态 | S1: 离职日期 | T1: 次数
A2: 1 | B2: 440306199306280437 | C2: 丘深壬 | D2: 440306199306280437 | E2: 8725 | F2: 2550 | G2: 6175 | H2: 25000 | I2: 2000 | J2: 500 | K2: 50 | L2: 创想悦动 | M2: 1 | O2: =VLOOKUP(C2,考勤!D:D,1,0) -> 丘深壬 | P2: =VLOOKUP(D2,工资表明细!$N$2:$AL$223,25,0) -> 2000 | Q2: =I2-P2 -> 0 | R2: 在职 | S2: 0 | T2: =COUNTIF(D:D,D2) -> 1
A3: 2 | B3: 441202199712254015 | C3: 何泽浩 | D3: 441202199712254015 | E3: 4886 | F3: 1428 | G3: 3458 | H3: 14000 | I3: 1120 | J3: 280 | K3: 28 | L3: 创想悦动 | M3: 1 | O3: =VLOOKUP(C3,考勤!D:D,1,0) -> 何泽浩 | P3: =VLOOKUP(D3,工资表明细!$N$2:$AL$223,25,0) -> 1120 | Q3: =I3-P3 -> 0 | R3: 在职 | S3: 0 | T3: =COUNTIF(D:D,D3) -> 1
A4: 3 | B4: 220581197802250174 | C4: 何洋 | D4: 220581197802250174 | E4: 9960.57 | F4: 2946.58 | G4: 7013.99 | H4: 35000 | I4: 2203.92 | J4: 672.66 | K4: 70 | L4: 创想悦动 | M4: 1 | O4: =VLOOKUP(C4,考勤!D:D,1,0) -> 何洋 | P4: =VLOOKUP(D4,工资表明细!$N$2:$AL$223,25,0) -> 2203.92 | Q4: =I4-P4 -> 0 | R4: 在职 | S4: 0 | T4: =COUNTIF(D:D,D4) -> 1
A5: 4 | B5: 420602199809040010 | C5: 刘临风 | D5: 420602199809040010 | E5: 6631 | F5: 1938 | G5: 4693 | H5: 19000 | I5: 1520 | J5: 380 | K5: 38 | L5: 创想悦动 | M5: 1 | O5: =VLOOKUP(C5,考勤!D:D,1,0) -> 刘临风 | P5: =VLOOKUP(D5,工资表明细!$N$2:$AL$223,25,0) -> 1520 | Q5: =I5-P5 -> 0 | R5: 在职 | S5: 0 | T5: =COUNTIF(D:D,D5) -> 1
A6: 5 | B6: 420502197605290638 | C6: 刘丹 | D6: 420502197605290638 | E6: 10430.77 | F6: 2973.52 | G6: 7457.25 | H6: 50000 | I6: 2203.92 | J6: 672.66 | K6: 96.94 | L6: 创想悦动 | M6: 1 | O6: =VLOOKUP(C6,考勤!D:D,1,0) -> 刘丹 | P6: =VLOOKUP(D6,工资表明细!$N$2:$AL$223,25,0) -> 2203.92 | Q6: =I6-P6 -> 0 | R6: 在职 | S6: 0 | T6: =COUNTIF(D:D,D6) -> 1
A7: 6 | B7: 130302198202073916 | C7: 刘伟 | D7: 130302198202073916 | E7: 10100.57 | F7: 2966.58 | G7: 7133.99 | H7: 45000 | I7: 2203.92 | J7: 672.66 | K7: 90 | L7: 创想悦动 | M7: 1 | O7: =VLOOKUP(C7,考勤!D:D,1,0) -> 刘伟 | P7: =VLOOKUP(D7,工资表明细!$N$2:$AL$223,25,0) -> 2203.92 | Q7: =I7-P7 -> 0 | R7: 在职 | S7: 0 | T7: =COUNTIF(D:D,D7) -> 1
A8: 7 | B8: 431103200105290625 | C8: 刘培琳 | D8: 431103200105290625 | E8: 3141 | F8: 918 | G8: 2223 | H8: 9000 | I8: 720 | J8: 180 | K8: 18 | L8: 创想悦动 | M8: 1 | O8: =VLOOKUP(C8,考勤!D:D,1,0) -> 刘培琳 | P8: =VLOOKUP(D8,工资表明细!$N$2:$AL$223,25,0) -> 720 | Q8: =I8-P8 -> 0 | R8: 在职 | S8: 0 | T8: =COUNTIF(D:D,D8) -> 1
A9: 8 | B9: 440921198308169216 | C9: 刘奎廷 | D9: 440921198308169216 | E9: 9857.25 | F9: 2863.92 | G9: 6993.33 | H9: 30000 | I9: 2203.92 | J9: 600 | K9: 60 | L9: 创想悦动 | M9: 1 | O9: =VLOOKUP(C9,考勤!D:D,1,0) -> 刘奎廷 | P9: =VLOOKUP(D9,工资表明细!$N$2:$AL$223,25,0) -> 2203.92 | Q9: =I9-P9 -> 0 | R9: 在职 | S9: 0 | T9: =COUNTIF(D:D,D9) -> 1
A10: 9 | B10: 420984198610014049 | C10: 刘婷 | D10: 420984198610014049 | E10: 5235 | F10: 1530 | G10: 3705 | H10: 15000 | I10: 1200 | J10: 300 | K10: 30 | L10: 创想悦动 | M10: 1 | O10: =VLOOKUP(C10,考勤!D:D,1,0) -> 刘婷 | P10: =VLOOKUP(D10,工资表明细!$N$2:$AL$223,25,0) -> 1200 | Q10: =I10-P10 -> 0 | R10: 在职 | S10: 0 | T10: =COUNTIF(D:D,D10) -> 1
A11: 10 | B11: 422126197808290516 | C11: 刘永松 | D11: 422126197808290516 | E11: 10430.77 | F11: 2973.52 | G11: 7457.25 | H11: 50000 | I11: 2203.92 | J11: 672.66 | K11: 96.94 | L11: 创想悦动 | M11: 1 | O11: =VLOOKUP(C11,考勤!D:D,1,0) -> 刘永松 | P11: =VLOOKUP(D11,工资表明细!$N$2:$AL$223,25,0) -> 2203.92 | Q11: =I11-P11 -> 0 | R11: 在职 | S11: 0 | T11: =COUNTIF(D:D,D11) -> 1
A12: 11 | B12: 421081199801124782 | C12: 刘玉娴 | D12: 421081199801124782 | E12: 6102 | F12: 1836 | G12: 4266 | H12: 18000 | I12: 1440 | J12: 360 | K12: 36 | L12: 创想悦动 | M12: 1 | O12: =VLOOKUP(C12,考勤!D:D,1,0) -> 刘玉娴 | P12: =VLOOKUP(D12,工资表明细!$N$2:$AL$223,25,0) -> 1440 | Q12: =I12-P12 -> 0 | R12: 在职 | S12: 0 | T12: =COUNTIF(D:D,D12) -> 1
A13: 12 | B13: 220402199004240017 | C13: 刘禹豪 | D13: 220402199004240017 | E13: 9423 | F13: 2754 | G13: 6669 | H13: 27000 | I13: 2160 | J13: 540 | K13: 54 | L13: 创想悦动 | M13: 1 | O13: =VLOOKUP(C13,考勤!D:D,1,0) -> 刘禹豪 | P13: =VLOOKUP(D13,工资表明细!$N$2:$AL$223,25,0) -> 2160 | Q13: =I13-P13 -> 0 | R13: 在职 | S13: 0 | T13: =COUNTIF(D:D,D13) -> 1
... A72: 71 | B72: 510107200005064246 | C72: 黄馨玥 | D72: 510107200005064246 | E72: 4746 | F72: 1428 | G72: 3318 | H72: 14000 | I72: 1120 | J72: 280 | K72: 28 | L72: 创想悦动 | M72: 1 | O72: =VLOOKUP(C72,考勤!D:D,1,0) -> 黄馨玥 | P72: =VLOOKUP(D72,工资表明细!$N$2:$AL$223,25,0) -> 1120 | Q72: =I72-P72 -> 0 | R72: 在职 | S72: 0 | T72: =COUNTIF(D:D,D72) -> 1
E82: =SUM(E2:E81) -> 523749.64 | F82: =SUM(F2:F81) -> 154261.74 | G82: =SUM(G2:G81) -> 369487.9 | I82: =SUM(I2:I81) -> 119278.4 | J82: =SUM(J2:J81) -> 31611.92 | K82: =SUM(K2:K81) -> 3371.42
I83: =I82-工资表明细!AL83 -> 0 | J83: =J82-工资表明细!AM83 -> 0 | K83: =K82-工资表明细!AN83 -> 0
G85: 检查1 | H85: 上月 | I85: 107394.48 | J85: 28599.26 | K85: 3005.78
G86: 检查2 | H86: 差异 | I86: =I82-I85 -> 11883.92 | J86: =J82-J85 -> 3012.66 | K86: =K82-K85 -> 365.64

Sheet 公积金
A1: 序号 | B1: 姓名 | C1: 身份证号码 | D1: 个人公积金账号 | E1: 缴存月份 | F1: 缴存基数 | G1: 单位缴存比例 | H1: 个人缴存比例 | I1: 缴存额 | J1: 所属公司 | K1: 单位缴 | L1: 个人缴 | M1: 备注 | N1: 检查1 | O1: 检查2 | P1: 检查3 | Q1: 检查4 | R1: 检查5 | T1: 检查1 | U1: 次数 | V1: 次数
A2: 1 | B2: 程蒙 | C2: 410811198111035034 | D2: 20192715407 | E2: 202607-202607 | F2: 19000 | G2: 0.06 | H2: 0.06 | I2: 2280 | J2: 创想悦动 | K2: 1140 | L2: 1140 | N2: =VLOOKUP(B2,工资表明细!$D$2:$AO$116,38,0) -> 1140 | O2: =F2*H2-L2 -> 0 | P2: =VLOOKUP(C2,工资表明细!$N$2:$AO$116,28,0) -> 1140 | Q2: =F2*H2-L2 -> 0 | R2: =P2+F2*G2-I2 -> 0 | T2: =VLOOKUP(B2,考勤!D:D,1,0) -> 程蒙 | U2: =COUNTIF(B:B,B2) -> 1 | V2: =COUNTIF(C:C,C2) -> 1
A3: 2 | B3: 陈碧云 | C3: 360281198707072145 | D3: 20313782797 | E3: 202607-202607 | F3: 20000 | G3: 0.06 | H3: 0.06 | I3: 2400 | J3: 创想悦动 | K3: 1200 | L3: 1200 | N3: =VLOOKUP(B3,工资表明细!$D$2:$AO$116,38,0) -> 1200 | O3: =F3*H3-L3 -> 0 | P3: =VLOOKUP(C3,工资表明细!$N$2:$AO$116,28,0) -> 1200 | Q3: =F3*H3-L3 -> 0 | R3: =P3+F3*G3-I3 -> 0 | T3: =VLOOKUP(B3,考勤!D:D,1,0) -> 陈碧云 | U3: =COUNTIF(B:B,B3) -> 1 | V3: =COUNTIF(C:C,C3) -> 1
A4: 3 | B4: 郑琦 | C4: 440882198405198016 | D4: 20911334251 | E4: 202607-202607 | F4: 22000 | G4: 0.06 | H4: 0.12 | I4: 3960 | J4: 创想悦动 | K4: 1320 | L4: 2640 | N4: =VLOOKUP(B4,工资表明细!$D$2:$AO$116,38,0) -> 2640 | O4: =F4*H4-L4 -> 0 | P4: =VLOOKUP(C4,工资表明细!$N$2:$AO$116,28,0) -> 2640 | Q4: =F4*H4-L4 -> 0 | R4: =P4+F4*G4-I4 -> 0 | T4: =VLOOKUP(B4,考勤!D:D,1,0) -> 郑琦 | U4: =COUNTIF(B:B,B4) -> 1 | V4: =COUNTIF(C:C,C4) -> 1
A5: 4 | B5: 曾育辉 | C5: 350681198011020558 | D5: 21395160730 | E5: 202607-202607 | F5: 30000 | G5: 0.06 | H5: 0.12 | I5: 5400 | J5: 创想悦动 | K5: 1800 | L5: 3600 | N5: =VLOOKUP(B5,工资表明细!$D$2:$AO$116,38,0) -> 3600 | O5: =F5*H5-L5 -> 0 | P5: =VLOOKUP(C5,工资表明细!$N$2:$AO$116,28,0) -> 3600 | Q5: =F5*H5-L5 -> 0 | R5: =P5+F5*G5-I5 -> 0 | T5: =VLOOKUP(B5,考勤!D:D,1,0) -> 曾育辉 | U5: =COUNTIF(B:B,B5) -> 1 | V5: =COUNTIF(C:C,C5) -> 1
A6: 5 | B6: 赵敬亭 | C6: 632826199006220029 | D6: 20765375085 | E6: 202607-202607 | F6: 28000 | G6: 0.06 | H6: 0.12 | I6: 5040 | J6: 创想悦动 | K6: 1680 | L6: 3360 | N6: =VLOOKUP(B6,工资表明细!$D$2:$AO$116,38,0) -> 3360 | O6: =F6*H6-L6 -> 0 | P6: =VLOOKUP(C6,工资表明细!$N$2:$AO$116,28,0) -> 3360 | Q6: =F6*H6-L6 -> 0 | R6: =P6+F6*G6-I6 -> 0 | T6: =VLOOKUP(B6,考勤!D:D,1,0) -> 赵敬亭 | U6: =COUNTIF(B:B,B6) -> 1 | V6: =COUNTIF(C:C,C6) -> 1
A7: 6 | B7: 潘瑜 | C7: 450205198310281016 | D7: 20575085179 | E7: 202607-202607 | F7: 28000 | G7: 0.06 | H7: 0.12 | I7: 5040 | J7: 创想悦动 | K7: 1680 | L7: 3360 | N7: =VLOOKUP(B7,工资表明细!$D$2:$AO$116,38,0) -> 3360 | O7: =F7*H7-L7 -> 0 | P7: =VLOOKUP(C7,工资表明细!$N$2:$AO$116,28,0) -> 3360 | Q7: =F7*H7-L7 -> 0 | R7: =P7+F7*G7-I7 -> 0 | T7: =VLOOKUP(B7,考勤!D:D,1,0) -> 潘瑜 | U7: =COUNTIF(B:B,B7) -> 1 | V7: =COUNTIF(C:C,C7) -> 1
A8: 7 | B8: 王生强 | C8: 642103198105045216 | D8: 20241668493 | E8: 202607-202607 | F8: 35000 | G8: 0.06 | H8: 0.12 | I8: 6300 | J8: 创想悦动 | K8: 2100 | L8: 4200 | N8: =VLOOKUP(B8,工资表明细!$D$2:$AO$116,38,0) -> 4200 | O8: =F8*H8-L8 -> 0 | P8: =VLOOKUP(C8,工资表明细!$N$2:$AO$116,28,0) -> 4200 | Q8: =F8*H8-L8 -> 0 | R8: =P8+F8*G8-I8 -> 0 | T8: =VLOOKUP(B8,考勤!D:D,1,0) -> 王生强 | U8: =COUNTIF(B:B,B8) -> 1 | V8: =COUNTIF(C:C,C8) -> 1
A9: 8 | B9: 狄慕华 | C9: 430406198904091512 | D9: 21000542018 | E9: 202607-202607 | F9: 26500 | G9: 0.06 | H9: 0.12 | I9: 4770 | J9: 创想悦动 | K9: 1590 | L9: 3180 | N9: =VLOOKUP(B9,工资表明细!$D$2:$AO$116,38,0) -> 3180 | O9: =F9*H9-L9 -> 0 | P9: =VLOOKUP(C9,工资表明细!$N$2:$AO$116,28,0) -> 3180 | Q9: =F9*H9-L9 -> 0 | R9: =P9+F9*G9-I9 -> 0 | T9: =VLOOKUP(B9,考勤!D:D,1,0) -> 狄慕华 | U9: =COUNTIF(B:B,B9) -> 1 | V9: =COUNTIF(C:C,C9) -> 1
A10: 9 | B10: 丘深壬 | C10: 440306199306280437 | D10: 21255134556 | E10: 202607-202607 | F10: 25000 | G10: 0.06 | H10: 0.06 | I10: 3000 | J10: 创想悦动 | K10: 1500 | L10: 1500 | N10: =VLOOKUP(B10,工资表明细!$D$2:$AO$116,38,0) -> 1500 | O10: =F10*H10-L10 -> 0 | P10: =VLOOKUP(C10,工资表明细!$N$2:$AO$116,28,0) -> 1500 | Q10: =F10*H10-L10 -> 0 | R10: =P10+F10*G10-I10 -> 0 | T10: =VLOOKUP(B10,考勤!D:D,1,0) -> 丘深壬 | U10: =COUNTIF(B:B,B10) -> 1 | V10: =COUNTIF(C:C,C10) -> 1
A11: 10 | B11: 李钊 | C11: 610303198311301210 | D11: 20038357882 | E11: 202607-202607 | F11: 36000 | G11: 0.06 | H11: 0.06 | I11: 4320 | J11: 创想悦动 | K11: 2160 | L11: 2160 | N11: =VLOOKUP(B11,工资表明细!$D$2:$AO$116,38,0) -> 2160 | O11: =F11*H11-L11 -> 0 | P11: =VLOOKUP(C11,工资表明细!$N$2:$AO$116,28,0) -> 2160 | Q11: =F11*H11-L11 -> 0 | R11: =P11+F11*G11-I11 -> 0 | T11: =VLOOKUP(B11,考勤!D:D,1,0) -> 李钊 | U11: =COUNTIF(B:B,B11) -> 1 | V11: =COUNTIF(C:C,C11) -> 1
A12: 11 | B12: 陈曦 | C12: 120106198508234519 | D12: 20038642899 | E12: 202607-202607 | F12: 25000 | G12: 0.06 | H12: 0.06 | I12: 3000 | J12: 创想悦动 | K12: 1500 | L12: 1500 | N12: =VLOOKUP(B12,工资表明细!$D$2:$AO$116,38,0) -> 1500 | O12: =F12*H12-L12 -> 0 | P12: =VLOOKUP(C12,工资表明细!$N$2:$AO$116,28,0) -> 1500 | Q12: =F12*H12-L12 -> 0 | R12: =P12+F12*G12-I12 -> 0 | T12: =VLOOKUP(B12,考勤!D:D,1,0) -> 陈曦 | U12: =COUNTIF(B:B,B12) -> 1 | V12: =COUNTIF(C:C,C12) -> 1
A13: 12 | B13: 杨振 | C13: 110105197902051515 | D13: 20038195204 | E13: 202607-202607 | F13: 44265 | G13: 0.06 | H13: 0.06 | I13: 5311.8 | J13: 创想悦动 | K13: 2655.9 | L13: 2655.9 | N13: =VLOOKUP(B13,工资表明细!$D$2:$AO$116,38,0) -> 2655.9 | O13: =F13*H13-L13 -> 0 | P13: =VLOOKUP(C13,工资表明细!$N$2:$AO$116,28,0) -> 2655.9 | Q13: =F13*H13-L13 -> 0 | R13: =P13+F13*G13-I13 -> 0 | T13: =VLOOKUP(B13,考勤!D:D,1,0) -> 杨振 | U13: =COUNTIF(B:B,B13) -> 1 | V13: =COUNTIF(C:C,C13) -> 1
... A72: 71 | B72: 吴润泽 | C72: 44050919970721561X | D72: 22324073558 | E72: 202607-202607 | F72: 26000 | G72: 0.06 | H72: 0.09 | I72: 3900 | J72: 创想悦动 | K72: 1560 | L72: 2340 | N72: =VLOOKUP(B72,工资表明细!$D$2:$AO$116,38,0) -> 2340 | O72: =F72*H72-L72 -> 0 | P72: =VLOOKUP(C72,工资表明细!$N$2:$AO$116,28,0) -> 2340 | Q72: =F72*H72-L72 -> 0 | R72: =P72+F72*G72-I72 -> 0 | T72: =VLOOKUP(B72,考勤!D:D,1,0) -> 吴润泽 | U72: =COUNTIF(B:B,B72) -> 1 | V72: =COUNTIF(C:C,C72) -> 1
U82: =SUM(U1:U79) -> 71
I83: =SUM(I1:I82) -> 230028.5 | L83: =SUM(L2:L82) -> 131083.1
H84: 检查1 | L84: =L83-工资表明细!AO83 -> 0
H86: 上月 | I86: 180490.8
H87: 差异 | I87: =I83-I86 -> 49537.7

Sheet 专项扣除
A1: 序号 | B1: 工号 | C1: 姓名 | D1: 累计子女教育 | E1: 累计继续教育 | F1: 累计住房贷款利息 | G1: 累计住房租金 | H1: 累计赡养老人 | I1: 累计3岁以下婴幼儿照护 | J1: 累计个人养老金 | K1: 工资-子女教育 | L1: 校验 | M1: 合计 | O1: 检查1 | P1: 检查2 | Q1: 离职日期
A2: 1 | B2: SCX00064 | C2: 王生强 | D2: 0 | E2: 0 | F2: 0 | G2: 0 | H2: 4500 | I2: 0 | J2: 0 | K2: =VLOOKUP(B2,工资表明细!$C$2:$AP$252,40,0) -> 0 | L2: =D2-K2 -> 0 | M2: =SUM(D2:J2) -> 4500 | O2: =VLOOKUP(B2,考勤!C:F,2,0) -> 王生强 | P2: =IF(C2=O2,1) -> 1 | Q2: =VLOOKUP(B2,工资表明细!$C$2:$I$495,7,0) -> 0
A3: 2 | B3: SCX00037 | C3: 李艾龙 | D3: 0 | E3: 0 | F3: 7000 | G3: 0 | H3: 0 | I3: 0 | J3: 0 | K3: =VLOOKUP(B3,工资表明细!$C$2:$AP$252,40,0) -> 0 | L3: =D3-K3 -> 0 | M3: =SUM(D3:J3) -> 7000 | O3: =VLOOKUP(B3,考勤!C:F,2,0) -> 李艾龙 | P3: =IF(C3=O3,1) -> 1 | Q3: =VLOOKUP(B3,工资表明细!$C$2:$I$495,7,0) -> 0
A4: 3 | B4: SCX00038 | C4: 刘培琳 | D4: 0 | E4: 0 | F4: 0 | G4: 9000 | H4: 0 | I4: 0 | J4: 0 | K4: =VLOOKUP(B4,工资表明细!$C$2:$AP$252,40,0) -> 0 | L4: =D4-K4 -> 0 | M4: =SUM(D4:J4) -> 9000 | O4: =VLOOKUP(B4,考勤!C:F,2,0) -> 刘培琳 | P4: =IF(C4=O4,1) -> 1 | Q4: =VLOOKUP(B4,工资表明细!$C$2:$I$495,7,0) -> 0
A5: 4 | B5: SCX00022 | C5: 刘锦翔 | D5: 0 | E5: 0 | F5: 0 | G5: 10500 | H5: 0 | I5: 0 | J5: 0 | K5: =VLOOKUP(B5,工资表明细!$C$2:$AP$252,40,0) -> 0 | L5: =D5-K5 -> 0 | M5: =SUM(D5:J5) -> 10500 | O5: =VLOOKUP(B5,考勤!C:F,2,0) -> 刘锦翔 | P5: =IF(C5=O5,1) -> 1 | Q5: =VLOOKUP(B5,工资表明细!$C$2:$I$495,7,0) -> 0
A6: 5 | B6: SCX00023 | C6: 刘永松 | D6: 28000 | E6: 0 | F6: 7000 | G6: 0 | H6: 10500 | I6: 0 | J6: 0 | K6: =VLOOKUP(B6,工资表明细!$C$2:$AP$252,40,0) -> 28000 | L6: =D6-K6 -> 0 | M6: =SUM(D6:J6) -> 45500 | O6: =VLOOKUP(B6,考勤!C:F,2,0) -> 刘永松 | P6: =IF(C6=O6,1) -> 1 | Q6: =VLOOKUP(B6,工资表明细!$C$2:$I$495,7,0) -> 0
A7: 6 | B7: SCX00002 | C7: 李奕佳 | D7: 0 | E7: 0 | F7: 0 | G7: 10500 | H7: 0 | I7: 0 | J7: 0 | M7: =SUM(D7:J7) -> 10500 | O7: =VLOOKUP(B7,考勤!C:F,2,0) -> 李奕佳 | P7: =IF(C7=O7,1) -> 1 | Q7: =VLOOKUP(B7,工资表明细!$C$2:$I$495,7,0) -> 0
A8: 7 | B8: SCX00017 | C8: 谢华明 | D8: 14000 | E8: 0 | F8: 0 | G8: 0 | H8: 21000 | I8: 0 | J8: 0 | K8: =VLOOKUP(B8,工资表明细!$C$2:$AP$252,40,0) -> 14000 | L8: =D8-K8 -> 0 | M8: =SUM(D8:J8) -> 35000 | O8: =VLOOKUP(B8,考勤!C:F,2,0) -> 谢华明 | P8: =IF(C8=O8,1) -> 1 | Q8: =VLOOKUP(B8,工资表明细!$C$2:$I$495,7,0) -> 0
C13: 合计 | D13: =SUM(D2:D12) -> 42000 | E13: =SUM(E2:E12) -> 0 | F13: =SUM(F2:F12) -> 14000 | G13: =SUM(G2:G12) -> 30000 | H13: =SUM(H2:H12) -> 36000 | I13: =SUM(I2:I12) -> 0 | J13: =SUM(J2:J12) -> 0
C14: 校验 | D14: =D13-工资表明细!AP83 -> 0 | E14: =E13-工资表明细!AQ83 -> 0 | F14: =F13-工资表明细!AR83 -> 0 | G14: =G13-工资表明细!AS83 -> 0 | H14: =H13-工资表明细!AT83 -> 0 | I14: =I13-工资表明细!AU83 -> 0 | J14: =J13-工资表明细!AV83 -> 0

Sheet 上月累计工资累计社保和公积金
A1: 序号 | B1: 公司 | C1: 工号 | D1: 姓名 | E1: 应付工资 | F1: 养老保险 | G1: 医疗保险 | H1: 失业保险 | I1: 住房公积金 | J1: 免税额 | K1: 本月合计扣除 | L1: 已交个人所得税 | M1: 月份 | N1: 检查 | O1: 公司更改校验
A2: 1 | B2: 创想悦动 | C2: SCX00001 | D2: 刘丹 | E2: 50000 | F2: 2203.92 | G2: 673.32 | H2: 88.53 | I2: 2655.9 | J2: 5000 | K2: 10621.67 | L2: 1417.83 | M2: 45992 | N2: =K2-F2-G2-H2-I2-J2 -> 0
A3: 2 | B3: 创想悦动 | C3: SCX00002 | D3: 李奕佳 | E3: 14000 | F3: 1120 | G3: 280 | H3: 28 | I3: 840 | J3: 5000 | K3: 7268 | L3: 201.96 | M3: 45992 | N3: =K3-F3-G3-H3-I3-J3 -> 0
A4: 3 | B4: 创想悦动 | C4: SCX00003 | D4: 申华 | E4: 50000 | F4: 2203.92 | G4: 673.32 | H4: 88.53 | I4: 2655.9 | J4: 5000 | K4: 10621.67 | L4: 1417.83 | M4: 45992 | N4: =K4-F4-G4-H4-I4-J4 -> 0 | Q4: 应付工资 | R4: 本月合计扣除 | S4: 已交个人所得税
A5: 4 | B5: 创想悦动 | C5: SCX00004 | D5: 杨晓波 | E5: 48000 | F5: 2203.92 | G5: 673.32 | H5: 88.53 | I5: 2655.9 | J5: 5000 | K5: 10621.67 | L5: 1217.83 | M5: 45992 | N5: =K5-F5-G5-H5-I5-J5 -> 0 | Q5: =SUM(E2:E47) -> 1157834.8 | R5: =SUM(K2:K47) -> 400025.42 | S5: =SUM(L2:L47) -> 23657.37
A6: 5 | B6: 创想悦动 | C6: SCX00005 | D6: 杨振 | E6: 45000 | F6: 2203.92 | G6: 673.32 | H6: 88.53 | I6: 2655.9 | J6: 5000 | K6: 10621.67 | L6: 1031.35 | M6: 45992 | N6: =K6-F6-G6-H6-I6-J6 -> 0
A7: 6 | B7: 创想悦动 | C7: SCX00006 | D7: 蔡昕宇 | E7: 35000 | F7: 0 | G7: 0 | H7: 0 | I7: 0 | J7: 5000 | K7: 5000 | L7: 900 | M7: 45992 | N7: =K7-F7-G7-H7-I7-J7 -> 0 | Q7: 1157834.8 | R7: 400025.42 | S7: 23657.37
A8: 7 | B8: 创想悦动 | C8: SCX00007 | D8: 廖斌 | E8: 18000 | F8: 1440 | G8: 360 | H8: 36 | I8: 1080 | J8: 5000 | K8: 7916 | L8: 302.52 | M8: 45992 | N8: =K8-F8-G8-H8-I8-J8 -> 0
A9: 8 | B9: 创想悦动 | C9: SCX00008 | D9: 刘奎廷 | E9: 30000 | F9: 2203.92 | G9: 600 | H9: 60 | I9: 1800 | J9: 5000 | K9: 9663.92 | L9: 610.08 | M9: 45992 | N9: =K9-F9-G9-H9-I9-J9 -> 0 | Q9: =Q5-Q7 -> 0 | R9: =R5-R7 -> 0 | S9: =S5-S7 -> 0
A10: 9 | B10: 创想悦动 | C10: SCX00009 | D10: 刘文峰 | E10: 32000 | F10: 2203.92 | G10: 640 | H10: 64 | I10: 1920 | J10: 5000 | K10: 9827.92 | L10: 665.16 | M10: 45992 | N10: =K10-F10-G10-H10-I10-J10 -> 0
A11: 10 | B11: 创想悦动 | C11: SCX00010 | D11: 冯金玉 | E11: 36000 | F11: 2203.92 | G11: 673.32 | H11: 72 | I11: 2160 | J11: 5000 | K11: 10109.24 | L11: 776.72 | M11: 45992 | N11: =K11-F11-G11-H11-I11-J11 -> 0
A12: 11 | B12: 创想悦动 | C12: SCX00011 | D12: 孙志伟 | E12: 30000 | F12: 2203.92 | G12: 600 | H12: 60 | I12: 1800 | J12: 5000 | K12: 9663.92 | L12: 610.08 | M12: 45992 | N12: =K12-F12-G12-H12-I12-J12 -> 0
A13: 12 | B13: 创想悦动 | C13: SCX00012 | D13: 张磊 | E13: 30000 | F13: 2203.92 | G13: 600 | H13: 60 | I13: 1800 | J13: 5000 | K13: 9663.92 | L13: 610.08 | M13: 45992 | N13: =K13-F13-G13-H13-I13-J13 -> 0
A14: 13 | B14: 创想悦动 | C14: SCX00013 | D14: 刘玉玺 | E14: 36000 | F14: 2203.92 | G14: 673.32 | H14: 72 | I14: 2160 | J14: 5000 | K14: 10109.24 | L14: 776.72 | M14: 45992 | N14: =K14-F14-G14-H14-I14-J14 -> 0
A15: 14 | B15: 创想悦动 | C15: SCX00014 | D15: 杨东升 | E15: 20000 | F15: 1600 | G15: 400 | H15: 40 | I15: 1200 | J15: 5000 | K15: 8240 | L15: 352.8 | M15: 45992 | N15: =K15-F15-G15-H15-I15-J15 -> 0
A16: 15 | B16: 创想悦动 | C16: SCX00015 | D16: 陈曦 | E16: 25000 | F16: 2000 | G16: 500 | H16: 50 | I16: 1500 | J16: 5000 | K16: 9050 | L16: 478.5 | M16: 45992 | N16: =K16-F16-G16-H16-I16-J16 -> 0
A17: 16 | B17: 创想悦动 | C17: SCX00016 | D17: 胡豪 | E17: 23000 | F17: 1840 | G17: 460 | H17: 46 | I17: 1380 | J17: 5000 | K17: 8726 | L17: 428.22 | M17: 45992 | N17: =K17-F17-G17-H17-I17-J17 -> 0
A18: 17 | B18: 创想悦动 | C18: SCX00017 | D18: 谢华明 | E18: 20000 | F18: 1600 | G18: 400 | H18: 40 | I18: 1200 | J18: 5000 | K18: 8240 | L18: 352.8 | M18: 45992 | N18: =K18-F18-G18-H18-I18-J18 -> 0
A19: 18 | B19: 创想悦动 | C19: SCX00018 | D19: 郑琦 | E19: 22000 | F19: 1760 | G19: 440 | H19: 44 | I19: 1320 | J19: 5000 | K19: 8564 | L19: 403.08 | M19: 45992 | N19: =K19-F19-G19-H19-I19-J19 -> 0
A20: 19 | B20: 创想悦动 | C20: SCX00019 | D20: 张文文 | E20: 15000 | F20: 1200 | G20: 300 | H20: 30 | I20: 900 | J20: 5000 | K20: 7430 | L20: 227.1 | M20: 45992 | N20: =K20-F20-G20-H20-I20-J20 -> 0
A21: 20 | B21: 创想悦动 | C21: SCX00021 | D21: 刘禹豪 | E21: 25000 | F21: 2000 | G21: 500 | H21: 50 | I21: 1500 | J21: 5000 | K21: 9050 | L21: 478.5 | M21: 45992 | N21: =K21-F21-G21-H21-I21-J21 -> 0
... A48: 1 | B48: 创想悦动 | C48: SCX00001 | D48: 刘丹 | E48: 50000 | F48: 2203.92 | G48: 672.66 | H48: 88.53 | I48: 2655.9 | J48: 5000 | K48: 10621.01 | L48: 3937.9 | M48: 46023 | N48: =K48-F48-G48-H48-I48-J48 -> 0
A49: 2 | B49: 创想悦动 | C49: SCX00002 | D49: 李奕佳 | E49: 14000 | F49: 1120 | G49: 280 | H49: 28 | I49: 840 | J49: 5000 | K49: 7268 | L49: 111.96 | M49: 46023 | N49: =K49-F49-G49-H49-I49-J49 -> 0 | Q49: 应付工资 | R49: 本月合计扣除 | S49: 已交个人所得税
A50: 3 | B50: 创想悦动 | C50: SCX00003 | D50: 申华 | E50: 48850.57 | F50: 2203.92 | G50: 672.66 | H50: 88.53 | I50: 2655.9 | J50: 5000 | K50: 10621.01 | L50: 3822.96 | M50: 46023 | N50: =K50-F50-G50-H50-I50-J50 -> 0 | Q50: =SUM(E48:E95) -> 1171986.4 | R50: =SUM(K48:K95) -> 404864.82 | S50: =SUM(L48:L95) -> 44540.48
A51: 4 | B51: 创想悦动 | C51: SCX00004 | D51: 杨晓波 | E51: 48000 | F51: 2203.92 | G51: 672.66 | H51: 88.53 | I51: 2655.9 | J51: 5000 | K51: 10621.01 | L51: 3737.9 | M51: 46023 | N51: =K51-F51-G51-H51-I51-J51 -> 0
A52: 5 | B52: 创想悦动 | C52: SCX00005 | D52: 杨振 | E52: 45000 | F52: 2203.92 | G52: 672.66 | H52: 88.53 | I52: 2655.9 | J52: 5000 | K52: 10621.01 | L52: 3324.38 | M52: 46023 | N52: =K52-F52-G52-H52-I52-J52 -> 0 | Q52: 1171986.4 | R52: 404864.82 | S52: 44540.48
A53: 6 | B53: 创想悦动 | C53: SCX00006 | D53: 蔡昕宇 | E53: 35000 | F53: 0 | G53: 0 | H53: 0 | I53: 0 | J53: 5000 | K53: 5000 | L53: 2580 | M53: 46023 | N53: =K53-F53-G53-H53-I53-J53 -> 0
A54: 7 | B54: 创想悦动 | C54: SCX00007 | D54: 廖斌 | E54: 18000 | F54: 1440 | G54: 360 | H54: 36 | I54: 1080 | J54: 5000 | K54: 7916 | L54: 302.52 | M54: 46023 | N54: =K54-F54-G54-H54-I54-J54 -> 0 | Q54: =Q50-Q52 -> 0 | R54: =R50-R52 -> 0 | S54: =S50-S52 -> 0
A55: 8 | B55: 创想悦动 | C55: SCX00008 | D55: 刘奎廷 | E55: 30000 | F55: 2203.92 | G55: 600 | H55: 60 | I55: 1800 | J55: 5000 | K55: 9663.92 | L55: 937.14 | M55: 46023 | N55: =K55-F55-G55-H55-I55-J55 -> 0
A56: 9 | B56: 创想悦动 | C56: SCX00009 | D56: 刘文峰 | E56: 32000 | F56: 2203.92 | G56: 640 | H56: 64 | I56: 1920 | J56: 5000 | K56: 9827.92 | L56: 1249.26 | M56: 46023 | N56: =K56-F56-G56-H56-I56-J56 -> 0
A57: 10 | B57: 创想悦动 | C57: SCX00010 | D57: 冯金玉 | E57: 36000 | F57: 2203.92 | G57: 672.66 | H57: 72 | I57: 2160 | J57: 5000 | K57: 10108.58 | L57: 1881.5 | M57: 46023 | N57: =K57-F57-G57-H57-I57-J57 -> 0
A58: 11 | B58: 创想悦动 | C58: SCX00011 | D58: 孙志伟 | E58: 29089.66 | F58: 2203.92 | G58: 600 | H58: 60 | I58: 1800 | J58: 5000 | K58: 9663.92 | L58: 846.1 | M58: 46023 | N58: =K58-F58-G58-H58-I58-J58 -> 0
A59: 12 | B59: 创想悦动 | C59: SCX00012 | D59: 张磊 | E59: 30000 | F59: 2203.92 | G59: 600 | H59: 60 | I59: 1800 | J59: 5000 | K59: 9663.92 | L59: 937.14 | M59: 46023 | N59: =K59-F59-G59-H59-I59-J59 -> 0
A60: 13 | B60: 创想悦动 | C60: SCX00013 | D60: 刘玉玺 | E60: 36000 | F60: 2203.92 | G60: 672.66 | H60: 72 | I60: 2160 | J60: 5000 | K60: 10108.58 | L60: 1881.5 | M60: 46023 | N60: =K60-F60-G60-H60-I60-J60 -> 0
A61: 14 | B61: 创想悦动 | C61: SCX00014 | D61: 杨东升 | E61: 20000 | F61: 1600 | G61: 400 | H61: 40 | I61: 1200 | J61: 5000 | K61: 8240 | L61: 352.8 | M61: 46023 | N61: =K61-F61-G61-H61-I61-J61 -> 0
A62: 15 | B62: 创想悦动 | C62: SCX00015 | D62: 陈曦 | E62: 25000 | F62: 2000 | G62: 500 | H62: 50 | I62: 1500 | J62: 5000 | K62: 9050 | L62: 478.5 | M62: 46023 | N62: =K62-F62-G62-H62-I62-J62 -> 0
A63: 16 | B63: 创想悦动 | C63: SCX00016 | D63: 胡豪 | E63: 23000 | F63: 1840 | G63: 460 | H63: 46 | I63: 1380 | J63: 5000 | K63: 8726 | L63: 428.22 | M63: 46023 | N63: =K63-F63-G63-H63-I63-J63 -> 0
A64: 17 | B64: 创想悦动 | C64: SCX00017 | D64: 谢华明 | E64: 20000 | F64: 1600 | G64: 400 | H64: 40 | I64: 1200 | J64: 5000 | K64: 8240 | L64: 52.8 | M64: 46023 | N64: =K64-F64-G64-H64-I64-J64 -> 0
A65: 18 | B65: 创想悦动 | C65: SCX00018 | D65: 郑琦 | E65: 22000 | F65: 1760 | G65: 440 | H65: 44 | I65: 1320 | J65: 5000 | K65: 8564 | L65: 403.08 | M65: 46023 | N65: =K65-F65-G65-H65-I65-J65 -> 0
A66: 19 | B66: 创想悦动 | C66: SCX00019 | D66: 张文文 | E66: 15000 | F66: 1200 | G66: 300 | H66: 30 | I66: 900 | J66: 5000 | K66: 7430 | L66: 227.1 | M66: 46023 | N66: =K66-F66-G66-H66-I66-J66 -> 0
... A95: 48 | B95: 创想悦动 | C95: SCX00052 | D95: 李安迪 | E95: 3218.39 | F95: 0 | G95: 0 | H95: 0 | I95: 0 | J95: 5000 | K95: 5000 | L95: 0 | M95: 46023 | N95: =K95-F95-G95-H95-I95-J95 -> 0
A96: 1 | B96: 创想悦动 | C96: SCX00001 | D96: 刘丹 | E96: 50100 | F96: 2203.92 | G96: 672.66 | H96: 88.53 | I96: 2655.9 | J96: 5000 | K96: 10621.01 | L96: 3947.9 | M96: 46054 | N96: =K96-F96-G96-H96-I96-J96 -> 0 | Q96: 应付工资 | R96: 本月合计扣除 | S96: 已交个人所得税
A97: 2 | B97: 创想悦动 | C97: SCX00002 | D97: 李奕佳 | E97: 14100 | F97: 1120 | G97: 280 | H97: 28 | I97: 840 | J97: 5000 | K97: 7268 | L97: 159.96 | M97: 46054 | N97: =K97-F97-G97-H97-I97-J97 -> 0 | Q97: =SUM(E96:E146) -> 1191912.6 | R97: =SUM(K96:K146) -> 419620.32 | S97: =SUM(L96:L146) -> 58270.84
A98: 3 | B98: 创想悦动 | C98: SCX00003 | D98: 申华 | E98: 50100 | F98: 2203.92 | G98: 672.66 | H98: 88.53 | I98: 2655.9 | J98: 5000 | K98: 10621.01 | L98: 3947.9 | M98: 46054 | N98: =K98-F98-G98-H98-I98-J98 -> 0
A99: 4 | B99: 创想悦动 | C99: SCX00004 | D99: 杨晓波 | E99: 48100 | F99: 2203.92 | G99: 672.66 | H99: 88.53 | I99: 2655.9 | J99: 5000 | K99: 10621.01 | L99: 3747.9 | M99: 46054 | N99: =K99-F99-G99-H99-I99-J99 -> 0 | Q99: 1191912.6 | R99: 419620.32 | S99: 58270.84
A100: 5 | B100: 创想悦动 | C100: SCX00005 | D100: 杨振 | E100: 45100 | F100: 2203.92 | G100: 672.66 | H100: 88.53 | I100: 2655.9 | J100: 5000 | K100: 10621.01 | L100: 3447.9 | M100: 46054 | N100: =K100-F100-G100-H100-I100-J100 -> 0
A101: 6 | B101: 创想悦动 | C101: SCX00006 | D101: 蔡昕宇 | E101: 35100 | F101: 0 | G101: 0 | H101: 0 | I101: 0 | J101: 5000 | K101: 5000 | L101: 3010 | M101: 46054 | N101: =K101-F101-G101-H101-I101-J101 -> 0 | Q101: =Q97-Q99 -> 0 | R101: =R97-R99 -> 0 | S101: =S97-S99 -> 0
A102: 7 | B102: 创想悦动 | C102: SCX00007 | D102: 廖斌 | E102: 18100 | F102: 1440 | G102: 360 | H102: 36 | I102: 1080 | J102: 5000 | K102: 7916 | L102: 305.52 | M102: 46054 | N102: =K102-F102-G102-H102-I102-J102 -> 0
A103: 8 | B103: 创想悦动 | C103: SCX00008 | D103: 刘奎廷 | E103: 30100 | F103: 2203.92 | G103: 600 | H103: 60 | I103: 1800 | J103: 5000 | K103: 9663.92 | L103: 2043.6 | M103: 46054 | N103: =K103-F103-G103-H103-I103-J103 -> 0
A104: 9 | B104: 创想悦动 | C104: SCX00009 | D104: 刘文峰 | E104: 32100 | F104: 2203.92 | G104: 640 | H104: 64 | I104: 1920 | J104: 5000 | K104: 9827.92 | L104: 2227.2 | M104: 46054 | N104: =K104-F104-G104-H104-I104-J104 -> 0
A105: 10 | B105: 创想悦动 | C105: SCX00010 | D105: 冯金玉 | E105: 36100 | F105: 2203.92 | G105: 672.66 | H105: 72 | I105: 2160 | J105: 5000 | K105: 10108.58 | L105: 499.14 | M105: 46054 | N105: =K105-F105-G105-H105-I105-J105 -> 0
A106: 11 | B106: 创想悦动 | C106: SCX00011 | D106: 孙志伟 | E106: 15172.41 | F106: 0 | G106: 0 | H106: 0 | I106: 0 | J106: 5000 | K106: 5000 | L106: 1017.24 | M106: 46054 | N106: =K106-F106-G106-H106-I106-J106 -> 0
A107: 12 | B107: 创想悦动 | C107: SCX00012 | D107: 张磊 | E107: 30100 | F107: 2203.92 | G107: 600 | H107: 60 | I107: 1800 | J107: 5000 | K107: 9663.92 | L107: 2043.6 | M107: 46054 | N107: =K107-F107-G107-H107-I107-J107 -> 0
A108: 13 | B108: 创想悦动 | C108: SCX00013 | D108: 刘玉玺 | E108: 16551.72 | F108: 0 | G108: 0 | H108: 0 | I108: 0 | J108: 5000 | K108: 5000 | L108: 1155.17 | M108: 46054 | N108: =K108-F108-G108-H108-I108-J108 -> 0
A109: 14 | B109: 创想悦动 | C109: SCX00014 | D109: 杨东升 | E109: 20100 | F109: 1600 | G109: 400 | H109: 40 | I109: 1200 | J109: 5000 | K109: 8240 | L109: 355.8 | M109: 46054 | N109: =K109-F109-G109-H109-I109-J109 -> 0
A110: 15 | B110: 创想悦动 | C110: SCX00015 | D110: 陈曦 | E110: 25100 | F110: 2000 | G110: 500 | H110: 50 | I110: 1500 | J110: 5000 | K110: 9050 | L110: 1318 | M110: 46054 | N110: =K110-F110-G110-H110-I110-J110 -> 0
A111: 16 | B111: 创想悦动 | C111: SCX00016 | D111: 胡豪 | E111: 22782.76 | F111: 1840 | G111: 460 | H111: 46 | I111: 1380 | J111: 5000 | K111: 8726 | L111: 884.04 | M111: 46054 | N111: =K111-F111-G111-H111-I111-J111 -> 0
A112: 17 | B112: 创想悦动 | C112: SCX00017 | D112: 谢华明 | E112: 20100 | F112: 1600 | G112: 400 | H112: 40 | I112: 1200 | J112: 5000 | K112: 8240 | L112: 205.8 | M112: 46054 | N112: =K112-F112-G112-H112-I112-J112 -> 0
A113: 18 | B113: 创想悦动 | C113: SCX00018 | D113: 郑琦 | E113: 22100 | F113: 1760 | G113: 440 | H113: 44 | I113: 1320 | J113: 5000 | K113: 8564 | L113: 714.64 | M113: 46054 | N113: =K113-F113-G113-H113-I113-J113 -> 0
... A146: 51 | B146: 创想悦动 | C146: SCX00054 | D146: 李杨 | E146: 2413.79 | F146: 0 | G146: 0 | H146: 0 | I146: 0 | J146: 5000 | K146: 5000 | L146: 0 | M146: 46054 | N146: =K146-F146-G146-H146-I146-J146 -> 0
A147: 1 | B147: 创想悦动 | C147: SCX00001 | D147: 刘丹 | E147: 50000 | F147: 2203.92 | G147: 672.66 | H147: 88.53 | I147: 2655.9 | J147: 5000 | K147: 10621.01 | L147: 5299.43 | M147: 46082 | N147: =K147-F147-G147-H147-I147-J147 -> 0 | Q147: 应付工资 | R147: 本月合计扣除 | S147: 已交个人所得税
A148: 2 | B148: 创想悦动 | C148: SCX00002 | D148: 李奕佳 | E148: 14000 | F148: 1120 | G148: 280 | H148: 28 | I148: 840 | J148: 5000 | K148: 7268 | L148: 156.96 | M148: 46082 | N148: =K148-F148-G148-H148-I148-J148 -> 0 | Q148: =SUM(E147:E198) -> 1205473.4 | R148: =SUM(K147:K198) -> 429666.9 | S148: =SUM(L147:L198) -> 70205.81
A149: 3 | B149: 创想悦动 | C149: SCX00003 | D149: 申华 | E149: 50000 | F149: 2203.92 | G149: 672.66 | H149: 88.53 | I149: 2655.9 | J149: 5000 | K149: 10621.01 | L149: 5184.48 | M149: 46082 | N149: =K149-F149-G149-H149-I149-J149 -> 0
A150: 4 | B150: 创想悦动 | C150: SCX00004 | D150: 杨晓波 | E150: 48000 | F150: 2203.92 | G150: 672.66 | H150: 88.53 | I150: 2655.9 | J150: 5000 | K150: 10621.01 | L150: 4299.43 | M150: 46082 | N150: =K150-F150-G150-H150-I150-J150 -> 0 | Q150: 1205473.4 | R150: 429666.9 | S150: 70205.81
A151: 5 | B151: 创想悦动 | C151: SCX00005 | D151: 杨振 | E151: 45000 | F151: 2203.92 | G151: 672.66 | H151: 88.53 | I151: 2655.9 | J151: 5000 | K151: 10621.01 | L151: 3437.9 | M151: 46082 | N151: =K151-F151-G151-H151-I151-J151 -> 0
A152: 6 | B152: 创想悦动 | C152: SCX00006 | D152: 蔡昕宇 | E152: 35000 | F152: 0 | G152: 0 | H152: 0 | I152: 0 | J152: 5000 | K152: 5000 | L152: 3000 | M152: 46082 | N152: =K152-F152-G152-H152-I152-J152 -> 0 | Q152: =Q148-Q150 -> 0 | R152: =R148-R150 -> 0 | S152: =S148-S150 -> 0
A153: 7 | B153: 创想悦动 | C153: SCX00007 | D153: 廖斌 | E153: 18000 | F153: 1440 | G153: 360 | H153: 36 | I153: 1080 | J153: 5000 | K153: 7916 | L153: 613.04 | M153: 46082 | N153: =K153-F153-G153-H153-I153-J153 -> 0
A154: 8 | B154: 创想悦动 | C154: SCX00008 | D154: 刘奎廷 | E154: 30000 | F154: 2203.92 | G154: 600 | H154: 60 | I154: 1800 | J154: 5000 | K154: 9663.92 | L154: 2033.61 | M154: 46082 | N154: =K154-F154-G154-H154-I154-J154 -> 0
A155: 9 | B155: 创想悦动 | C155: SCX00009 | D155: 刘文峰 | E155: 32000 | F155: 2203.92 | G155: 640 | H155: 64 | I155: 1920 | J155: 5000 | K155: 9827.92 | L155: 2217.21 | M155: 46082 | N155: =K155-F155-G155-H155-I155-J155 -> 0
A156: 10 | B156: 创想悦动 | C156: SCX00010 | D156: 冯金玉 | E156: 40965.52 | F156: 2203.92 | G156: 672.66 | H156: 72 | I156: 2160 | J156: 5000 | K156: 10108.58 | L156: 2385.69 | M156: 46082 | N156: =K156-F156-G156-H156-I156-J156 -> 0
A157: 11 | B157: 创想悦动 | C157: SCX00012 | D157: 张磊 | E157: 30000 | F157: 2203.92 | G157: 600 | H157: 60 | I157: 1800 | J157: 5000 | K157: 9663.92 | L157: 2033.61 | M157: 46082 | N157: =K157-F157-G157-H157-I157-J157 -> 0
A158: 12 | B158: 创想悦动 | C158: SCX00014 | D158: 杨东升 | E158: 20000 | F158: 1600 | G158: 400 | H158: 40 | I158: 1200 | J158: 5000 | K158: 8240 | L158: 1132.6 | M158: 46082 | N158: =K158-F158-G158-H158-I158-J158 -> 0
A159: 13 | B159: 创想悦动 | C159: SCX00015 | D159: 陈曦 | E159: 25750 | F159: 2000 | G159: 500 | H159: 50 | I159: 1500 | J159: 5000 | K159: 9050 | L159: 1670 | M159: 46082 | N159: =K159-F159-G159-H159-I159-J159 -> 0
A160: 14 | B160: 创想悦动 | C160: SCX00016 | D160: 胡豪 | E160: 23000 | F160: 1840 | G160: 460 | H160: 46 | I160: 1380 | J160: 5000 | K160: 8726 | L160: 1427.4 | M160: 46082 | N160: =K160-F160-G160-H160-I160-J160 -> 0
A161: 15 | B161: 创想悦动 | C161: SCX00017 | D161: 谢华明 | E161: 20000 | F161: 1600 | G161: 400 | H161: 40 | I161: 1200 | J161: 5000 | K161: 8240 | L161: 202.8 | M161: 46082 | N161: =K161-F161-G161-H161-I161-J161 -> 0
A162: 16 | B162: 创想悦动 | C162: SCX00018 | D162: 郑琦 | E162: 22000 | F162: 1760 | G162: 440 | H162: 44 | I162: 1320 | J162: 5000 | K162: 8564 | L162: 1343.6 | M162: 46082 | N162: =K162-F162-G162-H162-I162-J162 -> 0
A163: 17 | B163: 创想悦动 | C163: SCX00019 | D163: 张文文 | E163: 15000 | F163: 1200 | G163: 300 | H163: 30 | I163: 900 | J163: 5000 | K163: 7430 | L163: 227.1 | M163: 46082 | N163: =K163-F163-G163-H163-I163-J163 -> 0
A164: 18 | B164: 创想悦动 | C164: SCX00021 | D164: 刘禹豪 | E164: 25000 | F164: 2000 | G164: 500 | H164: 50 | I164: 1500 | J164: 5000 | K164: 9050 | L164: 1595 | M164: 46082 | N164: =K164-F164-G164-H164-I164-J164 -> 0
... A198: 52 | B198: 创想悦动 | C198: SCX00059 | D198: 肖婷 | E198: 689.66 | F198: 0 | G198: 0 | H198: 0 | I198: 0 | J198: 5000 | K198: 5000 | L198: 0 | M198: 46082 | N198: =K198-F198-G198-H198-I198-J198 -> 0
A199: 1 | B199: 创想悦动 | C199: SCX00001 | D199: 刘丹 | E199: 50000 | F199: 2203.92 | G199: 672.66 | H199: 88.53 | I199: 2655.9 | J199: 5000 | K199: 10621.01 | L199: 7875.8 | M199: 46113 | N199: =K199-F199-G199-H199-I199-J199 -> 0 | Q199: 应付工资 | R199: 本月合计扣除 | S199: 已交个人所得税
A200: 2 | B200: 创想悦动 | C200: SCX00002 | D200: 李奕佳 | E200: 16000 | F200: 1120 | G200: 280 | H200: 28 | I200: 840 | J200: 5000 | K200: 7268 | L200: 216.96 | M200: 46113 | N200: =K200-F200-G200-H200-I200-J200 -> 0 | Q200: =SUM(E199:E254) -> 1292024.1 | R200: =SUM(K199:K254) -> 463374.9 | S200: =SUM(L199:L254) -> 90960.77
A201: 3 | B201: 创想悦动 | C201: SCX00003 | D201: 申华 | E201: 50000 | F201: 2203.92 | G201: 672.66 | H201: 88.53 | I201: 2655.9 | J201: 5000 | K201: 10621.01 | L201: 7875.8 | M201: 46113 | N201: =K201-F201-G201-H201-I201-J201 -> 0
A202: 4 | B202: 创想悦动 | C202: SCX00004 | D202: 杨晓波 | E202: 48200 | F202: 2203.92 | G202: 672.66 | H202: 88.53 | I202: 2655.9 | J202: 5000 | K202: 10621.01 | L202: 7515.8 | M202: 46113 | N202: =K202-F202-G202-H202-I202-J202 -> 0 | Q202: 1292024.1 | R202: 463374.9 | S202: 90960.77
A203: 5 | B203: 创想悦动 | C203: SCX00005 | D203: 杨振 | E203: 45000 | F203: 2203.92 | G203: 672.66 | H203: 88.53 | I203: 2655.9 | J203: 5000 | K203: 10621.01 | L203: 6237.33 | M203: 46113 | N203: =K203-F203-G203-H203-I203-J203 -> 0
A204: 6 | B204: 创想悦动 | C204: SCX00006 | D204: 蔡昕宇 | E204: 38000 | F204: 0 | G204: 0 | H204: 0 | I204: 0 | J204: 5000 | K204: 5000 | L204: 4210 | M204: 46113 | N204: =K204-F204-G204-H204-I204-J204 -> 0 | Q204: =Q200-Q202 -> 0 | R204: =R200-R202 -> 0 | S204: =S200-S202 -> 0
A205: 7 | B205: 创想悦动 | C205: SCX00007 | D205: 廖斌 | E205: 18000 | F205: 1440 | G205: 360 | H205: 36 | I205: 1080 | J205: 5000 | K205: 7916 | L205: 1008.4 | M205: 46113 | N205: =K205-F205-G205-H205-I205-J205 -> 0
A206: 8 | B206: 创想悦动 | C206: SCX00008 | D206: 刘奎廷 | E206: 30000 | F206: 2203.92 | G206: 600 | H206: 60 | I206: 1800 | J206: 5000 | K206: 9663.92 | L206: 2033.61 | M206: 46113 | N206: =K206-F206-G206-H206-I206-J206 -> 0
A207: 9 | B207: 创想悦动 | C207: SCX00009 | D207: 刘文峰 | E207: 32000 | F207: 2203.92 | G207: 640 | H207: 64 | I207: 1920 | J207: 5000 | K207: 9827.92 | L207: 2217.21 | M207: 46113 | N207: =K207-F207-G207-H207-I207-J207 -> 0
A208: 10 | B208: 创想悦动 | C208: SCX00012 | D208: 张磊 | E208: 30000 | F208: 2203.92 | G208: 600 | H208: 60 | I208: 1800 | J208: 5000 | K208: 9663.92 | L208: 2033.61 | M208: 46113 | N208: =K208-F208-G208-H208-I208-J208 -> 0
A209: 11 | B209: 创想悦动 | C209: SCX00014 | D209: 杨东升 | E209: 20000 | F209: 1600 | G209: 400 | H209: 40 | I209: 1200 | J209: 5000 | K209: 8240 | L209: 1176 | M209: 46113 | N209: =K209-F209-G209-H209-I209-J209 -> 0
A210: 12 | B210: 创想悦动 | C210: SCX00015 | D210: 陈曦 | E210: 25000 | F210: 2000 | G210: 500 | H210: 50 | I210: 1500 | J210: 5000 | K210: 9050 | L210: 1595 | M210: 46113 | N210: =K210-F210-G210-H210-I210-J210 -> 0
A211: 13 | B211: 创想悦动 | C211: SCX00016 | D211: 胡豪 | E211: 23200 | F211: 1840 | G211: 460 | H211: 46 | I211: 1380 | J211: 5000 | K211: 8726 | L211: 1447.4 | M211: 46113 | N211: =K211-F211-G211-H211-I211-J211 -> 0
A212: 14 | B212: 创想悦动 | C212: SCX00017 | D212: 谢华明 | E212: 21200 | F212: 1600 | G212: 400 | H212: 40 | I212: 1200 | J212: 5000 | K212: 8240 | L212: 238.8 | M212: 46113 | N212: =K212-F212-G212-H212-I212-J212 -> 0
A213: 15 | B213: 创想悦动 | C213: SCX00018 | D213: 郑琦 | E213: 24000 | F213: 1760 | G213: 440 | H213: 44 | I213: 1320 | J213: 5000 | K213: 8564 | L213: 1543.6 | M213: 46113 | N213: =K213-F213-G213-H213-I213-J213 -> 0
A214: 16 | B214: 创想悦动 | C214: SCX00019 | D214: 张文文 | E214: 16200 | F214: 1200 | G214: 300 | H214: 30 | I214: 900 | J214: 5000 | K214: 7430 | L214: 483.6 | M214: 46113 | N214: =K214-F214-G214-H214-I214-J214 -> 0
A215: 17 | B215: 创想悦动 | C215: SCX00021 | D215: 刘禹豪 | E215: 27200 | F215: 2000 | G215: 500 | H215: 50 | I215: 1500 | J215: 5000 | K215: 9050 | L215: 1815 | M215: 46113 | N215: =K215-F215-G215-H215-I215-J215 -> 0
A216: 18 | B216: 创想悦动 | C216: SCX00022 | D216: 刘锦翔 | E216: 14000 | F216: 1040 | G216: 260 | H216: 26 | I216: 780 | J216: 5000 | K216: 7106 | L216: 161.82 | M216: 46113 | N216: =K216-F216-G216-H216-I216-J216 -> 0
... A254: 56 | B254: 创想悦动 | C254: SCX00065 | D254: 张哲 | E254: 6436.78 | F254: 0 | G254: 0 | H254: 0 | I254: 0 | J254: 5000 | K254: 5000 | L254: 43.1 | M254: 46113 | N254: =K254-F254-G254-H254-I254-J254 -> 0
A255: 1 | B255: 创想悦动 | C255: SCX00001 | D255: 刘丹 | E255: 50200 | F255: 2203.92 | G255: 672.66 | H255: 88.53 | I255: 2655.9 | J255: 5000 | K255: 10621.01 | L255: 7915.8 | M255: 46143 | N255: =K255-F255-G255-H255-I255-J255 -> 0 | Q255: 应付工资 | R255: 本月合计扣除 | S255: 已交个人所得税
A256: 2 | B256: 创想悦动 | C256: SCX00002 | D256: 李奕佳 | E256: 16000 | F256: 1440 | G256: 360 | H256: 36 | I256: 840 | J256: 5000 | K256: 7676 | L256: 204.72 | M256: 46143 | N256: =K256-F256-G256-H256-I256-J256 -> 0 | Q256: =SUM(E255:E319) -> 1396495.4 | R256: =SUM(K255:K319) -> 521949.42 | S256: =SUM(L255:L319) -> 101716.62
...
